Workbook
Name budget: 'Budget Dashboard'!$L1
Name budget_range: 'Budget Dashboard'!$Q1
Name budget_rank: 'Budget Dashboard'!$R1
Name cc_budget: Calculations!$K1
Name cc_delta: Calculations!$L1
Name cc_in_focus: Calculations!$G1
Name cc_month_number: Calculations!$F1
Name cc_show_remaining_budget: Calculations!$I1
Name cc_show_type: Calculations!$H1
Name cc_tracked: Calculations!$J1
Name cc_type: Calculations!$E1
Name combined_rank: 'Budget Dashboard'!$S1
Name combined_rank_norm: 'Budget Dashboard'!$U1
Name combined_rank_norm_run_range: 'Budget Dashboard'!$V1
Name combined_rank_range: 'Budget Dashboard'!$T1
Name combined_rank_unique: 'Budget Dashboard'!$W1
Name current_date: TODAY()
Name expenses_header_row: ROW(Expenses[[#Headers],[Expenses]])
Name expenses_max_row: MAX(ROW(Expenses[]))
Name expenses_min_row: MIN(ROW(Expenses[]))
Name expenses_total_row: ROW('Budget Planning'!$C$36)
Name header_row_id: 'Budget Dashboard'!$D1
Name income_header_row: ROW(Income[[#Headers],[Income]])
Name income_max_row: MAX(ROW(Income[]))
Name income_min_row: MIN(ROW(Income[]))
Name income_total_row: ROW('Budget Planning'!$C$20)
Name is_category: 'Budget Dashboard'!$F1
Name is_empty: 'Budget Dashboard'!$H1
Name is_header: 'Budget Dashboard'!$E1
Name is_total: 'Budget Dashboard'!$G1
Name item: 'Budget Dashboard'!$J1
Name out_budget: 'Budget Dashboard'!$AA1
Name out_percentage_completed: 'Budget Dashboard'!$AB1
Name out_tracked: 'Budget Dashboard'!$Z1
Name row_id: 'Budget Dashboard'!$C1
Name savings_header_row: ROW(Savings[[#Headers],[Savings]])
Name savings_max_row: MAX(ROW(Savings[]))
Name savings_min_row: MIN(ROW(Savings[]))
Name savings_rate_calculation_type: Settings!$E$22
Name savings_total_row: ROW('Budget Planning'!$C$49)
Name selected_period: Calculations!$E$20
Name selected_period_display: Calculations!$E$21
Name selected_year: Calculations!$E$19
Name shift_late_income_starting_day: Settings!$E$18
Name shift_late_income_status: Settings!$E$16
Name sort_max_row: 'Budget Dashboard'!$N1
Name sort_min_row: 'Budget Dashboard'!$M1
Name starting_year: Settings!$E$8
Name tracked: 'Budget Dashboard'!$K1
Name tracked_range: 'Budget Dashboard'!$O1
Name tracker_rank: 'Budget Dashboard'!$P1
Name type: 'Budget Dashboard'!$I1

Sheet Settings
C6: General
D8: Starting Year: | E8: 2025 | G8: Set the starting year(yyyy) once at the beginning and do not change it again.
C12: Budget Tracking & Dashboard
D14: Late Monthly Income:
D16: Shift late income? | E16: Yes(Active) | G16: Activate this option to treat late income received on or after a certain day of the month as income for the next month. This is especially recommended in case you receive your montly paycheck towards the end of the month and prefer to consider this income as the disposable income for the next month.
D18: Starting on day X in month: | E18: 20
D20: KPI Calculation in Dashboard
D22: Savings Rate as % of Income: | E22: % allocated to Savings | G22: Choose how you want the savings rate(SR) to be calculated in the dashboard KPI tiles:
G23: 1) Active Option(% allocated to Savings): SR = Savings / Income
G24: 2) Passive Option(% not allocated to Expenses) SR = (Income - Expenses) / Income

Sheet Budget Planning
C5: Define starting year in Settings → | E5: 2025 | S5: =E5+1 -> 2026 | AG5: =S5+1 -> 2027 | AU5: =AG5+1 -> 2028 | BI5: =AU5+1 -> 2029 | BW5: =BI5+1 -> 2030 | CK5: =BW5+1 -> 2031 | CY5: =CK5+1 -> 2032 | DM5: =CY5+1 -> 2033 | EA5: =DM5+1 -> 2034 | EO5: =EA5+1 -> 2035
E6: =IF(E7=0, "Jan ✓", "Jan") -> Jan ✓ | F6: =IF(F7=0, "Feb ✓", "Feb") -> Feb ✓ | G6: =IF(G7=0, "Mar ✓", "Mar") -> Mar ✓ | H6: =IF(H7=0, "Apr ✓", "Apr") -> Apr ✓ | I6: =IF(I7=0, "May ✓", "May") -> May ✓ | J6: =IF(J7=0, "June ✓", "June") -> June ✓ | K6: =IF(K7=0, "July ✓", "July") -> July ✓ | L6: =IF(L7=0, "Aug ✓", "Aug") -> Aug ✓ | M6: =IF(M7=0, "Sep ✓", "Sep") -> Sep ✓ | N6: =IF(N7=0, "Oct ✓", "Oct") -> Oct ✓ | O6: =IF(O7=0, "Nov ✓", "Nov") -> Nov ✓ | P6: =IF(P7=0, "Dec ✓", "Dec") -> Dec ✓ | Q6: =IF(Q7=0, "Total ✓", "Total") -> Total ✓ | S6: =IF(S7=0, "Jan ✓", "Jan") -> Jan ✓ | T6: =IF(T7=0, "Feb ✓", "Feb") -> Feb ✓ | U6: =IF(U7=0, "Mar ✓", "Mar") -> Mar ✓ | V6: =IF(V7=0, "Apr ✓", "Apr") -> Apr ✓ | W6: =IF(W7=0, "May ✓", "May") -> May ✓ | X6: =IF(X7=0, "June ✓", "June") -> June ✓ | Y6: =IF(Y7=0, "July ✓", "July") -> July ✓ | Z6: =IF(Z7=0, "Aug ✓", "Aug") -> Aug ✓ | AA6: =IF(AA7=0, "Sep ✓", "Sep") -> Sep ✓ | AB6: =IF(AB7=0, "Oct ✓", "Oct") -> Oct ✓ | AC6: =IF(AC7=0, "Nov ✓", "Nov") -> Nov ✓ | AD6: =IF(AD7=0, "Dec ✓", "Dec") -> Dec ✓ | AE6: =IF(AE7=0, "Total ✓", "Total") -> Total ✓ | AG6: =IF(AG7=0, "Jan ✓", "Jan") -> Jan ✓ | AH6: =IF(AH7=0, "Feb ✓", "Feb") -> Feb ✓ | AI6: =IF(AI7=0, "Mar ✓", "Mar") -> Mar ✓ | AJ6: =IF(AJ7=0, "Apr ✓", "Apr") -> Apr ✓ | AK6: =IF(AK7=0, "May ✓", "May") -> May ✓ | AL6: =IF(AL7=0, "June ✓", "June") -> June ✓ | AM6: =IF(AM7=0, "July ✓", "July") -> July ✓ | AN6: =IF(AN7=0, "Aug ✓", "Aug") -> Aug ✓ | AO6: =IF(AO7=0, "Sep ✓", "Sep") -> Sep ✓ | AP6: =IF(AP7=0, "Oct ✓", "Oct") -> Oct ✓ | AQ6: =IF(AQ7=0, "Nov ✓", "Nov") -> Nov ✓ | AR6: =IF(AR7=0, "Dec ✓", "Dec") -> Dec ✓ | AS6: =IF(AS7=0, "Total ✓", "Total") -> Total ✓ | AU6: =IF(AU7=0, "Jan ✓", "Jan") -> Jan ✓ | AV6: =IF(AV7=0, "Feb ✓", "Feb") -> Feb ✓ | AW6: =IF(AW7=0, "Mar ✓", "Mar") -> Mar ✓ | AX6: =IF(AX7=0, "Apr ✓", "Apr") -> Apr ✓ | AY6: =IF(AY7=0, "May ✓", "May") -> May ✓ | AZ6: =IF(AZ7=0, "June ✓", "June") -> June ✓ | BA6: =IF(BA7=0, "July ✓", "July") -> July ✓ | BB6: =IF(BB7=0, "Aug ✓", "Aug") -> Aug ✓ | BC6: =IF(BC7=0, "Sep ✓", "Sep") -> Sep ✓ | BD6: =IF(BD7=0, "Oct ✓", "Oct") -> Oct ✓ | BE6: =IF(BE7=0, "Nov ✓", "Nov") -> Nov ✓ | BF6: =IF(BF7=0, "Dec ✓", "Dec") -> Dec ✓ | BG6: =IF(BG7=0, "Total ✓", "Total") -> Total ✓ | BI6: =IF(BI7=0, "Jan ✓", "Jan") -> Jan ✓ | BJ6: =IF(BJ7=0, "Feb ✓", "Feb") -> Feb ✓ | BK6: =IF(BK7=0, "Mar ✓", "Mar") -> Mar ✓ | BL6: =IF(BL7=0, "Apr ✓", "Apr") -> Apr ✓ | BM6: =IF(BM7=0, "May ✓", "May") -> May ✓ | BN6: =IF(BN7=0, "June ✓", "June") -> June ✓ | BO6: =IF(BO7=0, "July ✓", "July") -> July ✓ | BP6: =IF(BP7=0, "Aug ✓", "Aug") -> Aug ✓ | BQ6: =IF(BQ7=0, "Sep ✓", "Sep") -> Sep ✓ | BR6: =IF(BR7=0, "Oct ✓", "Oct") -> Oct ✓ | BS6: =IF(BS7=0, "Nov ✓", "Nov") -> Nov ✓ | BT6: =IF(BT7=0, "Dec ✓", "Dec") -> Dec ✓ | BU6: =IF(BU7=0, "Total ✓", "Total") -> Total ✓ | BW6: =IF(BW7=0, "Jan ✓", "Jan") -> Jan ✓ | BX6: =IF(BX7=0, "Feb ✓", "Feb") -> Feb ✓ | BY6: =IF(BY7=0, "Mar ✓", "Mar") -> Mar ✓ | BZ6: =IF(BZ7=0, "Apr ✓", "Apr") -> Apr ✓ | CA6: =IF(CA7=0, "May ✓", "May") -> May ✓ | CB6: =IF(CB7=0, "June ✓", "June") -> June ✓ | CC6: =IF(CC7=0, "July ✓", "July") -> July ✓ | CD6: =IF(CD7=0, "Aug ✓", "Aug") -> Aug ✓ | CE6: =IF(CE7=0, "Sep ✓", "Sep") -> Sep ✓ | CF6: =IF(CF7=0, "Oct ✓", "Oct") -> Oct ✓ | CG6: =IF(CG7=0, "Nov ✓", "Nov") -> Nov ✓ | CH6: =IF(CH7=0, "Dec ✓", "Dec") -> Dec ✓ | CI6: =IF(CI7=0, "Total ✓", "Total") -> Total ✓ | CK6: =IF(CK7=0, "Jan ✓", "Jan") -> Jan ✓ | CL6: =IF(CL7=0, "Feb ✓", "Feb") -> Feb ✓ | CM6: =IF(CM7=0, "Mar ✓", "Mar") -> Mar ✓ | CN6: =IF(CN7=0, "Apr ✓", "Apr") -> Apr ✓ | CO6: =IF(CO7=0, "May ✓", "May") -> May ✓ | CP6: =IF(CP7=0, "June ✓", "June") -> June ✓ | CQ6: =IF(CQ7=0, "July ✓", "July") -> July ✓ | CR6: =IF(CR7=0, "Aug ✓", "Aug") -> Aug ✓ | CS6: =IF(CS7=0, "Sep ✓", "Sep") -> Sep ✓ | CT6: =IF(CT7=0, "Oct ✓", "Oct") -> Oct ✓ | CU6: =IF(CU7=0, "Nov ✓", "Nov") -> Nov ✓ | CV6: =IF(CV7=0, "Dec ✓", "Dec") -> Dec ✓ | CW6: =IF(CW7=0, "Total ✓", "Total") -> Total ✓ | CY6: =IF(CY7=0, "Jan ✓", "Jan") -> Jan ✓ | CZ6: =IF(CZ7=0, "Feb ✓", "Feb") -> Feb ✓ | DA6: =IF(DA7=0, "Mar ✓", "Mar") -> Mar ✓ | DB6: =IF(DB7=0, "Apr ✓", "Apr") -> Apr ✓ | DC6: =IF(DC7=0, "May ✓", "May") -> May ✓ | DD6: =IF(DD7=0, "June ✓", "June") -> June ✓ | DE6: =IF(DE7=0, "July ✓", "July") -> July ✓ | DF6: =IF(DF7=0, "Aug ✓", "Aug") -> Aug ✓ | DG6: =IF(DG7=0, "Sep ✓", "Sep") -> Sep ✓ | DH6: =IF(DH7=0, "Oct ✓", "Oct") -> Oct ✓ | DI6: =IF(DI7=0, "Nov ✓", "Nov") -> Nov ✓ | DJ6: =IF(DJ7=0, "Dec ✓", "Dec") -> Dec ✓ | DK6: =IF(DK7=0, "Total ✓", "Total") -> Total ✓ | DM6: =IF(DM7=0, "Jan ✓", "Jan") -> Jan ✓ | DN6: =IF(DN7=0, "Feb ✓", "Feb") -> Feb ✓ | DO6: =IF(DO7=0, "Mar ✓", "Mar") -> Mar ✓ | DP6: =IF(DP7=0, "Apr ✓", "Apr") -> Apr ✓ | DQ6: =IF(DQ7=0, "May ✓", "May") -> May ✓ | DR6: =IF(DR7=0, "June ✓", "June") -> June ✓ | DS6: =IF(DS7=0, "July ✓", "July") -> July ✓ | DT6: =IF(DT7=0, "Aug ✓", "Aug") -> Aug ✓ | DU6: =IF(DU7=0, "Sep ✓", "Sep") -> Sep ✓ | DV6: =IF(DV7=0, "Oct ✓", "Oct") -> Oct ✓ | DW6: =IF(DW7=0, "Nov ✓", "Nov") -> Nov ✓ | DX6: =IF(DX7=0, "Dec ✓", "Dec") -> Dec ✓ | DY6: =IF(DY7=0, "Total ✓", "Total") -> Total ✓ | EA6: =IF(EA7=0, "Jan ✓", "Jan") -> Jan ✓ | EB6: =IF(EB7=0, "Feb ✓", "Feb") -> Feb ✓ | EC6: =IF(EC7=0, "Mar ✓", "Mar") -> Mar ✓ | ED6: =IF(ED7=0, "Apr ✓", "Apr") -> Apr ✓ | EE6: =IF(EE7=0, "May ✓", "May") -> May ✓ | EF6: =IF(EF7=0, "June ✓", "June") -> June ✓ | EG6: =IF(EG7=0, "July ✓", "July") -> July ✓ | EH6: =IF(EH7=0, "Aug ✓", "Aug") -> Aug ✓ | EI6: =IF(EI7=0, "Sep ✓", "Sep") -> Sep ✓ | EJ6: =IF(EJ7=0, "Oct ✓", "Oct") -> Oct ✓ | EK6: =IF(EK7=0, "Nov ✓", "Nov") -> Nov ✓ | EL6: =IF(EL7=0, "Dec ✓", "Dec") -> Dec ✓ | EM6: =IF(EM7=0, "Total ✓", "Total") -> Total ✓ | EO6: =IF(EO7=0, "Jan ✓", "Jan") -> Jan ✓ | EP6: =IF(EP7=0, "Feb ✓", "Feb") -> Feb ✓ | EQ6: =IF(EQ7=0, "Mar ✓", "Mar") -> Mar ✓ | ER6: =IF(ER7=0, "Apr ✓", "Apr") -> Apr ✓ | ES6: =IF(ES7=0, "May ✓", "May") -> May ✓ | ET6: =IF(ET7=0, "June ✓", "June") -> June ✓ | EU6: =IF(EU7=0, "July ✓", "July") -> July ✓ | EV6: =IF(EV7=0, "Aug ✓", "Aug") -> Aug ✓ | EW6: =IF(EW7=0, "Sep ✓", "Sep") -> Sep ✓ | EX6: =IF(EX7=0, "Oct ✓", "Oct") -> Oct ✓ | EY6: =IF(EY7=0, "Nov ✓", "Nov") -> Nov ✓ | EZ6: =IF(EZ7=0, "Dec ✓", "Dec") -> Dec ✓ | FA6: =IF(FA7=0, "Total ✓", "Total") -> Total ✓
C7: To be allocated: | E7: =E20-(E36+E49) -> 0 | F7: =F20-(F36+F49) -> 0 | G7: =G20-(G36+G49) -> 0 | H7: =H20-(H36+H49) -> 0 | I7: =I20-(I36+I49) -> 0 | J7: =J20-(J36+J49) -> 0 | K7: =K20-(K36+K49) -> 0 | L7: =L20-(L36+L49) -> 0 | ... Q7: =Q20-(Q36+Q49) -> 0 | S7: =S20-(S36+S49) -> 0 | T7: =T20-(T36+T49) -> 0 | U7: =U20-(U36+U49) -> 0 | V7: =V20-(V36+V49) -> 0 | W7: =W20-(W36+W49) -> 0 | X7: =X20-(X36+X49) -> 0 | Y7: =Y20-(Y36+Y49) -> 0 | Z7: =Z20-(Z36+Z49) -> 0 | ... AE7: =AE20-(AE36+AE49) -> 0 | AG7: =AG20-(AG36+AG49) -> 0 | AH7: =AH20-(AH36+AH49) -> 0 | AI7: =AI20-(AI36+AI49) -> 0 | AJ7: =AJ20-(AJ36+AJ49) -> 0 | AK7: =AK20-(AK36+AK49) -> 0 | AL7: =AL20-(AL36+AL49) -> 0 | AM7: =AM20-(AM36+AM49) -> 0 | AN7: =AN20-(AN36+AN49) -> 0 | ... AS7: =AS20-(AS36+AS49) -> 0 | AU7: =AU20-(AU36+AU49) -> 0 | AV7: =AV20-(AV36+AV49) -> 0 | AW7: =AW20-(AW36+AW49) -> 0 | AX7: =AX20-(AX36+AX49) -> 0 | AY7: =AY20-(AY36+AY49) -> 0 | AZ7: =AZ20-(AZ36+AZ49) -> 0 | BA7: =BA20-(BA36+BA49) -> 0 | BB7: =BB20-(BB36+BB49) -> 0 | ... BG7: =BG20-(BG36+BG49) -> 0 | BI7: =BI20-(BI36+BI49) -> 0 | BJ7: =BJ20-(BJ36+BJ49) -> 0 | BK7: =BK20-(BK36+BK49) -> 0 | BL7: =BL20-(BL36+BL49) -> 0 | BM7: =BM20-(BM36+BM49) -> 0 | BN7: =BN20-(BN36+BN49) -> 0 | BO7: =BO20-(BO36+BO49) -> 0 | BP7: =BP20-(BP36+BP49) -> 0 | ... BU7: =BU20-(BU36+BU49) -> 0 | BW7: =BW20-(BW36+BW49) -> 0 | BX7: =BX20-(BX36+BX49) -> 0 | BY7: =BY20-(BY36+BY49) -> 0 | BZ7: =BZ20-(BZ36+BZ49) -> 0 | CA7: =CA20-(CA36+CA49) -> 0 | CB7: =CB20-(CB36+CB49) -> 0 | CC7: =CC20-(CC36+CC49) -> 0 | CD7: =CD20-(CD36+CD49) -> 0 | ... CI7: =CI20-(CI36+CI49) -> 0 | CK7: =CK20-(CK36+CK49) -> 0 | CL7: =CL20-(CL36+CL49) -> 0 | CM7: =CM20-(CM36+CM49) -> 0 | CN7: =CN20-(CN36+CN49) -> 0 | CO7: =CO20-(CO36+CO49) -> 0 | CP7: =CP20-(CP36+CP49) -> 0 | CQ7: =CQ20-(CQ36+CQ49) -> 0 | CR7: =CR20-(CR36+CR49) -> 0 | ... CW7: =CW20-(CW36+CW49) -> 0 | CY7: =CY20-(CY36+CY49) -> 0 | CZ7: =CZ20-(CZ36+CZ49) -> 0 | DA7: =DA20-(DA36+DA49) -> 0 | DB7: =DB20-(DB36+DB49) -> 0 | DC7: =DC20-(DC36+DC49) -> 0 | DD7: =DD20-(DD36+DD49) -> 0 | DE7: =DE20-(DE36+DE49) -> 0 | DF7: =DF20-(DF36+DF49) -> 0 | ... DK7: =DK20-(DK36+DK49) -> 0 | DM7: =DM20-(DM36+DM49) -> 0 | DN7: =DN20-(DN36+DN49) -> 0 | DO7: =DO20-(DO36+DO49) -> 0 | DP7: =DP20-(DP36+DP49) -> 0 | DQ7: =DQ20-(DQ36+DQ49) -> 0 | DR7: =DR20-(DR36+DR49) -> 0 | DS7: =DS20-(DS36+DS49) -> 0 | DT7: =DT20-(DT36+DT49) -> 0 | ... DY7: =DY20-(DY36+DY49) -> 0 | EA7: =EA20-(EA36+EA49) -> 0 | EB7: =EB20-(EB36+EB49) -> 0 | EC7: =EC20-(EC36+EC49) -> 0 | ED7: =ED20-(ED36+ED49) -> 0 | EE7: =EE20-(EE36+EE49) -> 0 | EF7: =EF20-(EF36+EF49) -> 0 | EG7: =EG20-(EG36+EG49) -> 0 | EH7: =EH20-(EH36+EH49) -> 0 | ... EM7: =EM20-(EM36+EM49) -> 0 | EO7: =EO20-(EO36+EO49) -> 0 | EP7: =EP20-(EP36+EP49) -> 0 | EQ7: =EQ20-(EQ36+EQ49) -> 0 | ER7: =ER20-(ER36+ER49) -> 0 | ES7: =ES20-(ES36+ES49) -> 0 | ET7: =ET20-(ET36+ET49) -> 0 | EU7: =EU20-(EU36+EU49) -> 0 | EV7: =EV20-(EV36+EV49) -> 0 | ... FA7: =FA20-(FA36+FA49) -> 0
C9: Income | E9: =DATE(E$5, 1, 1) -> 45658 | F9: =DATE(E$5, 2, 1) -> 45689 | G9: =DATE(E$5, 3, 1) -> 45717 | H9: =DATE(E$5, 4, 1) -> 45748 | I9: =DATE(E$5, 5, 1) -> 45778 | J9: =DATE(E$5, 6, 1) -> 45809 | K9: =DATE(E$5, 7, 1) -> 45839 | L9: =DATE(E$5, 8, 1) -> 45870 | M9: =DATE(E$5, 9, 1) -> 45901 | N9: =DATE(E$5, 10, 1) -> 45931 | O9: =DATE(E$5, 11, 1) -> 45962 | P9: =DATE(E$5, 12, 1) -> 45992 | Q9: =E$5 -> 2025 | S9: =DATE(S$5, 1, 1) -> 46023 | T9: =DATE(S$5, 2, 1) -> 46054 | U9: =DATE(S$5, 3, 1) -> 46082 | V9: =DATE(S$5, 4, 1) -> 46113 | W9: =DATE(S$5, 5, 1) -> 46143 | X9: =DATE(S$5, 6, 1) -> 46174 | Y9: =DATE(S$5, 7, 1) -> 46204 | Z9: =DATE(S$5, 8, 1) -> 46235 | AA9: =DATE(S$5, 9, 1) -> 46266 | AB9: =DATE(S$5, 10, 1) -> 46296 | AC9: =DATE(S$5, 11, 1) -> 46327 | AD9: =DATE(S$5, 12, 1) -> 46357 | AE9: =S$5 -> 2026 | AG9: =DATE(AG$5, 1, 1) -> 46388 | AH9: =DATE(AG$5, 2, 1) -> 46419 | AI9: =DATE(AG$5, 3, 1) -> 46447 | AJ9: =DATE(AG$5, 4, 1) -> 46478 | AK9: =DATE(AG$5, 5, 1) -> 46508 | AL9: =DATE(AG$5, 6, 1) -> 46539 | AM9: =DATE(AG$5, 7, 1) -> 46569 | AN9: =DATE(AG$5, 8, 1) -> 46600 | AO9: =DATE(AG$5, 9, 1) -> 46631 | AP9: =DATE(AG$5, 10, 1) -> 46661 | AQ9: =DATE(AG$5, 11, 1) -> 46692 | AR9: =DATE(AG$5, 12, 1) -> 46722 | AS9: =AG$5 -> 2027 | AU9: =DATE(AU$5, 1, 1) -> 46753 | AV9: =DATE(AU$5, 2, 1) -> 46784 | AW9: =DATE(AU$5, 3, 1) -> 46813 | AX9: =DATE(AU$5, 4, 1) -> 46844 | AY9: =DATE(AU$5, 5, 1) -> 46874 | AZ9: =DATE(AU$5, 6, 1) -> 46905 | BA9: =DATE(AU$5, 7, 1) -> 46935 | BB9: =DATE(AU$5, 8, 1) -> 46966 | BC9: =DATE(AU$5, 9, 1) -> 46997 | BD9: =DATE(AU$5, 10, 1) -> 47027 | BE9: =DATE(AU$5, 11, 1) -> 47058 | BF9: =DATE(AU$5, 12, 1) -> 47088 | BG9: =AU$5 -> 2028 | BI9: =DATE(BI$5, 1, 1) -> 47119 | BJ9: =DATE(BI$5, 2, 1) -> 47150 | BK9: =DATE(BI$5, 3, 1) -> 47178 | BL9: =DATE(BI$5, 4, 1) -> 47209 | BM9: =DATE(BI$5, 5, 1) -> 47239 | BN9: =DATE(BI$5, 6, 1) -> 47270 | BO9: =DATE(BI$5, 7, 1) -> 47300 | BP9: =DATE(BI$5, 8, 1) -> 47331 | BQ9: =DATE(BI$5, 9, 1) -> 47362 | BR9: =DATE(BI$5, 10, 1) -> 47392 | BS9: =DATE(BI$5, 11, 1) -> 47423 | BT9: =DATE(BI$5, 12, 1) -> 47453 | BU9: =BI$5 -> 2029 | BW9: =DATE(BW$5, 1, 1) -> 47484 | BX9: =DATE(BW$5, 2, 1) -> 47515 | BY9: =DATE(BW$5, 3, 1) -> 47543 | BZ9: =DATE(BW$5, 4, 1) -> 47574 | CA9: =DATE(BW$5, 5, 1) -> 47604 | CB9: =DATE(BW$5, 6, 1) -> 47635 | CC9: =DATE(BW$5, 7, 1) -> 47665 | CD9: =DATE(BW$5, 8, 1) -> 47696 | CE9: =DATE(BW$5, 9, 1) -> 47727 | CF9: =DATE(BW$5, 10, 1) -> 47757 | CG9: =DATE(BW$5, 11, 1) -> 47788 | CH9: =DATE(BW$5, 12, 1) -> 47818 | CI9: =BW$5 -> 2030 | CK9: =DATE(CK$5, 1, 1) -> 47849 | CL9: =DATE(CK$5, 2, 1) -> 47880 | CM9: =DATE(CK$5, 3, 1) -> 47908 | CN9: =DATE(CK$5, 4, 1) -> 47939 | CO9: =DATE(CK$5, 5, 1) -> 47969 | CP9: =DATE(CK$5, 6, 1) -> 48000 | CQ9: =DATE(CK$5, 7, 1) -> 48030 | CR9: =DATE(CK$5, 8, 1) -> 48061 | CS9: =DATE(CK$5, 9, 1) -> 48092 | CT9: =DATE(CK$5, 10, 1) -> 48122 | CU9: =DATE(CK$5, 11, 1) -> 48153 | CV9: =DATE(CK$5, 12, 1) -> 48183 | CW9: =CK$5 -> 2031 | CY9: =DATE(CY$5, 1, 1) -> 48214 | CZ9: =DATE(CY$5, 2, 1) -> 48245 | DA9: =DATE(CY$5, 3, 1) -> 48274 | DB9: =DATE(CY$5, 4, 1) -> 48305 | DC9: =DATE(CY$5, 5, 1) -> 48335 | DD9: =DATE(CY$5, 6, 1) -> 48366 | DE9: =DATE(CY$5, 7, 1) -> 48396 | DF9: =DATE(CY$5, 8, 1) -> 48427 | DG9: =DATE(CY$5, 9, 1) -> 48458 | DH9: =DATE(CY$5, 10, 1) -> 48488 | DI9: =DATE(CY$5, 11, 1) -> 48519 | DJ9: =DATE(CY$5, 12, 1) -> 48549 | DK9: =CY$5 -> 2032 | DM9: =DATE(DM$5, 1, 1) -> 48580 | DN9: =DATE(DM$5, 2, 1) -> 48611 | DO9: =DATE(DM$5, 3, 1) -> 48639 | DP9: =DATE(DM$5, 4, 1) -> 48670 | DQ9: =DATE(DM$5, 5, 1) -> 48700 | DR9: =DATE(DM$5, 6, 1) -> 48731 | DS9: =DATE(DM$5, 7, 1) -> 48761 | DT9: =DATE(DM$5, 8, 1) -> 48792 | DU9: =DATE(DM$5, 9, 1) -> 48823 | DV9: =DATE(DM$5, 10, 1) -> 48853 | DW9: =DATE(DM$5, 11, 1) -> 48884 | DX9: =DATE(DM$5, 12, 1) -> 48914 | DY9: =DM$5 -> 2033 | EA9: =DATE(EA$5, 1, 1) -> 48945 | EB9: =DATE(EA$5, 2, 1) -> 48976 | EC9: =DATE(EA$5, 3, 1) -> 49004 | ED9: =DATE(EA$5, 4, 1) -> 49035 | EE9: =DATE(EA$5, 5, 1) -> 49065 | EF9: =DATE(EA$5, 6, 1) -> 49096 | EG9: =DATE(EA$5, 7, 1) -> 49126 | EH9: =DATE(EA$5, 8, 1) -> 49157 | EI9: =DATE(EA$5, 9, 1) -> 49188 | EJ9: =DATE(EA$5, 10, 1) -> 49218 | EK9: =DATE(EA$5, 11, 1) -> 49249 | EL9: =DATE(EA$5, 12, 1) -> 49279 | EM9: =EA$5 -> 2034 | EO9: =DATE(EO$5, 1, 1) -> 49310 | EP9: =DATE(EO$5, 2, 1) -> 49341 | EQ9: =DATE(EO$5, 3, 1) -> 49369 | ER9: =DATE(EO$5, 4, 1) -> 49400 | ES9: =DATE(EO$5, 5, 1) -> 49430 | ET9: =DATE(EO$5, 6, 1) -> 49461 | EU9: =DATE(EO$5, 7, 1) -> 49491 | EV9: =DATE(EO$5, 8, 1) -> 49522 | EW9: =DATE(EO$5, 9, 1) -> 49553 | EX9: =DATE(EO$5, 10, 1) -> 49583 | EY9: =DATE(EO$5, 11, 1) -> 49614 | EZ9: =DATE(EO$5, 12, 1) -> 49644 | FA9: =EO$5 -> 2035
C10: Employment (Net) | E10: 3500 | F10: 3500 | G10: 3500 | H10: 4500 | I10: 4500 | J10: 4500 | K10: 4500 | L10: 4500 | M10: 4500 | N10: 4500 | O10: 4500 | P10: 4500 | Q10: =SUM(E10:P10) -> 51000 | AE10: =SUM(S10:AD10) -> 0 | AS10: =SUM(AG10:AR10) -> 0 | BG10: =SUM(AU10:BF10) -> 0 | BU10: =SUM(BI10:BT10) -> 0 | CI10: =SUM(BW10:CH10) -> 0 | CW10: =SUM(CK10:CV10) -> 0 | DK10: =SUM(CY10:DJ10) -> 0 | DY10: =SUM(DM10:DX10) -> 0 | EM10: =SUM(EA10:EL10) -> 0 | FA10: =SUM(EO10:EZ10) -> 0
C11: Side Hustle (Net) | E11: 1000 | F11: 1000 | G11: 1000 | H11: 1000 | I11: 1000 | J11: 1000 | K11: 1000 | L11: 1000 | M11: 1000 | N11: 1000 | O11: 1000 | P11: 1000 | Q11: =SUM(E11:P11) -> 12000 | AE11: =SUM(S11:AD11) -> 0 | AS11: =SUM(AG11:AR11) -> 0 | BG11: =SUM(AU11:BF11) -> 0 | BU11: =SUM(BI11:BT11) -> 0 | CI11: =SUM(BW11:CH11) -> 0 | CW11: =SUM(CK11:CV11) -> 0 | DK11: =SUM(CY11:DJ11) -> 0 | DY11: =SUM(DM11:DX11) -> 0 | EM11: =SUM(EA11:EL11) -> 0 | FA11: =SUM(EO11:EZ11) -> 0
C12: Dividends | E12: 150 | F12: 50 | G12: 100 | H12: 150 | I12: 50 | J12: 100 | K12: 150 | L12: 50 | M12: 100 | N12: 150 | O12: 50 | P12: 100 | Q12: =SUM(E12:P12) -> 1200 | AE12: =SUM(S12:AD12) -> 0 | AS12: =SUM(AG12:AR12) -> 0 | BG12: =SUM(AU12:BF12) -> 0 | BU12: =SUM(BI12:BT12) -> 0 | CI12: =SUM(BW12:CH12) -> 0 | CW12: =SUM(CK12:CV12) -> 0 | DK12: =SUM(CY12:DJ12) -> 0 | DY12: =SUM(DM12:DX12) -> 0 | EM12: =SUM(EA12:EL12) -> 0 | FA12: =SUM(EO12:EZ12) -> 0
C13: Enter Income Category... | Q13: =SUM(E13:P13) -> 0 | AE13: =SUM(S13:AD13) -> 0 | AS13: =SUM(AG13:AR13) -> 0 | BG13: =SUM(AU13:BF13) -> 0 | BU13: =SUM(BI13:BT13) -> 0 | CI13: =SUM(BW13:CH13) -> 0 | CW13: =SUM(CK13:CV13) -> 0 | DK13: =SUM(CY13:DJ13) -> 0 | DY13: =SUM(DM13:DX13) -> 0 | EM13: =SUM(EA13:EL13) -> 0 | FA13: =SUM(EO13:EZ13) -> 0
C14: Enter Income Category... | Q14: =SUM(E14:P14) -> 0 | AE14: =SUM(S14:AD14) -> 0 | AS14: =SUM(AG14:AR14) -> 0 | BG14: =SUM(AU14:BF14) -> 0 | BU14: =SUM(BI14:BT14) -> 0 | CI14: =SUM(BW14:CH14) -> 0 | CW14: =SUM(CK14:CV14) -> 0 | DK14: =SUM(CY14:DJ14) -> 0 | DY14: =SUM(DM14:DX14) -> 0 | EM14: =SUM(EA14:EL14) -> 0 | FA14: =SUM(EO14:EZ14) -> 0
C15: Enter Income Category... | Q15: =SUM(E15:P15) -> 0 | AE15: =SUM(S15:AD15) -> 0 | AS15: =SUM(AG15:AR15) -> 0 | BG15: =SUM(AU15:BF15) -> 0 | BU15: =SUM(BI15:BT15) -> 0 | CI15: =SUM(BW15:CH15) -> 0 | CW15: =SUM(CK15:CV15) -> 0 | DK15: =SUM(CY15:DJ15) -> 0 | DY15: =SUM(DM15:DX15) -> 0 | EM15: =SUM(EA15:EL15) -> 0 | FA15: =SUM(EO15:EZ15) -> 0
C16: Enter Income Category... | Q16: =SUM(E16:P16) -> 0 | AE16: =SUM(S16:AD16) -> 0 | AS16: =SUM(AG16:AR16) -> 0 | BG16: =SUM(AU16:BF16) -> 0 | BU16: =SUM(BI16:BT16) -> 0 | CI16: =SUM(BW16:CH16) -> 0 | CW16: =SUM(CK16:CV16) -> 0 | DK16: =SUM(CY16:DJ16) -> 0 | DY16: =SUM(DM16:DX16) -> 0 | EM16: =SUM(EA16:EL16) -> 0 | FA16: =SUM(EO16:EZ16) -> 0
C17: Enter Income Category... | Q17: =SUM(E17:P17) -> 0 | AE17: =SUM(S17:AD17) -> 0 | AS17: =SUM(AG17:AR17) -> 0 | BG17: =SUM(AU17:BF17) -> 0 | BU17: =SUM(BI17:BT17) -> 0 | CI17: =SUM(BW17:CH17) -> 0 | CW17: =SUM(CK17:CV17) -> 0 | DK17: =SUM(CY17:DJ17) -> 0 | DY17: =SUM(DM17:DX17) -> 0 | EM17: =SUM(EA17:EL17) -> 0 | FA17: =SUM(EO17:EZ17) -> 0
C18: Enter Income Category... | Q18: =SUM(E18:P18) -> 0 | AE18: =SUM(S18:AD18) -> 0 | AS18: =SUM(AG18:AR18) -> 0 | BG18: =SUM(AU18:BF18) -> 0 | BU18: =SUM(BI18:BT18) -> 0 | CI18: =SUM(BW18:CH18) -> 0 | CW18: =SUM(CK18:CV18) -> 0 | DK18: =SUM(CY18:DJ18) -> 0 | DY18: =SUM(DM18:DX18) -> 0 | EM18: =SUM(EA18:EL18) -> 0 | FA18: =SUM(EO18:EZ18) -> 0
C19: Enter Income Category... | Q19: =SUM(E19:P19) -> 0 | AE19: =SUM(S19:AD19) -> 0 | AS19: =SUM(AG19:AR19) -> 0 | BG19: =SUM(AU19:BF19) -> 0 | BU19: =SUM(BI19:BT19) -> 0 | CI19: =SUM(BW19:CH19) -> 0 | CW19: =SUM(CK19:CV19) -> 0 | DK19: =SUM(CY19:DJ19) -> 0 | DY19: =SUM(DM19:DX19) -> 0 | EM19: =SUM(EA19:EL19) -> 0 | FA19: =SUM(EO19:EZ19) -> 0
C20: Total | E20: {=SUM(INDIRECT(ADDRESS(income_min_row, COLUMN()) & ":" & ADDRESS(income_max_row, COLUMN())))} -> 4650 | F20: {=SUM(INDIRECT(ADDRESS(income_min_row, COLUMN()) & ":" & ADDRESS(income_max_row, COLUMN())))} -> 4550 | G20: {=SUM(INDIRECT(ADDRESS(income_min_row, COLUMN()) & ":" & ADDRESS(income_max_row, COLUMN())))} -> 4600 | H20: {=SUM(INDIRECT(ADDRESS(income_min_row, COLUMN()) & ":" & ADDRESS(income_max_row, COLUMN())))} -> 5650 | I20: {=SUM(INDIRECT(ADDRESS(income_min_row, COLUMN()) & ":" & ADDRESS(income_max_row, COLUMN())))} -> 5550 | J20: {=SUM(INDIRECT(ADDRESS(income_min_row, COLUMN()) & ":" & ADDRESS(income_max_row, COLUMN())))} -> 5600 | K20: {=SUM(INDIRECT(ADDRESS(income_min_row, COLUMN()) & ":" & ADDRESS(income_max_row, COLUMN())))} -> 5650 | L20: {=SUM(INDIRECT(ADDRESS(income_min_row, COLUMN()) & ":" & ADDRESS(income_max_row, COLUMN())))} -> 5550 | ... Q20: {=SUM(INDIRECT(ADDRESS(income_min_row, COLUMN()) & ":" & ADDRESS(income_max_row, COLUMN())))} -> 64200 | S20: {=SUM(INDIRECT(ADDRESS(income_min_row, COLUMN()) & ":" & ADDRESS(income_max_row, COLUMN())))} -> 0 | T20: {=SUM(INDIRECT(ADDRESS(income_min_row, COLUMN()) & ":" & ADDRESS(income_max_row, COLUMN())))} -> 0 | U20: {=SUM(INDIRECT(ADDRESS(income_min_row, COLUMN()) & ":" & ADDRESS(income_max_row, COLUMN())))} -> 0 | V20: {=SUM(INDIRECT(ADDRESS(income_min_row, COLUMN()) & ":" & ADDRESS(income_max_row, COLUMN())))} -> 0 | W20: {=SUM(INDIRECT(ADDRESS(income_min_row, COLUMN()) & ":" & ADDRESS(income_max_row, COLUMN())))} -> 0 | X20: {=SUM(INDIRECT(ADDRESS(income_min_row, COLUMN()) & ":" & ADDRESS(income_max_row, COLUMN())))} -> 0 | Y20: {=SUM(INDIRECT(ADDRESS(income_min_row, COLUMN()) & ":" & ADDRESS(income_max_row, COLUMN())))} -> 0 | Z20: {=SUM(INDIRECT(ADDRESS(income_min_row, COLUMN()) & ":" & ADDRESS(income_max_row, COLUMN())))} -> 0 | ... AE20: {=SUM(INDIRECT(ADDRESS(income_min_row, COLUMN()) & ":" & ADDRESS(income_max_row, COLUMN())))} -> 0 | AG20: {=SUM(INDIRECT(ADDRESS(income_min_row, COLUMN()) & ":" & ADDRESS(income_max_row, COLUMN())))} -> 0 | AH20: {=SUM(INDIRECT(ADDRESS(income_min_row, COLUMN()) & ":" & ADDRESS(income_max_row, COLUMN())))} -> 0 | AI20: {=SUM(INDIRECT(ADDRESS(income_min_row, COLUMN()) & ":" & ADDRESS(income_max_row, COLUMN())))} -> 0 | AJ20: {=SUM(INDIRECT(ADDRESS(income_min_row, COLUMN()) & ":" & ADDRESS(income_max_row, COLUMN())))} -> 0 | AK20: {=SUM(INDIRECT(ADDRESS(income_min_row, COLUMN()) & ":" & ADDRESS(income_max_row, COLUMN())))} -> 0 | AL20: {=SUM(INDIRECT(ADDRESS(income_min_row, COLUMN()) & ":" & ADDRESS(income_max_row, COLUMN())))} -> 0 | AM20: {=SUM(INDIRECT(ADDRESS(income_min_row, COLUMN()) & ":" & ADDRESS(income_max_row, COLUMN())))} -> 0 | AN20: {=SUM(INDIRECT(ADDRESS(income_min_row, COLUMN()) & ":" & ADDRESS(income_max_row, COLUMN())))} -> 0 | ... AS20: {=SUM(INDIRECT(ADDRESS(income_min_row, COLUMN()) & ":" & ADDRESS(income_max_row, COLUMN())))} -> 0 | AU20: {=SUM(INDIRECT(ADDRESS(income_min_row, COLUMN()) & ":" & ADDRESS(income_max_row, COLUMN())))} -> 0 | AV20: {=SUM(INDIRECT(ADDRESS(income_min_row, COLUMN()) & ":" & ADDRESS(income_max_row, COLUMN())))} -> 0 | AW20: {=SUM(INDIRECT(ADDRESS(income_min_row, COLUMN()) & ":" & ADDRESS(income_max_row, COLUMN())))} -> 0 | AX20: {=SUM(INDIRECT(ADDRESS(income_min_row, COLUMN()) & ":" & ADDRESS(income_max_row, COLUMN())))} -> 0 | AY20: {=SUM(INDIRECT(ADDRESS(income_min_row, COLUMN()) & ":" & ADDRESS(income_max_row, COLUMN())))} -> 0 | AZ20: {=SUM(INDIRECT(ADDRESS(income_min_row, COLUMN()) & ":" & ADDRESS(income_max_row, COLUMN())))} -> 0 | BA20: {=SUM(INDIRECT(ADDRESS(income_min_row, COLUMN()) & ":" & ADDRESS(income_max_row, COLUMN())))} -> 0 | BB20: {=SUM(INDIRECT(ADDRESS(income_min_row, COLUMN()) & ":" & ADDRESS(income_max_row, COLUMN())))} -> 0 | ... BG20: {=SUM(INDIRECT(ADDRESS(income_min_row, COLUMN()) & ":" & ADDRESS(income_max_row, COLUMN())))} -> 0 | BI20: {=SUM(INDIRECT(ADDRESS(income_min_row, COLUMN()) & ":" & ADDRESS(income_max_row, COLUMN())))} -> 0 | BJ20: {=SUM(INDIRECT(ADDRESS(income_min_row, COLUMN()) & ":" & ADDRESS(income_max_row, COLUMN())))} -> 0 | BK20: {=SUM(INDIRECT(ADDRESS(income_min_row, COLUMN()) & ":" & ADDRESS(income_max_row, COLUMN())))} -> 0 | BL20: {=SUM(INDIRECT(ADDRESS(income_min_row, COLUMN()) & ":" & ADDRESS(income_max_row, COLUMN())))} -> 0 | BM20: {=SUM(INDIRECT(ADDRESS(income_min_row, COLUMN()) & ":" & ADDRESS(income_max_row, COLUMN())))} -> 0 | BN20: {=SUM(INDIRECT(ADDRESS(income_min_row, COLUMN()) & ":" & ADDRESS(income_max_row, COLUMN())))} -> 0 | BO20: {=SUM(INDIRECT(ADDRESS(income_min_row, COLUMN()) & ":" & ADDRESS(income_max_row, COLUMN())))} -> 0 | BP20: {=SUM(INDIRECT(ADDRESS(income_min_row, COLUMN()) & ":" & ADDRESS(income_max_row, COLUMN())))} -> 0 | ... BU20: {=SUM(INDIRECT(ADDRESS(income_min_row, COLUMN()) & ":" & ADDRESS(income_max_row, COLUMN())))} -> 0 | BW20: {=SUM(INDIRECT(ADDRESS(income_min_row, COLUMN()) & ":" & ADDRESS(income_max_row, COLUMN())))} -> 0 | BX20: {=SUM(INDIRECT(ADDRESS(income_min_row, COLUMN()) & ":" & ADDRESS(income_max_row, COLUMN())))} -> 0 | BY20: {=SUM(INDIRECT(ADDRESS(income_min_row, COLUMN()) & ":" & ADDRESS(income_max_row, COLUMN())))} -> 0 | BZ20: {=SUM(INDIRECT(ADDRESS(income_min_row, COLUMN()) & ":" & ADDRESS(income_max_row, COLUMN())))} -> 0 | CA20: {=SUM(INDIRECT(ADDRESS(income_min_row, COLUMN()) & ":" & ADDRESS(income_max_row, COLUMN())))} -> 0 | CB20: {=SUM(INDIRECT(ADDRESS(income_min_row, COLUMN()) & ":" & ADDRESS(income_max_row, COLUMN())))} -> 0 | CC20: {=SUM(INDIRECT(ADDRESS(income_min_row, COLUMN()) & ":" & ADDRESS(income_max_row, COLUMN())))} -> 0 | CD20: {=SUM(INDIRECT(ADDRESS(income_min_row, COLUMN()) & ":" & ADDRESS(income_max_row, COLUMN())))} -> 0 | ... CI20: {=SUM(INDIRECT(ADDRESS(income_min_row, COLUMN()) & ":" & ADDRESS(income_max_row, COLUMN())))} -> 0 | CK20: {=SUM(INDIRECT(ADDRESS(income_min_row, COLUMN()) & ":" & ADDRESS(income_max_row, COLUMN())))} -> 0 | CL20: {=SUM(INDIRECT(ADDRESS(income_min_row, COLUMN()) & ":" & ADDRESS(income_max_row, COLUMN())))} -> 0 | CM20: {=SUM(INDIRECT(ADDRESS(income_min_row, COLUMN()) & ":" & ADDRESS(income_max_row, COLUMN())))} -> 0 | CN20: {=SUM(INDIRECT(ADDRESS(income_min_row, COLUMN()) & ":" & ADDRESS(income_max_row, COLUMN())))} -> 0 | CO20: {=SUM(INDIRECT(ADDRESS(income_min_row, COLUMN()) & ":" & ADDRESS(income_max_row, COLUMN())))} -> 0 | CP20: {=SUM(INDIRECT(ADDRESS(income_min_row, COLUMN()) & ":" & ADDRESS(income_max_row, COLUMN())))} -> 0 | CQ20: {=SUM(INDIRECT(ADDRESS(income_min_row, COLUMN()) & ":" & ADDRESS(income_max_row, COLUMN())))} -> 0 | CR20: {=SUM(INDIRECT(ADDRESS(income_min_row, COLUMN()) & ":" & ADDRESS(income_max_row, COLUMN())))} -> 0 | ... CW20: {=SUM(INDIRECT(ADDRESS(income_min_row, COLUMN()) & ":" & ADDRESS(income_max_row, COLUMN())))} -> 0 | CY20: {=SUM(INDIRECT(ADDRESS(income_min_row, COLUMN()) & ":" & ADDRESS(income_max_row, COLUMN())))} -> 0 | CZ20: {=SUM(INDIRECT(ADDRESS(income_min_row, COLUMN()) & ":" & ADDRESS(income_max_row, COLUMN())))} -> 0 | DA20: {=SUM(INDIRECT(ADDRESS(income_min_row, COLUMN()) & ":" & ADDRESS(income_max_row, COLUMN())))} -> 0 | DB20: {=SUM(INDIRECT(ADDRESS(income_min_row, COLUMN()) & ":" & ADDRESS(income_max_row, COLUMN())))} -> 0 | DC20: {=SUM(INDIRECT(ADDRESS(income_min_row, COLUMN()) & ":" & ADDRESS(income_max_row, COLUMN())))} -> 0 | DD20: {=SUM(INDIRECT(ADDRESS(income_min_row, COLUMN()) & ":" & ADDRESS(income_max_row, COLUMN())))} -> 0 | DE20: {=SUM(INDIRECT(ADDRESS(income_min_row, COLUMN()) & ":" & ADDRESS(income_max_row, COLUMN())))} -> 0 | DF20: {=SUM(INDIRECT(ADDRESS(income_min_row, COLUMN()) & ":" & ADDRESS(income_max_row, COLUMN())))} -> 0 | ... DK20: {=SUM(INDIRECT(ADDRESS(income_min_row, COLUMN()) & ":" & ADDRESS(income_max_row, COLUMN())))} -> 0 | DM20: {=SUM(INDIRECT(ADDRESS(income_min_row, COLUMN()) & ":" & ADDRESS(income_max_row, COLUMN())))} -> 0 | DN20: {=SUM(INDIRECT(ADDRESS(income_min_row, COLUMN()) & ":" & ADDRESS(income_max_row, COLUMN())))} -> 0 | DO20: {=SUM(INDIRECT(ADDRESS(income_min_row, COLUMN()) & ":" & ADDRESS(income_max_row, COLUMN())))} -> 0 | DP20: {=SUM(INDIRECT(ADDRESS(income_min_row, COLUMN()) & ":" & ADDRESS(income_max_row, COLUMN())))} -> 0 | DQ20: {=SUM(INDIRECT(ADDRESS(income_min_row, COLUMN()) & ":" & ADDRESS(income_max_row, COLUMN())))} -> 0 | DR20: {=SUM(INDIRECT(ADDRESS(income_min_row, COLUMN()) & ":" & ADDRESS(income_max_row, COLUMN())))} -> 0 | DS20: {=SUM(INDIRECT(ADDRESS(income_min_row, COLUMN()) & ":" & ADDRESS(income_max_row, COLUMN())))} -> 0 | DT20: {=SUM(INDIRECT(ADDRESS(income_min_row, COLUMN()) & ":" & ADDRESS(income_max_row, COLUMN())))} -> 0 | ... DY20: {=SUM(INDIRECT(ADDRESS(income_min_row, COLUMN()) & ":" & ADDRESS(income_max_row, COLUMN())))} -> 0 | EA20: {=SUM(INDIRECT(ADDRESS(income_min_row, COLUMN()) & ":" & ADDRESS(income_max_row, COLUMN())))} -> 0 | EB20: {=SUM(INDIRECT(ADDRESS(income_min_row, COLUMN()) & ":" & ADDRESS(income_max_row, COLUMN())))} -> 0 | EC20: {=SUM(INDIRECT(ADDRESS(income_min_row, COLUMN()) & ":" & ADDRESS(income_max_row, COLUMN())))} -> 0 | ED20: {=SUM(INDIRECT(ADDRESS(income_min_row, COLUMN()) & ":" & ADDRESS(income_max_row, COLUMN())))} -> 0 | EE20: {=SUM(INDIRECT(ADDRESS(income_min_row, COLUMN()) & ":" & ADDRESS(income_max_row, COLUMN())))} -> 0 | EF20: {=SUM(INDIRECT(ADDRESS(income_min_row, COLUMN()) & ":" & ADDRESS(income_max_row, COLUMN())))} -> 0 | EG20: {=SUM(INDIRECT(ADDRESS(income_min_row, COLUMN()) & ":" & ADDRESS(income_max_row, COLUMN())))} -> 0 | EH20: {=SUM(INDIRECT(ADDRESS(income_min_row, COLUMN()) & ":" & ADDRESS(income_max_row, COLUMN())))} -> 0 | ... EM20: {=SUM(INDIRECT(ADDRESS(income_min_row, COLUMN()) & ":" & ADDRESS(income_max_row, COLUMN())))} -> 0 | EO20: {=SUM(INDIRECT(ADDRESS(income_min_row, COLUMN()) & ":" & ADDRESS(income_max_row, COLUMN())))} -> 0 | EP20: {=SUM(INDIRECT(ADDRESS(income_min_row, COLUMN()) & ":" & ADDRESS(income_max_row, COLUMN())))} -> 0 | EQ20: {=SUM(INDIRECT(ADDRESS(income_min_row, COLUMN()) & ":" & ADDRESS(income_max_row, COLUMN())))} -> 0 | ER20: {=SUM(INDIRECT(ADDRESS(income_min_row, COLUMN()) & ":" & ADDRESS(income_max_row, COLUMN())))} -> 0 | ES20: {=SUM(INDIRECT(ADDRESS(income_min_row, COLUMN()) & ":" & ADDRESS(income_max_row, COLUMN())))} -> 0 | ET20: {=SUM(INDIRECT(ADDRESS(income_min_row, COLUMN()) & ":" & ADDRESS(income_max_row, COLUMN())))} -> 0 | EU20: {=SUM(INDIRECT(ADDRESS(income_min_row, COLUMN()) & ":" & ADDRESS(income_max_row, COLUMN())))} -> 0 | EV20: {=SUM(INDIRECT(ADDRESS(income_min_row, COLUMN()) & ":" & ADDRESS(income_max_row, COLUMN())))} -> 0 | ... FA20: {=SUM(INDIRECT(ADDRESS(income_min_row, COLUMN()) & ":" & ADDRESS(income_max_row, COLUMN())))} -> 0
C22: Expenses | E22: =DATE(E$5, 1, 1) -> 45658 | F22: =DATE(E$5, 2, 1) -> 45689 | G22: =DATE(E$5, 3, 1) -> 45717 | H22: =DATE(E$5, 4, 1) -> 45748 | I22: =DATE(E$5, 5, 1) -> 45778 | J22: =DATE(E$5, 6, 1) -> 45809 | K22: =DATE(E$5, 7, 1) -> 45839 | L22: =DATE(E$5, 8, 1) -> 45870 | M22: =DATE(E$5, 9, 1) -> 45901 | N22: =DATE(E$5, 10, 1) -> 45931 | O22: =DATE(E$5, 11, 1) -> 45962 | P22: =DATE(E$5, 12, 1) -> 45992 | Q22: =E$5 -> 2025 | S22: =DATE(S$5, 1, 1) -> 46023 | T22: =DATE(S$5, 2, 1) -> 46054 | U22: =DATE(S$5, 3, 1) -> 46082 | V22: =DATE(S$5, 4, 1) -> 46113 | W22: =DATE(S$5, 5, 1) -> 46143 | X22: =DATE(S$5, 6, 1) -> 46174 | Y22: =DATE(S$5, 7, 1) -> 46204 | Z22: =DATE(S$5, 8, 1) -> 46235 | AA22: =DATE(S$5, 9, 1) -> 46266 | AB22: =DATE(S$5, 10, 1) -> 46296 | AC22: =DATE(S$5, 11, 1) -> 46327 | AD22: =DATE(S$5, 12, 1) -> 46357 | AE22: =S$5 -> 2026 | AG22: =DATE(AG$5, 1, 1) -> 46388 | AH22: =DATE(AG$5, 2, 1) -> 46419 | AI22: =DATE(AG$5, 3, 1) -> 46447 | AJ22: =DATE(AG$5, 4, 1) -> 46478 | AK22: =DATE(AG$5, 5, 1) -> 46508 | AL22: =DATE(AG$5, 6, 1) -> 46539 | AM22: =DATE(AG$5, 7, 1) -> 46569 | AN22: =DATE(AG$5, 8, 1) -> 46600 | AO22: =DATE(AG$5, 9, 1) -> 46631 | AP22: =DATE(AG$5, 10, 1) -> 46661 | AQ22: =DATE(AG$5, 11, 1) -> 46692 | AR22: =DATE(AG$5, 12, 1) -> 46722 | AS22: =AG$5 -> 2027 | AU22: =DATE(AU$5, 1, 1) -> 46753 | AV22: =DATE(AU$5, 2, 1) -> 46784 | AW22: =DATE(AU$5, 3, 1) -> 46813 | AX22: =DATE(AU$5, 4, 1) -> 46844 | AY22: =DATE(AU$5, 5, 1) -> 46874 | AZ22: =DATE(AU$5, 6, 1) -> 46905 | BA22: =DATE(AU$5, 7, 1) -> 46935 | BB22: =DATE(AU$5, 8, 1) -> 46966 | BC22: =DATE(AU$5, 9, 1) -> 46997 | BD22: =DATE(AU$5, 10, 1) -> 47027 | BE22: =DATE(AU$5, 11, 1) -> 47058 | BF22: =DATE(AU$5, 12, 1) -> 47088 | BG22: =AU$5 -> 2028 | BI22: =DATE(BI$5, 1, 1) -> 47119 | BJ22: =DATE(BI$5, 2, 1) -> 47150 | BK22: =DATE(BI$5, 3, 1) -> 47178 | BL22: =DATE(BI$5, 4, 1) -> 47209 | BM22: =DATE(BI$5, 5, 1) -> 47239 | BN22: =DATE(BI$5, 6, 1) -> 47270 | BO22: =DATE(BI$5, 7, 1) -> 47300 | BP22: =DATE(BI$5, 8, 1) -> 47331 | BQ22: =DATE(BI$5, 9, 1) -> 47362 | BR22: =DATE(BI$5, 10, 1) -> 47392 | BS22: =DATE(BI$5, 11, 1) -> 47423 | BT22: =DATE(BI$5, 12, 1) -> 47453 | BU22: =BI$5 -> 2029 | BW22: =DATE(BW$5, 1, 1) -> 47484 | BX22: =DATE(BW$5, 2, 1) -> 47515 | BY22: =DATE(BW$5, 3, 1) -> 47543 | BZ22: =DATE(BW$5, 4, 1) -> 47574 | CA22: =DATE(BW$5, 5, 1) -> 47604 | CB22: =DATE(BW$5, 6, 1) -> 47635 | CC22: =DATE(BW$5, 7, 1) -> 47665 | CD22: =DATE(BW$5, 8, 1) -> 47696 | CE22: =DATE(BW$5, 9, 1) -> 47727 | CF22: =DATE(BW$5, 10, 1) -> 47757 | CG22: =DATE(BW$5, 11, 1) -> 47788 | CH22: =DATE(BW$5, 12, 1) -> 47818 | CI22: =BW$5 -> 2030 | CK22: =DATE(CK$5, 1, 1) -> 47849 | CL22: =DATE(CK$5, 2, 1) -> 47880 | CM22: =DATE(CK$5, 3, 1) -> 47908 | CN22: =DATE(CK$5, 4, 1) -> 47939 | CO22: =DATE(CK$5, 5, 1) -> 47969 | CP22: =DATE(CK$5, 6, 1) -> 48000 | CQ22: =DATE(CK$5, 7, 1) -> 48030 | CR22: =DATE(CK$5, 8, 1) -> 48061 | CS22: =DATE(CK$5, 9, 1) -> 48092 | CT22: =DATE(CK$5, 10, 1) -> 48122 | CU22: =DATE(CK$5, 11, 1) -> 48153 | CV22: =DATE(CK$5, 12, 1) -> 48183 | CW22: =CK$5 -> 2031 | CY22: =DATE(CY$5, 1, 1) -> 48214 | CZ22: =DATE(CY$5, 2, 1) -> 48245 | DA22: =DATE(CY$5, 3, 1) -> 48274 | DB22: =DATE(CY$5, 4, 1) -> 48305 | DC22: =DATE(CY$5, 5, 1) -> 48335 | DD22: =DATE(CY$5, 6, 1) -> 48366 | DE22: =DATE(CY$5, 7, 1) -> 48396 | DF22: =DATE(CY$5, 8, 1) -> 48427 | DG22: =DATE(CY$5, 9, 1) -> 48458 | DH22: =DATE(CY$5, 10, 1) -> 48488 | DI22: =DATE(CY$5, 11, 1) -> 48519 | DJ22: =DATE(CY$5, 12, 1) -> 48549 | DK22: =CY$5 -> 2032 | DM22: =DATE(DM$5, 1, 1) -> 48580 | DN22: =DATE(DM$5, 2, 1) -> 48611 | DO22: =DATE(DM$5, 3, 1) -> 48639 | DP22: =DATE(DM$5, 4, 1) -> 48670 | DQ22: =DATE(DM$5, 5, 1) -> 48700 | DR22: =DATE(DM$5, 6, 1) -> 48731 | DS22: =DATE(DM$5, 7, 1) -> 48761 | DT22: =DATE(DM$5, 8, 1) -> 48792 | DU22: =DATE(DM$5, 9, 1) -> 48823 | DV22: =DATE(DM$5, 10, 1) -> 48853 | DW22: =DATE(DM$5, 11, 1) -> 48884 | DX22: =DATE(DM$5, 12, 1) -> 48914 | DY22: =DM$5 -> 2033 | EA22: =DATE(EA$5, 1, 1) -> 48945 | EB22: =DATE(EA$5, 2, 1) -> 48976 | EC22: =DATE(EA$5, 3, 1) -> 49004 | ED22: =DATE(EA$5, 4, 1) -> 49035 | EE22: =DATE(EA$5, 5, 1) -> 49065 | EF22: =DATE(EA$5, 6, 1) -> 49096 | EG22: =DATE(EA$5, 7, 1) -> 49126 | EH22: =DATE(EA$5, 8, 1) -> 49157 | EI22: =DATE(EA$5, 9, 1) -> 49188 | EJ22: =DATE(EA$5, 10, 1) -> 49218 | EK22: =DATE(EA$5, 11, 1) -> 49249 | EL22: =DATE(EA$5, 12, 1) -> 49279 | EM22: =EA$5 -> 2034 | EO22: =DATE(EO$5, 1, 1) -> 49310 | EP22: =DATE(EO$5, 2, 1) -> 49341 | EQ22: =DATE(EO$5, 3, 1) -> 49369 | ER22: =DATE(EO$5, 4, 1) -> 49400 | ES22: =DATE(EO$5, 5, 1) -> 49430 | ET22: =DATE(EO$5, 6, 1) -> 49461 | EU22: =DATE(EO$5, 7, 1) -> 49491 | EV22: =DATE(EO$5, 8, 1) -> 49522 | EW22: =DATE(EO$5, 9, 1) -> 49553 | EX22: =DATE(EO$5, 10, 1) -> 49583 | EY22: =DATE(EO$5, 11, 1) -> 49614 | EZ22: =DATE(EO$5, 12, 1) -> 49644 | FA22: =EO$5 -> 2035
C23: Housing | E23: 1200 | F23: 1200 | G23: 1200 | H23: 1200 | I23: 1200 | J23: 1200 | K23: 1200 | L23: 1200 | M23: 1200 | N23: 1200 | O23: 1200 | P23: 1200 | Q23: =SUM(E23:P23) -> 14400 | AE23: =SUM(S23:AD23) -> 0 | AS23: =SUM(AG23:AR23) -> 0 | BG23: =SUM(AU23:BF23) -> 0 | BU23: =SUM(BI23:BT23) -> 0 | CI23: =SUM(BW23:CH23) -> 0 | CW23: =SUM(CK23:CV23) -> 0 | DK23: =SUM(CY23:DJ23) -> 0 | DY23: =SUM(DM23:DX23) -> 0 | EM23: =SUM(EA23:EL23) -> 0 | FA23: =SUM(EO23:EZ23) -> 0
C24: Utilites | E24: 300 | F24: 300 | G24: 300 | H24: 300 | I24: 300 | J24: 300 | K24: 300 | L24: 300 | M24: 300 | N24: 300 | O24: 300 | P24: 300 | Q24: =SUM(E24:P24) -> 3600 | AE24: =SUM(S24:AD24) -> 0 | AS24: =SUM(AG24:AR24) -> 0 | BG24: =SUM(AU24:BF24) -> 0 | BU24: =SUM(BI24:BT24) -> 0 | CI24: =SUM(BW24:CH24) -> 0 | CW24: =SUM(CK24:CV24) -> 0 | DK24: =SUM(CY24:DJ24) -> 0 | DY24: =SUM(DM24:DX24) -> 0 | EM24: =SUM(EA24:EL24) -> 0 | FA24: =SUM(EO24:EZ24) -> 0
C25: Groceries | E25: 350 | F25: 350 | G25: 350 | H25: 350 | I25: 350 | J25: 350 | K25: 350 | L25: 350 | M25: 350 | N25: 350 | O25: 350 | P25: 350 | Q25: =SUM(E25:P25) -> 4200 | AE25: =SUM(S25:AD25) -> 0 | AS25: =SUM(AG25:AR25) -> 0 | BG25: =SUM(AU25:BF25) -> 0 | BU25: =SUM(BI25:BT25) -> 0 | CI25: =SUM(BW25:CH25) -> 0 | CW25: =SUM(CK25:CV25) -> 0 | DK25: =SUM(CY25:DJ25) -> 0 | DY25: =SUM(DM25:DX25) -> 0 | EM25: =SUM(EA25:EL25) -> 0 | FA25: =SUM(EO25:EZ25) -> 0
C26: Transportation | E26: 300 | F26: 300 | G26: 300 | H26: 300 | I26: 300 | J26: 300 | K26: 300 | L26: 300 | M26: 300 | N26: 300 | O26: 300 | P26: 300 | Q26: =SUM(E26:P26) -> 3600 | AE26: =SUM(S26:AD26) -> 0 | AS26: =SUM(AG26:AR26) -> 0 | BG26: =SUM(AU26:BF26) -> 0 | BU26: =SUM(BI26:BT26) -> 0 | CI26: =SUM(BW26:CH26) -> 0 | CW26: =SUM(CK26:CV26) -> 0 | DK26: =SUM(CY26:DJ26) -> 0 | DY26: =SUM(DM26:DX26) -> 0 | EM26: =SUM(EA26:EL26) -> 0 | FA26: =SUM(EO26:EZ26) -> 0
C27: Insurances | G27: 150 | J27: 150 | M27: 150 | P27: 150 | Q27: =SUM(E27:P27) -> 600 | AE27: =SUM(S27:AD27) -> 0 | AS27: =SUM(AG27:AR27) -> 0 | BG27: =SUM(AU27:BF27) -> 0 | BU27: =SUM(BI27:BT27) -> 0 | CI27: =SUM(BW27:CH27) -> 0 | CW27: =SUM(CK27:CV27) -> 0 | DK27: =SUM(CY27:DJ27) -> 0 | DY27: =SUM(DM27:DX27) -> 0 | EM27: =SUM(EA27:EL27) -> 0 | FA27: =SUM(EO27:EZ27) -> 0
C28: Clothing | E28: 200 | F28: 200 | G28: 200 | H28: 200 | I28: 200 | J28: 200 | K28: 200 | L28: 200 | M28: 200 | N28: 200 | O28: 200 | P28: 200 | Q28: =SUM(E28:P28) -> 2400
C29: Body Care & Medicine | E29: 200 | F29: 200 | G29: 200 | H29: 200 | I29: 200 | J29: 200 | K29: 200 | L29: 200 | M29: 200 | N29: 200 | O29: 200 | P29: 200 | Q29: =SUM(E29:P29) -> 2400 | AE29: =SUM(S29:AD29) -> 0 | AS29: =SUM(AG29:AR29) -> 0 | BG29: =SUM(AU29:BF29) -> 0 | BU29: =SUM(BI29:BT29) -> 0 | CI29: =SUM(BW29:CH29) -> 0 | CW29: =SUM(CK29:CV29) -> 0 | DK29: =SUM(CY29:DJ29) -> 0 | DY29: =SUM(DM29:DX29) -> 0 | EM29: =SUM(EA29:EL29) -> 0 | FA29: =SUM(EO29:EZ29) -> 0
C30: Media | E30: 50 | F30: 50 | G30: 50 | H30: 50 | I30: 50 | J30: 50 | K30: 50 | L30: 50 | M30: 50 | N30: 50 | O30: 50 | P30: 50 | Q30: =SUM(E30:P30) -> 600
C31: Fun & Vacation | E31: 300 | F31: 300 | G31: 300 | H31: 1200 | I31: 300 | J31: 300 | K31: 300 | L31: 1500 | M31: 300 | N31: 300 | O31: 300 | P31: 600 | Q31: =SUM(E31:P31) -> 6000
C32: Enter Expenses Category... | Q32: =SUM(E32:P32) -> 0 | AE32: =SUM(S32:AD32) -> 0 | AS32: =SUM(AG32:AR32) -> 0 | BG32: =SUM(AU32:BF32) -> 0 | BU32: =SUM(BI32:BT32) -> 0 | CI32: =SUM(BW32:CH32) -> 0 | CW32: =SUM(CK32:CV32) -> 0 | DK32: =SUM(CY32:DJ32) -> 0 | DY32: =SUM(DM32:DX32) -> 0 | EM32: =SUM(EA32:EL32) -> 0 | FA32: =SUM(EO32:EZ32) -> 0
C33: Enter Expenses Category... | Q33: =SUM(E33:P33) -> 0 | AE33: =SUM(S33:AD33) -> 0 | AS33: =SUM(AG33:AR33) -> 0 | BG33: =SUM(AU33:BF33) -> 0 | BU33: =SUM(BI33:BT33) -> 0 | CI33: =SUM(BW33:CH33) -> 0 | CW33: =SUM(CK33:CV33) -> 0 | DK33: =SUM(CY33:DJ33) -> 0 | DY33: =SUM(DM33:DX33) -> 0 | EM33: =SUM(EA33:EL33) -> 0 | FA33: =SUM(EO33:EZ33) -> 0
C34: Enter Expenses Category... | Q34: =SUM(E34:P34) -> 0 | AE34: =SUM(S34:AD34) -> 0 | AS34: =SUM(AG34:AR34) -> 0 | BG34: =SUM(AU34:BF34) -> 0 | BU34: =SUM(BI34:BT34) -> 0 | CI34: =SUM(BW34:CH34) -> 0 | CW34: =SUM(CK34:CV34) -> 0 | DK34: =SUM(CY34:DJ34) -> 0 | DY34: =SUM(DM34:DX34) -> 0 | EM34: =SUM(EA34:EL34) -> 0 | FA34: =SUM(EO34:EZ34) -> 0
C35: Enter Expenses Category... | Q35: =SUM(E35:P35) -> 0 | AE35: =SUM(S35:AD35) -> 0 | AS35: =SUM(AG35:AR35) -> 0 | BG35: =SUM(AU35:BF35) -> 0 | BU35: =SUM(BI35:BT35) -> 0 | CI35: =SUM(BW35:CH35) -> 0 | CW35: =SUM(CK35:CV35) -> 0 | DK35: =SUM(CY35:DJ35) -> 0 | DY35: =SUM(DM35:DX35) -> 0 | EM35: =SUM(EA35:EL35) -> 0 | FA35: =SUM(EO35:EZ35) -> 0
C36: Total | E36: {=SUM(INDIRECT(ADDRESS(expenses_min_row, COLUMN()) & ":" & ADDRESS(expenses_max_row, COLUMN())))} -> 2900 | F36: {=SUM(INDIRECT(ADDRESS(expenses_min_row, COLUMN()) & ":" & ADDRESS(expenses_max_row, COLUMN())))} -> 2900 | G36: {=SUM(INDIRECT(ADDRESS(expenses_min_row, COLUMN()) & ":" & ADDRESS(expenses_max_row, COLUMN())))} -> 3050 | H36: {=SUM(INDIRECT(ADDRESS(expenses_min_row, COLUMN()) & ":" & ADDRESS(expenses_max_row, COLUMN())))} -> 3800 | I36: {=SUM(INDIRECT(ADDRESS(expenses_min_row, COLUMN()) & ":" & ADDRESS(expenses_max_row, COLUMN())))} -> 2900 | J36: {=SUM(INDIRECT(ADDRESS(expenses_min_row, COLUMN()) & ":" & ADDRESS(expenses_max_row, COLUMN())))} -> 3050 | K36: {=SUM(INDIRECT(ADDRESS(expenses_min_row, COLUMN()) & ":" & ADDRESS(expenses_max_row, COLUMN())))} -> 2900 | L36: {=SUM(INDIRECT(ADDRESS(expenses_min_row, COLUMN()) & ":" & ADDRESS(expenses_max_row, COLUMN())))} -> 4100 | ... Q36: {=SUM(INDIRECT(ADDRESS(expenses_min_row, COLUMN()) & ":" & ADDRESS(expenses_max_row, COLUMN())))} -> 37800 | S36: {=SUM(INDIRECT(ADDRESS(expenses_min_row, COLUMN()) & ":" & ADDRESS(expenses_max_row, COLUMN())))} -> 0 | T36: {=SUM(INDIRECT(ADDRESS(expenses_min_row, COLUMN()) & ":" & ADDRESS(expenses_max_row, COLUMN())))} -> 0 | U36: {=SUM(INDIRECT(ADDRESS(expenses_min_row, COLUMN()) & ":" & ADDRESS(expenses_max_row, COLUMN())))} -> 0 | V36: {=SUM(INDIRECT(ADDRESS(expenses_min_row, COLUMN()) & ":" & ADDRESS(expenses_max_row, COLUMN())))} -> 0 | W36: {=SUM(INDIRECT(ADDRESS(expenses_min_row, COLUMN()) & ":" & ADDRESS(expenses_max_row, COLUMN())))} -> 0 | X36: {=SUM(INDIRECT(ADDRESS(expenses_min_row, COLUMN()) & ":" & ADDRESS(expenses_max_row, COLUMN())))} -> 0 | Y36: {=SUM(INDIRECT(ADDRESS(expenses_min_row, COLUMN()) & ":" & ADDRESS(expenses_max_row, COLUMN())))} -> 0 | Z36: {=SUM(INDIRECT(ADDRESS(expenses_min_row, COLUMN()) & ":" & ADDRESS(expenses_max_row, COLUMN())))} -> 0 | ... AE36: {=SUM(INDIRECT(ADDRESS(expenses_min_row, COLUMN()) & ":" & ADDRESS(expenses_max_row, COLUMN())))} -> 0 | AG36: {=SUM(INDIRECT(ADDRESS(expenses_min_row, COLUMN()) & ":" & ADDRESS(expenses_max_row, COLUMN())))} -> 0 | AH36: {=SUM(INDIRECT(ADDRESS(expenses_min_row, COLUMN()) & ":" & ADDRESS(expenses_max_row, COLUMN())))} -> 0 | AI36: {=SUM(INDIRECT(ADDRESS(expenses_min_row, COLUMN()) & ":" & ADDRESS(expenses_max_row, COLUMN())))} -> 0 | AJ36: {=SUM(INDIRECT(ADDRESS(expenses_min_row, COLUMN()) & ":" & ADDRESS(expenses_max_row, COLUMN())))} -> 0 | AK36: {=SUM(INDIRECT(ADDRESS(expenses_min_row, COLUMN()) & ":" & ADDRESS(expenses_max_row, COLUMN())))} -> 0 | AL36: {=SUM(INDIRECT(ADDRESS(expenses_min_row, COLUMN()) & ":" & ADDRESS(expenses_max_row, COLUMN())))} -> 0 | AM36: {=SUM(INDIRECT(ADDRESS(expenses_min_row, COLUMN()) & ":" & ADDRESS(expenses_max_row, COLUMN())))} -> 0 | AN36: {=SUM(INDIRECT(ADDRESS(expenses_min_row, COLUMN()) & ":" & ADDRESS(expenses_max_row, COLUMN())))} -> 0 | ... AS36: {=SUM(INDIRECT(ADDRESS(expenses_min_row, COLUMN()) & ":" & ADDRESS(expenses_max_row, COLUMN())))} -> 0 | AU36: {=SUM(INDIRECT(ADDRESS(expenses_min_row, COLUMN()) & ":" & ADDRESS(expenses_max_row, COLUMN())))} -> 0 | AV36: {=SUM(INDIRECT(ADDRESS(expenses_min_row, COLUMN()) & ":" & ADDRESS(expenses_max_row, COLUMN())))} -> 0 | AW36: {=SUM(INDIRECT(ADDRESS(expenses_min_row, COLUMN()) & ":" & ADDRESS(expenses_max_row, COLUMN())))} -> 0 | AX36: {=SUM(INDIRECT(ADDRESS(expenses_min_row, COLUMN()) & ":" & ADDRESS(expenses_max_row, COLUMN())))} -> 0 | AY36: {=SUM(INDIRECT(ADDRESS(expenses_min_row, COLUMN()) & ":" & ADDRESS(expenses_max_row, COLUMN())))} -> 0 | AZ36: {=SUM(INDIRECT(ADDRESS(expenses_min_row, COLUMN()) & ":" & ADDRESS(expenses_max_row, COLUMN())))} -> 0 | BA36: {=SUM(INDIRECT(ADDRESS(expenses_min_row, COLUMN()) & ":" & ADDRESS(expenses_max_row, COLUMN())))} -> 0 | BB36: {=SUM(INDIRECT(ADDRESS(expenses_min_row, COLUMN()) & ":" & ADDRESS(expenses_max_row, COLUMN())))} -> 0 | ... BG36: {=SUM(INDIRECT(ADDRESS(expenses_min_row, COLUMN()) & ":" & ADDRESS(expenses_max_row, COLUMN())))} -> 0 | BI36: {=SUM(INDIRECT(ADDRESS(expenses_min_row, COLUMN()) & ":" & ADDRESS(expenses_max_row, COLUMN())))} -> 0 | BJ36: {=SUM(INDIRECT(ADDRESS(expenses_min_row, COLUMN()) & ":" & ADDRESS(expenses_max_row, COLUMN())))} -> 0 | BK36: {=SUM(INDIRECT(ADDRESS(expenses_min_row, COLUMN()) & ":" & ADDRESS(expenses_max_row, COLUMN())))} -> 0 | BL36: {=SUM(INDIRECT(ADDRESS(expenses_min_row, COLUMN()) & ":" & ADDRESS(expenses_max_row, COLUMN())))} -> 0 | BM36: {=SUM(INDIRECT(ADDRESS(expenses_min_row, COLUMN()) & ":" & ADDRESS(expenses_max_row, COLUMN())))} -> 0 | BN36: {=SUM(INDIRECT(ADDRESS(expenses_min_row, COLUMN()) & ":" & ADDRESS(expenses_max_row, COLUMN())))} -> 0 | BO36: {=SUM(INDIRECT(ADDRESS(expenses_min_row, COLUMN()) & ":" & ADDRESS(expenses_max_row, COLUMN())))} -> 0 | BP36: {=SUM(INDIRECT(ADDRESS(expenses_min_row, COLUMN()) & ":" & ADDRESS(expenses_max_row, COLUMN())))} -> 0 | ... BU36: {=SUM(INDIRECT(ADDRESS(expenses_min_row, COLUMN()) & ":" & ADDRESS(expenses_max_row, COLUMN())))} -> 0 | BW36: {=SUM(INDIRECT(ADDRESS(expenses_min_row, COLUMN()) & ":" & ADDRESS(expenses_max_row, COLUMN())))} -> 0 | BX36: {=SUM(INDIRECT(ADDRESS(expenses_min_row, COLUMN()) & ":" & ADDRESS(expenses_max_row, COLUMN())))} -> 0 | BY36: {=SUM(INDIRECT(ADDRESS(expenses_min_row, COLUMN()) & ":" & ADDRESS(expenses_max_row, COLUMN())))} -> 0 | BZ36: {=SUM(INDIRECT(ADDRESS(expenses_min_row, COLUMN()) & ":" & ADDRESS(expenses_max_row, COLUMN())))} -> 0 | CA36: {=SUM(INDIRECT(ADDRESS(expenses_min_row, COLUMN()) & ":" & ADDRESS(expenses_max_row, COLUMN())))} -> 0 | CB36: {=SUM(INDIRECT(ADDRESS(expenses_min_row, COLUMN()) & ":" & ADDRESS(expenses_max_row, COLUMN())))} -> 0 | CC36: {=SUM(INDIRECT(ADDRESS(expenses_min_row, COLUMN()) & ":" & ADDRESS(expenses_max_row, COLUMN())))} -> 0 | CD36: {=SUM(INDIRECT(ADDRESS(expenses_min_row, COLUMN()) & ":" & ADDRESS(expenses_max_row, COLUMN())))} -> 0 | ... CI36: {=SUM(INDIRECT(ADDRESS(expenses_min_row, COLUMN()) & ":" & ADDRESS(expenses_max_row, COLUMN())))} -> 0 | CK36: {=SUM(INDIRECT(ADDRESS(expenses_min_row, COLUMN()) & ":" & ADDRESS(expenses_max_row, COLUMN())))} -> 0 | CL36: {=SUM(INDIRECT(ADDRESS(expenses_min_row, COLUMN()) & ":" & ADDRESS(expenses_max_row, COLUMN())))} -> 0 | CM36: {=SUM(INDIRECT(ADDRESS(expenses_min_row, COLUMN()) & ":" & ADDRESS(expenses_max_row, COLUMN())))} -> 0 | CN36: {=SUM(INDIRECT(ADDRESS(expenses_min_row, COLUMN()) & ":" & ADDRESS(expenses_max_row, COLUMN())))} -> 0 | CO36: {=SUM(INDIRECT(ADDRESS(expenses_min_row, COLUMN()) & ":" & ADDRESS(expenses_max_row, COLUMN())))} -> 0 | CP36: {=SUM(INDIRECT(ADDRESS(expenses_min_row, COLUMN()) & ":" & ADDRESS(expenses_max_row, COLUMN())))} -> 0 | CQ36: {=SUM(INDIRECT(ADDRESS(expenses_min_row, COLUMN()) & ":" & ADDRESS(expenses_max_row, COLUMN())))} -> 0 | CR36: {=SUM(INDIRECT(ADDRESS(expenses_min_row, COLUMN()) & ":" & ADDRESS(expenses_max_row, COLUMN())))} -> 0 | ... CW36: {=SUM(INDIRECT(ADDRESS(expenses_min_row, COLUMN()) & ":" & ADDRESS(expenses_max_row, COLUMN())))} -> 0 | CY36: {=SUM(INDIRECT(ADDRESS(expenses_min_row, COLUMN()) & ":" & ADDRESS(expenses_max_row, COLUMN())))} -> 0 | CZ36: {=SUM(INDIRECT(ADDRESS(expenses_min_row, COLUMN()) & ":" & ADDRESS(expenses_max_row, COLUMN())))} -> 0 | DA36: {=SUM(INDIRECT(ADDRESS(expenses_min_row, COLUMN()) & ":" & ADDRESS(expenses_max_row, COLUMN())))} -> 0 | DB36: {=SUM(INDIRECT(ADDRESS(expenses_min_row, COLUMN()) & ":" & ADDRESS(expenses_max_row, COLUMN())))} -> 0 | DC36: {=SUM(INDIRECT(ADDRESS(expenses_min_row, COLUMN()) & ":" & ADDRESS(expenses_max_row, COLUMN())))} -> 0 | DD36: {=SUM(INDIRECT(ADDRESS(expenses_min_row, COLUMN()) & ":" & ADDRESS(expenses_max_row, COLUMN())))} -> 0 | DE36: {=SUM(INDIRECT(ADDRESS(expenses_min_row, COLUMN()) & ":" & ADDRESS(expenses_max_row, COLUMN())))} -> 0 | DF36: {=SUM(INDIRECT(ADDRESS(expenses_min_row, COLUMN()) & ":" & ADDRESS(expenses_max_row, COLUMN())))} -> 0 | ... DK36: {=SUM(INDIRECT(ADDRESS(expenses_min_row, COLUMN()) & ":" & ADDRESS(expenses_max_row, COLUMN())))} -> 0 | DM36: {=SUM(INDIRECT(ADDRESS(expenses_min_row, COLUMN()) & ":" & ADDRESS(expenses_max_row, COLUMN())))} -> 0 | DN36: {=SUM(INDIRECT(ADDRESS(expenses_min_row, COLUMN()) & ":" & ADDRESS(expenses_max_row, COLUMN())))} -> 0 | DO36: {=SUM(INDIRECT(ADDRESS(expenses_min_row, COLUMN()) & ":" & ADDRESS(expenses_max_row, COLUMN())))} -> 0 | DP36: {=SUM(INDIRECT(ADDRESS(expenses_min_row, COLUMN()) & ":" & ADDRESS(expenses_max_row, COLUMN())))} -> 0 | DQ36: {=SUM(INDIRECT(ADDRESS(expenses_min_row, COLUMN()) & ":" & ADDRESS(expenses_max_row, COLUMN())))} -> 0 | DR36: {=SUM(INDIRECT(ADDRESS(expenses_min_row, COLUMN()) & ":" & ADDRESS(expenses_max_row, COLUMN())))} -> 0 | DS36: {=SUM(INDIRECT(ADDRESS(expenses_min_row, COLUMN()) & ":" & ADDRESS(expenses_max_row, COLUMN())))} -> 0 | DT36: {=SUM(INDIRECT(ADDRESS(expenses_min_row, COLUMN()) & ":" & ADDRESS(expenses_max_row, COLUMN())))} -> 0 | ... DY36: {=SUM(INDIRECT(ADDRESS(expenses_min_row, COLUMN()) & ":" & ADDRESS(expenses_max_row, COLUMN())))} -> 0 | EA36: {=SUM(INDIRECT(ADDRESS(expenses_min_row, COLUMN()) & ":" & ADDRESS(expenses_max_row, COLUMN())))} -> 0 | EB36: {=SUM(INDIRECT(ADDRESS(expenses_min_row, COLUMN()) & ":" & ADDRESS(expenses_max_row, COLUMN())))} -> 0 | EC36: {=SUM(INDIRECT(ADDRESS(expenses_min_row, COLUMN()) & ":" & ADDRESS(expenses_max_row, COLUMN())))} -> 0 | ED36: {=SUM(INDIRECT(ADDRESS(expenses_min_row, COLUMN()) & ":" & ADDRESS(expenses_max_row, COLUMN())))} -> 0 | EE36: {=SUM(INDIRECT(ADDRESS(expenses_min_row, COLUMN()) & ":" & ADDRESS(expenses_max_row, COLUMN())))} -> 0 | EF36: {=SUM(INDIRECT(ADDRESS(expenses_min_row, COLUMN()) & ":" & ADDRESS(expenses_max_row, COLUMN())))} -> 0 | EG36: {=SUM(INDIRECT(ADDRESS(expenses_min_row, COLUMN()) & ":" & ADDRESS(expenses_max_row, COLUMN())))} -> 0 | EH36: {=SUM(INDIRECT(ADDRESS(expenses_min_row, COLUMN()) & ":" & ADDRESS(expenses_max_row, COLUMN())))} -> 0 | ... EM36: {=SUM(INDIRECT(ADDRESS(expenses_min_row, COLUMN()) & ":" & ADDRESS(expenses_max_row, COLUMN())))} -> 0 | EO36: {=SUM(INDIRECT(ADDRESS(expenses_min_row, COLUMN()) & ":" & ADDRESS(expenses_max_row, COLUMN())))} -> 0 | EP36: {=SUM(INDIRECT(ADDRESS(expenses_min_row, COLUMN()) & ":" & ADDRESS(expenses_max_row, COLUMN())))} -> 0 | EQ36: {=SUM(INDIRECT(ADDRESS(expenses_min_row, COLUMN()) & ":" & ADDRESS(expenses_max_row, COLUMN())))} -> 0 | ER36: {=SUM(INDIRECT(ADDRESS(expenses_min_row, COLUMN()) & ":" & ADDRESS(expenses_max_row, COLUMN())))} -> 0 | ES36: {=SUM(INDIRECT(ADDRESS(expenses_min_row, COLUMN()) & ":" & ADDRESS(expenses_max_row, COLUMN())))} -> 0 | ET36: {=SUM(INDIRECT(ADDRESS(expenses_min_row, COLUMN()) & ":" & ADDRESS(expenses_max_row, COLUMN())))} -> 0 | EU36: {=SUM(INDIRECT(ADDRESS(expenses_min_row, COLUMN()) & ":" & ADDRESS(expenses_max_row, COLUMN())))} -> 0 | EV36: {=SUM(INDIRECT(ADDRESS(expenses_min_row, COLUMN()) & ":" & ADDRESS(expenses_max_row, COLUMN())))} -> 0 | ... FA36: {=SUM(INDIRECT(ADDRESS(expenses_min_row, COLUMN()) & ":" & ADDRESS(expenses_max_row, COLUMN())))} -> 0
C38: Savings | E38: =DATE(E$5, 1, 1) -> 45658 | F38: =DATE(E$5, 2, 1) -> 45689 | G38: =DATE(E$5, 3, 1) -> 45717 | H38: =DATE(E$5, 4, 1) -> 45748 | I38: =DATE(E$5, 5, 1) -> 45778 | J38: =DATE(E$5, 6, 1) -> 45809 | K38: =DATE(E$5, 7, 1) -> 45839 | L38: =DATE(E$5, 8, 1) -> 45870 | M38: =DATE(E$5, 9, 1) -> 45901 | N38: =DATE(E$5, 10, 1) -> 45931 | O38: =DATE(E$5, 11, 1) -> 45962 | P38: =DATE(E$5, 12, 1) -> 45992 | Q38: =E$5 -> 2025 | S38: =DATE(S$5, 1, 1) -> 46023 | T38: =DATE(S$5, 2, 1) -> 46054 | U38: =DATE(S$5, 3, 1) -> 46082 | V38: =DATE(S$5, 4, 1) -> 46113 | W38: =DATE(S$5, 5, 1) -> 46143 | X38: =DATE(S$5, 6, 1) -> 46174 | Y38: =DATE(S$5, 7, 1) -> 46204 | Z38: =DATE(S$5, 8, 1) -> 46235 | AA38: =DATE(S$5, 9, 1) -> 46266 | AB38: =DATE(S$5, 10, 1) -> 46296 | AC38: =DATE(S$5, 11, 1) -> 46327 | AD38: =DATE(S$5, 12, 1) -> 46357 | AE38: =S$5 -> 2026 | AG38: =DATE(AG$5, 1, 1) -> 46388 | AH38: =DATE(AG$5, 2, 1) -> 46419 | AI38: =DATE(AG$5, 3, 1) -> 46447 | AJ38: =DATE(AG$5, 4, 1) -> 46478 | AK38: =DATE(AG$5, 5, 1) -> 46508 | AL38: =DATE(AG$5, 6, 1) -> 46539 | AM38: =DATE(AG$5, 7, 1) -> 46569 | AN38: =DATE(AG$5, 8, 1) -> 46600 | AO38: =DATE(AG$5, 9, 1) -> 46631 | AP38: =DATE(AG$5, 10, 1) -> 46661 | AQ38: =DATE(AG$5, 11, 1) -> 46692 | AR38: =DATE(AG$5, 12, 1) -> 46722 | AS38: =AG$5 -> 2027 | AU38: =DATE(AU$5, 1, 1) -> 46753 | AV38: =DATE(AU$5, 2, 1) -> 46784 | AW38: =DATE(AU$5, 3, 1) -> 46813 | AX38: =DATE(AU$5, 4, 1) -> 46844 | AY38: =DATE(AU$5, 5, 1) -> 46874 | AZ38: =DATE(AU$5, 6, 1) -> 46905 | BA38: =DATE(AU$5, 7, 1) -> 46935 | BB38: =DATE(AU$5, 8, 1) -> 46966 | BC38: =DATE(AU$5, 9, 1) -> 46997 | BD38: =DATE(AU$5, 10, 1) -> 47027 | BE38: =DATE(AU$5, 11, 1) -> 47058 | BF38: =DATE(AU$5, 12, 1) -> 47088 | BG38: =AU$5 -> 2028 | BI38: =DATE(BI$5, 1, 1) -> 47119 | BJ38: =DATE(BI$5, 2, 1) -> 47150 | BK38: =DATE(BI$5, 3, 1) -> 47178 | BL38: =DATE(BI$5, 4, 1) -> 47209 | BM38: =DATE(BI$5, 5, 1) -> 47239 | BN38: =DATE(BI$5, 6, 1) -> 47270 | BO38: =DATE(BI$5, 7, 1) -> 47300 | BP38: =DATE(BI$5, 8, 1) -> 47331 | BQ38: =DATE(BI$5, 9, 1) -> 47362 | BR38: =DATE(BI$5, 10, 1) -> 47392 | BS38: =DATE(BI$5, 11, 1) -> 47423 | BT38: =DATE(BI$5, 12, 1) -> 47453 | BU38: =BI$5 -> 2029 | BW38: =DATE(BW$5, 1, 1) -> 47484 | BX38: =DATE(BW$5, 2, 1) -> 47515 | BY38: =DATE(BW$5, 3, 1) -> 47543 | BZ38: =DATE(BW$5, 4, 1) -> 47574 | CA38: =DATE(BW$5, 5, 1) -> 47604 | CB38: =DATE(BW$5, 6, 1) -> 47635 | CC38: =DATE(BW$5, 7, 1) -> 47665 | CD38: =DATE(BW$5, 8, 1) -> 47696 | CE38: =DATE(BW$5, 9, 1) -> 47727 | CF38: =DATE(BW$5, 10, 1) -> 47757 | CG38: =DATE(BW$5, 11, 1) -> 47788 | CH38: =DATE(BW$5, 12, 1) -> 47818 | CI38: =BW$5 -> 2030 | CK38: =DATE(CK$5, 1, 1) -> 47849 | CL38: =DATE(CK$5, 2, 1) -> 47880 | CM38: =DATE(CK$5, 3, 1) -> 47908 | CN38: =DATE(CK$5, 4, 1) -> 47939 | CO38: =DATE(CK$5, 5, 1) -> 47969 | CP38: =DATE(CK$5, 6, 1) -> 48000 | CQ38: =DATE(CK$5, 7, 1) -> 48030 | CR38: =DATE(CK$5, 8, 1) -> 48061 | CS38: =DATE(CK$5, 9, 1) -> 48092 | CT38: =DATE(CK$5, 10, 1) -> 48122 | CU38: =DATE(CK$5, 11, 1) -> 48153 | CV38: =DATE(CK$5, 12, 1) -> 48183 | CW38: =CK$5 -> 2031 | CY38: =DATE(CY$5, 1, 1) -> 48214 | CZ38: =DATE(CY$5, 2, 1) -> 48245 | DA38: =DATE(CY$5, 3, 1) -> 48274 | DB38: =DATE(CY$5, 4, 1) -> 48305 | DC38: =DATE(CY$5, 5, 1) -> 48335 | DD38: =DATE(CY$5, 6, 1) -> 48366 | DE38: =DATE(CY$5, 7, 1) -> 48396 | DF38: =DATE(CY$5, 8, 1) -> 48427 | DG38: =DATE(CY$5, 9, 1) -> 48458 | DH38: =DATE(CY$5, 10, 1) -> 48488 | DI38: =DATE(CY$5, 11, 1) -> 48519 | DJ38: =DATE(CY$5, 12, 1) -> 48549 | DK38: =CY$5 -> 2032 | DM38: =DATE(DM$5, 1, 1) -> 48580 | DN38: =DATE(DM$5, 2, 1) -> 48611 | DO38: =DATE(DM$5, 3, 1) -> 48639 | DP38: =DATE(DM$5, 4, 1) -> 48670 | DQ38: =DATE(DM$5, 5, 1) -> 48700 | DR38: =DATE(DM$5, 6, 1) -> 48731 | DS38: =DATE(DM$5, 7, 1) -> 48761 | DT38: =DATE(DM$5, 8, 1) -> 48792 | DU38: =DATE(DM$5, 9, 1) -> 48823 | DV38: =DATE(DM$5, 10, 1) -> 48853 | DW38: =DATE(DM$5, 11, 1) -> 48884 | DX38: =DATE(DM$5, 12, 1) -> 48914 | DY38: =DM$5 -> 2033 | EA38: =DATE(EA$5, 1, 1) -> 48945 | EB38: =DATE(EA$5, 2, 1) -> 48976 | EC38: =DATE(EA$5, 3, 1) -> 49004 | ED38: =DATE(EA$5, 4, 1) -> 49035 | EE38: =DATE(EA$5, 5, 1) -> 49065 | EF38: =DATE(EA$5, 6, 1) -> 49096 | EG38: =DATE(EA$5, 7, 1) -> 49126 | EH38: =DATE(EA$5, 8, 1) -> 49157 | EI38: =DATE(EA$5, 9, 1) -> 49188 | EJ38: =DATE(EA$5, 10, 1) -> 49218 | EK38: =DATE(EA$5, 11, 1) -> 49249 | EL38: =DATE(EA$5, 12, 1) -> 49279 | EM38: =EA$5 -> 2034 | EO38: =DATE(EO$5, 1, 1) -> 49310 | EP38: =DATE(EO$5, 2, 1) -> 49341 | EQ38: =DATE(EO$5, 3, 1) -> 49369 | ER38: =DATE(EO$5, 4, 1) -> 49400 | ES38: =DATE(EO$5, 5, 1) -> 49430 | ET38: =DATE(EO$5, 6, 1) -> 49461 | EU38: =DATE(EO$5, 7, 1) -> 49491 | EV38: =DATE(EO$5, 8, 1) -> 49522 | EW38: =DATE(EO$5, 9, 1) -> 49553 | EX38: =DATE(EO$5, 10, 1) -> 49583 | EY38: =DATE(EO$5, 11, 1) -> 49614 | EZ38: =DATE(EO$5, 12, 1) -> 49644 | FA38: =EO$5 -> 2035
C39: Emergency Fund | E39: 1000 | F39: 1000 | G39: 1000 | Q39: =SUM(E39:P39) -> 3000 | AE39: =SUM(S39:AD39) -> 0 | AS39: =SUM(AG39:AR39) -> 0 | BG39: =SUM(AU39:BF39) -> 0 | BU39: =SUM(BI39:BT39) -> 0 | CI39: =SUM(BW39:CH39) -> 0 | CW39: =SUM(CK39:CV39) -> 0 | DK39: =SUM(CY39:DJ39) -> 0 | DY39: =SUM(DM39:DX39) -> 0 | EM39: =SUM(EA39:EL39) -> 0 | FA39: =SUM(EO39:EZ39) -> 0
C40: Retirement Account | E40: 400 | F40: 400 | G40: 400 | H40: 400 | I40: 400 | J40: 400 | K40: 400 | L40: 400 | M40: 400 | N40: 400 | O40: 400 | P40: 400 | Q40: =SUM(E40:P40) -> 4800 | AE40: =SUM(S40:AD40) -> 0 | AS40: =SUM(AG40:AR40) -> 0 | BG40: =SUM(AU40:BF40) -> 0 | BU40: =SUM(BI40:BT40) -> 0 | CI40: =SUM(BW40:CH40) -> 0 | CW40: =SUM(CK40:CV40) -> 0 | DK40: =SUM(CY40:DJ40) -> 0 | DY40: =SUM(DM40:DX40) -> 0 | EM40: =SUM(EA40:EL40) -> 0 | FA40: =SUM(EO40:EZ40) -> 0
C41: Stock Portfolio | E41: 150 | F41: 150 | G41: 150 | H41: 750 | I41: 750 | J41: 750 | K41: 750 | L41: 750 | M41: 750 | N41: 750 | O41: 750 | P41: 750 | Q41: =SUM(E41:P41) -> 7200 | AE41: =SUM(S41:AD41) -> 0 | AS41: =SUM(AG41:AR41) -> 0 | BG41: =SUM(AU41:BF41) -> 0 | BU41: =SUM(BI41:BT41) -> 0 | CI41: =SUM(BW41:CH41) -> 0 | CW41: =SUM(CK41:CV41) -> 0 | DK41: =SUM(CY41:DJ41) -> 0 | DY41: =SUM(DM41:DX41) -> 0 | EM41: =SUM(EA41:EL41) -> 0 | FA41: =SUM(EO41:EZ41) -> 0
C42: Sinking Fund Down Payment | H42: 600 | I42: 1400 | J42: 1300 | K42: 1500 | L42: 200 | M42: 1300 | N42: 1500 | O42: 1400 | P42: 1000 | Q42: =SUM(E42:P42) -> 10200 | AE42: =SUM(S42:AD42) -> 0 | AS42: =SUM(AG42:AR42) -> 0 | BG42: =SUM(AU42:BF42) -> 0 | BU42: =SUM(BI42:BT42) -> 0 | CI42: =SUM(BW42:CH42) -> 0 | CW42: =SUM(CK42:CV42) -> 0 | DK42: =SUM(CY42:DJ42) -> 0 | DY42: =SUM(DM42:DX42) -> 0 | EM42: =SUM(EA42:EL42) -> 0 | FA42: =SUM(EO42:EZ42) -> 0
C43: Sinking Fund Rest | E43: 200 | F43: 100 | H43: 100 | I43: 100 | J43: 100 | K43: 100 | L43: 100 | M43: 100 | N43: 100 | O43: 100 | P43: 100 | Q43: =SUM(E43:P43) -> 1200 | AE43: =SUM(S43:AD43) -> 0 | AS43: =SUM(AG43:AR43) -> 0 | BG43: =SUM(AU43:BF43) -> 0 | BU43: =SUM(BI43:BT43) -> 0 | CI43: =SUM(BW43:CH43) -> 0 | CW43: =SUM(CK43:CV43) -> 0 | DK43: =SUM(CY43:DJ43) -> 0 | DY43: =SUM(DM43:DX43) -> 0 | EM43: =SUM(EA43:EL43) -> 0 | FA43: =SUM(EO43:EZ43) -> 0
C44: Enter Savings Category... | Q44: =SUM(E44:P44) -> 0 | AE44: =SUM(S44:AD44) -> 0 | AS44: =SUM(AG44:AR44) -> 0 | BG44: =SUM(AU44:BF44) -> 0 | BU44: =SUM(BI44:BT44) -> 0 | CI44: =SUM(BW44:CH44) -> 0 | CW44: =SUM(CK44:CV44) -> 0 | DK44: =SUM(CY44:DJ44) -> 0 | DY44: =SUM(DM44:DX44) -> 0 | EM44: =SUM(EA44:EL44) -> 0 | FA44: =SUM(EO44:EZ44) -> 0
C45: Enter Savings Category... | Q45: =SUM(E45:P45) -> 0 | AE45: =SUM(S45:AD45) -> 0 | AS45: =SUM(AG45:AR45) -> 0 | BG45: =SUM(AU45:BF45) -> 0 | BU45: =SUM(BI45:BT45) -> 0 | CI45: =SUM(BW45:CH45) -> 0 | CW45: =SUM(CK45:CV45) -> 0 | DK45: =SUM(CY45:DJ45) -> 0 | DY45: =SUM(DM45:DX45) -> 0 | EM45: =SUM(EA45:EL45) -> 0 | FA45: =SUM(EO45:EZ45) -> 0
C46: Enter Savings Category... | Q46: =SUM(E46:P46) -> 0 | AE46: =SUM(S46:AD46) -> 0 | AS46: =SUM(AG46:AR46) -> 0 | BG46: =SUM(AU46:BF46) -> 0 | BU46: =SUM(BI46:BT46) -> 0 | CI46: =SUM(BW46:CH46) -> 0 | CW46: =SUM(CK46:CV46) -> 0 | DK46: =SUM(CY46:DJ46) -> 0 | DY46: =SUM(DM46:DX46) -> 0 | EM46: =SUM(EA46:EL46) -> 0 | FA46: =SUM(EO46:EZ46) -> 0
C47: Enter Savings Category... | Q47: =SUM(E47:P47) -> 0 | AE47: =SUM(S47:AD47) -> 0 | AS47: =SUM(AG47:AR47) -> 0 | BG47: =SUM(AU47:BF47) -> 0 | BU47: =SUM(BI47:BT47) -> 0 | CI47: =SUM(BW47:CH47) -> 0 | CW47: =SUM(CK47:CV47) -> 0 | DK47: =SUM(CY47:DJ47) -> 0 | DY47: =SUM(DM47:DX47) -> 0 | EM47: =SUM(EA47:EL47) -> 0 | FA47: =SUM(EO47:EZ47) -> 0
C48: Enter Savings Category... | Q48: =SUM(E48:P48) -> 0 | AE48: =SUM(S48:AD48) -> 0 | AS48: =SUM(AG48:AR48) -> 0 | BG48: =SUM(AU48:BF48) -> 0 | BU48: =SUM(BI48:BT48) -> 0 | CI48: =SUM(BW48:CH48) -> 0 | CW48: =SUM(CK48:CV48) -> 0 | DK48: =SUM(CY48:DJ48) -> 0 | DY48: =SUM(DM48:DX48) -> 0 | EM48: =SUM(EA48:EL48) -> 0 | FA48: =SUM(EO48:EZ48) -> 0
C49: Total | E49: {=SUM(INDIRECT(ADDRESS(savings_min_row, COLUMN()) & ":" & ADDRESS(savings_max_row, COLUMN())))} -> 1750 | F49: {=SUM(INDIRECT(ADDRESS(savings_min_row, COLUMN()) & ":" & ADDRESS(savings_max_row, COLUMN())))} -> 1650 | G49: {=SUM(INDIRECT(ADDRESS(savings_min_row, COLUMN()) & ":" & ADDRESS(savings_max_row, COLUMN())))} -> 1550 | H49: {=SUM(INDIRECT(ADDRESS(savings_min_row, COLUMN()) & ":" & ADDRESS(savings_max_row, COLUMN())))} -> 1850 | I49: {=SUM(INDIRECT(ADDRESS(savings_min_row, COLUMN()) & ":" & ADDRESS(savings_max_row, COLUMN())))} -> 2650 | J49: {=SUM(INDIRECT(ADDRESS(savings_min_row, COLUMN()) & ":" & ADDRESS(savings_max_row, COLUMN())))} -> 2550 | K49: {=SUM(INDIRECT(ADDRESS(savings_min_row, COLUMN()) & ":" & ADDRESS(savings_max_row, COLUMN())))} -> 2750 | L49: {=SUM(INDIRECT(ADDRESS(savings_min_row, COLUMN()) & ":" & ADDRESS(savings_max_row, COLUMN())))} -> 1450 | ... Q49: {=SUM(INDIRECT(ADDRESS(savings_min_row, COLUMN()) & ":" & ADDRESS(savings_max_row, COLUMN())))} -> 26400 | S49: {=SUM(INDIRECT(ADDRESS(savings_min_row, COLUMN()) & ":" & ADDRESS(savings_max_row, COLUMN())))} -> 0 | T49: {=SUM(INDIRECT(ADDRESS(savings_min_row, COLUMN()) & ":" & ADDRESS(savings_max_row, COLUMN())))} -> 0 | U49: {=SUM(INDIRECT(ADDRESS(savings_min_row, COLUMN()) & ":" & ADDRESS(savings_max_row, COLUMN())))} -> 0 | V49: {=SUM(INDIRECT(ADDRESS(savings_min_row, COLUMN()) & ":" & ADDRESS(savings_max_row, COLUMN())))} -> 0 | W49: {=SUM(INDIRECT(ADDRESS(savings_min_row, COLUMN()) & ":" & ADDRESS(savings_max_row, COLUMN())))} -> 0 | X49: {=SUM(INDIRECT(ADDRESS(savings_min_row, COLUMN()) & ":" & ADDRESS(savings_max_row, COLUMN())))} -> 0 | Y49: {=SUM(INDIRECT(ADDRESS(savings_min_row, COLUMN()) & ":" & ADDRESS(savings_max_row, COLUMN())))} -> 0 | Z49: {=SUM(INDIRECT(ADDRESS(savings_min_row, COLUMN()) & ":" & ADDRESS(savings_max_row, COLUMN())))} -> 0 | ... AE49: {=SUM(INDIRECT(ADDRESS(savings_min_row, COLUMN()) & ":" & ADDRESS(savings_max_row, COLUMN())))} -> 0 | AG49: {=SUM(INDIRECT(ADDRESS(savings_min_row, COLUMN()) & ":" & ADDRESS(savings_max_row, COLUMN())))} -> 0 | AH49: {=SUM(INDIRECT(ADDRESS(savings_min_row, COLUMN()) & ":" & ADDRESS(savings_max_row, COLUMN())))} -> 0 | AI49: {=SUM(INDIRECT(ADDRESS(savings_min_row, COLUMN()) & ":" & ADDRESS(savings_max_row, COLUMN())))} -> 0 | AJ49: {=SUM(INDIRECT(ADDRESS(savings_min_row, COLUMN()) & ":" & ADDRESS(savings_max_row, COLUMN())))} -> 0 | AK49: {=SUM(INDIRECT(ADDRESS(savings_min_row, COLUMN()) & ":" & ADDRESS(savings_max_row, COLUMN())))} -> 0 | AL49: {=SUM(INDIRECT(ADDRESS(savings_min_row, COLUMN()) & ":" & ADDRESS(savings_max_row, COLUMN())))} -> 0 | AM49: {=SUM(INDIRECT(ADDRESS(savings_min_row, COLUMN()) & ":" & ADDRESS(savings_max_row, COLUMN())))} -> 0 | AN49: {=SUM(INDIRECT(ADDRESS(savings_min_row, COLUMN()) & ":" & ADDRESS(savings_max_row, COLUMN())))} -> 0 | ... AS49: {=SUM(INDIRECT(ADDRESS(savings_min_row, COLUMN()) & ":" & ADDRESS(savings_max_row, COLUMN())))} -> 0 | AU49: {=SUM(INDIRECT(ADDRESS(savings_min_row, COLUMN()) & ":" & ADDRESS(savings_max_row, COLUMN())))} -> 0 | AV49: {=SUM(INDIRECT(ADDRESS(savings_min_row, COLUMN()) & ":" & ADDRESS(savings_max_row, COLUMN())))} -> 0 | AW49: {=SUM(INDIRECT(ADDRESS(savings_min_row, COLUMN()) & ":" & ADDRESS(savings_max_row, COLUMN())))} -> 0 | AX49: {=SUM(INDIRECT(ADDRESS(savings_min_row, COLUMN()) & ":" & ADDRESS(savings_max_row, COLUMN())))} -> 0 | AY49: {=SUM(INDIRECT(ADDRESS(savings_min_row, COLUMN()) & ":" & ADDRESS(savings_max_row, COLUMN())))} -> 0 | AZ49: {=SUM(INDIRECT(ADDRESS(savings_min_row, COLUMN()) & ":" & ADDRESS(savings_max_row, COLUMN())))} -> 0 | BA49: {=SUM(INDIRECT(ADDRESS(savings_min_row, COLUMN()) & ":" & ADDRESS(savings_max_row, COLUMN())))} -> 0 | BB49: {=SUM(INDIRECT(ADDRESS(savings_min_row, COLUMN()) & ":" & ADDRESS(savings_max_row, COLUMN())))} -> 0 | ... BG49: {=SUM(INDIRECT(ADDRESS(savings_min_row, COLUMN()) & ":" & ADDRESS(savings_max_row, COLUMN())))} -> 0 | BI49: {=SUM(INDIRECT(ADDRESS(savings_min_row, COLUMN()) & ":" & ADDRESS(savings_max_row, COLUMN())))} -> 0 | BJ49: {=SUM(INDIRECT(ADDRESS(savings_min_row, COLUMN()) & ":" & ADDRESS(savings_max_row, COLUMN())))} -> 0 | BK49: {=SUM(INDIRECT(ADDRESS(savings_min_row, COLUMN()) & ":" & ADDRESS(savings_max_row, COLUMN())))} -> 0 | BL49: {=SUM(INDIRECT(ADDRESS(savings_min_row, COLUMN()) & ":" & ADDRESS(savings_max_row, COLUMN())))} -> 0 | BM49: {=SUM(INDIRECT(ADDRESS(savings_min_row, COLUMN()) & ":" & ADDRESS(savings_max_row, COLUMN())))} -> 0 | BN49: {=SUM(INDIRECT(ADDRESS(savings_min_row, COLUMN()) & ":" & ADDRESS(savings_max_row, COLUMN())))} -> 0 | BO49: {=SUM(INDIRECT(ADDRESS(savings_min_row, COLUMN()) & ":" & ADDRESS(savings_max_row, COLUMN())))} -> 0 | BP49: {=SUM(INDIRECT(ADDRESS(savings_min_row, COLUMN()) & ":" & ADDRESS(savings_max_row, COLUMN())))} -> 0 | ... BU49: {=SUM(INDIRECT(ADDRESS(savings_min_row, COLUMN()) & ":" & ADDRESS(savings_max_row, COLUMN())))} -> 0 | BW49: {=SUM(INDIRECT(ADDRESS(savings_min_row, COLUMN()) & ":" & ADDRESS(savings_max_row, COLUMN())))} -> 0 | BX49: {=SUM(INDIRECT(ADDRESS(savings_min_row, COLUMN()) & ":" & ADDRESS(savings_max_row, COLUMN())))} -> 0 | BY49: {=SUM(INDIRECT(ADDRESS(savings_min_row, COLUMN()) & ":" & ADDRESS(savings_max_row, COLUMN())))} -> 0 | BZ49: {=SUM(INDIRECT(ADDRESS(savings_min_row, COLUMN()) & ":" & ADDRESS(savings_max_row, COLUMN())))} -> 0 | CA49: {=SUM(INDIRECT(ADDRESS(savings_min_row, COLUMN()) & ":" & ADDRESS(savings_max_row, COLUMN())))} -> 0 | CB49: {=SUM(INDIRECT(ADDRESS(savings_min_row, COLUMN()) & ":" & ADDRESS(savings_max_row, COLUMN())))} -> 0 | CC49: {=SUM(INDIRECT(ADDRESS(savings_min_row, COLUMN()) & ":" & ADDRESS(savings_max_row, COLUMN())))} -> 0 | CD49: {=SUM(INDIRECT(ADDRESS(savings_min_row, COLUMN()) & ":" & ADDRESS(savings_max_row, COLUMN())))} -> 0 | ... CI49: {=SUM(INDIRECT(ADDRESS(savings_min_row, COLUMN()) & ":" & ADDRESS(savings_max_row, COLUMN())))} -> 0 | CK49: {=SUM(INDIRECT(ADDRESS(savings_min_row, COLUMN()) & ":" & ADDRESS(savings_max_row, COLUMN())))} -> 0 | CL49: {=SUM(INDIRECT(ADDRESS(savings_min_row, COLUMN()) & ":" & ADDRESS(savings_max_row, COLUMN())))} -> 0 | CM49: {=SUM(INDIRECT(ADDRESS(savings_min_row, COLUMN()) & ":" & ADDRESS(savings_max_row, COLUMN())))} -> 0 | CN49: {=SUM(INDIRECT(ADDRESS(savings_min_row, COLUMN()) & ":" & ADDRESS(savings_max_row, COLUMN())))} -> 0 | CO49: {=SUM(INDIRECT(ADDRESS(savings_min_row, COLUMN()) & ":" & ADDRESS(savings_max_row, COLUMN())))} -> 0 | CP49: {=SUM(INDIRECT(ADDRESS(savings_min_row, COLUMN()) & ":" & ADDRESS(savings_max_row, COLUMN())))} -> 0 | CQ49: {=SUM(INDIRECT(ADDRESS(savings_min_row, COLUMN()) & ":" & ADDRESS(savings_max_row, COLUMN())))} -> 0 | CR49: {=SUM(INDIRECT(ADDRESS(savings_min_row, COLUMN()) & ":" & ADDRESS(savings_max_row, COLUMN())))} -> 0 | ... CW49: {=SUM(INDIRECT(ADDRESS(savings_min_row, COLUMN()) & ":" & ADDRESS(savings_max_row, COLUMN())))} -> 0 | CY49: {=SUM(INDIRECT(ADDRESS(savings_min_row, COLUMN()) & ":" & ADDRESS(savings_max_row, COLUMN())))} -> 0 | CZ49: {=SUM(INDIRECT(ADDRESS(savings_min_row, COLUMN()) & ":" & ADDRESS(savings_max_row, COLUMN())))} -> 0 | DA49: {=SUM(INDIRECT(ADDRESS(savings_min_row, COLUMN()) & ":" & ADDRESS(savings_max_row, COLUMN())))} -> 0 | DB49: {=SUM(INDIRECT(ADDRESS(savings_min_row, COLUMN()) & ":" & ADDRESS(savings_max_row, COLUMN())))} -> 0 | DC49: {=SUM(INDIRECT(ADDRESS(savings_min_row, COLUMN()) & ":" & ADDRESS(savings_max_row, COLUMN())))} -> 0 | DD49: {=SUM(INDIRECT(ADDRESS(savings_min_row, COLUMN()) & ":" & ADDRESS(savings_max_row, COLUMN())))} -> 0 | DE49: {=SUM(INDIRECT(ADDRESS(savings_min_row, COLUMN()) & ":" & ADDRESS(savings_max_row, COLUMN())))} -> 0 | DF49: {=SUM(INDIRECT(ADDRESS(savings_min_row, COLUMN()) & ":" & ADDRESS(savings_max_row, COLUMN())))} -> 0 | ... DK49: {=SUM(INDIRECT(ADDRESS(savings_min_row, COLUMN()) & ":" & ADDRESS(savings_max_row, COLUMN())))} -> 0 | DM49: {=SUM(INDIRECT(ADDRESS(savings_min_row, COLUMN()) & ":" & ADDRESS(savings_max_row, COLUMN())))} -> 0 | DN49: {=SUM(INDIRECT(ADDRESS(savings_min_row, COLUMN()) & ":" & ADDRESS(savings_max_row, COLUMN())))} -> 0 | DO49: {=SUM(INDIRECT(ADDRESS(savings_min_row, COLUMN()) & ":" & ADDRESS(savings_max_row, COLUMN())))} -> 0 | DP49: {=SUM(INDIRECT(ADDRESS(savings_min_row, COLUMN()) & ":" & ADDRESS(savings_max_row, COLUMN())))} -> 0 | DQ49: {=SUM(INDIRECT(ADDRESS(savings_min_row, COLUMN()) & ":" & ADDRESS(savings_max_row, COLUMN())))} -> 0 | DR49: {=SUM(INDIRECT(ADDRESS(savings_min_row, COLUMN()) & ":" & ADDRESS(savings_max_row, COLUMN())))} -> 0 | DS49: {=SUM(INDIRECT(ADDRESS(savings_min_row, COLUMN()) & ":" & ADDRESS(savings_max_row, COLUMN())))} -> 0 | DT49: {=SUM(INDIRECT(ADDRESS(savings_min_row, COLUMN()) & ":" & ADDRESS(savings_max_row, COLUMN())))} -> 0 | ... DY49: {=SUM(INDIRECT(ADDRESS(savings_min_row, COLUMN()) & ":" & ADDRESS(savings_max_row, COLUMN())))} -> 0 | EA49: {=SUM(INDIRECT(ADDRESS(savings_min_row, COLUMN()) & ":" & ADDRESS(savings_max_row, COLUMN())))} -> 0 | EB49: {=SUM(INDIRECT(ADDRESS(savings_min_row, COLUMN()) & ":" & ADDRESS(savings_max_row, COLUMN())))} -> 0 | EC49: {=SUM(INDIRECT(ADDRESS(savings_min_row, COLUMN()) & ":" & ADDRESS(savings_max_row, COLUMN())))} -> 0 | ED49: {=SUM(INDIRECT(ADDRESS(savings_min_row, COLUMN()) & ":" & ADDRESS(savings_max_row, COLUMN())))} -> 0 | EE49: {=SUM(INDIRECT(ADDRESS(savings_min_row, COLUMN()) & ":" & ADDRESS(savings_max_row, COLUMN())))} -> 0 | EF49: {=SUM(INDIRECT(ADDRESS(savings_min_row, COLUMN()) & ":" & ADDRESS(savings_max_row, COLUMN())))} -> 0 | EG49: {=SUM(INDIRECT(ADDRESS(savings_min_row, COLUMN()) & ":" & ADDRESS(savings_max_row, COLUMN())))} -> 0 | EH49: {=SUM(INDIRECT(ADDRESS(savings_min_row, COLUMN()) & ":" & ADDRESS(savings_max_row, COLUMN())))} -> 0 | ... EM49: {=SUM(INDIRECT(ADDRESS(savings_min_row, COLUMN()) & ":" & ADDRESS(savings_max_row, COLUMN())))} -> 0 | EO49: {=SUM(INDIRECT(ADDRESS(savings_min_row, COLUMN()) & ":" & ADDRESS(savings_max_row, COLUMN())))} -> 0 | EP49: {=SUM(INDIRECT(ADDRESS(savings_min_row, COLUMN()) & ":" & ADDRESS(savings_max_row, COLUMN())))} -> 0 | EQ49: {=SUM(INDIRECT(ADDRESS(savings_min_row, COLUMN()) & ":" & ADDRESS(savings_max_row, COLUMN())))} -> 0 | ER49: {=SUM(INDIRECT(ADDRESS(savings_min_row, COLUMN()) & ":" & ADDRESS(savings_max_row, COLUMN())))} -> 0 | ES49: {=SUM(INDIRECT(ADDRESS(savings_min_row, COLUMN()) & ":" & ADDRESS(savings_max_row, COLUMN())))} -> 0 | ET49: {=SUM(INDIRECT(ADDRESS(savings_min_row, COLUMN()) & ":" & ADDRESS(savings_max_row, COLUMN())))} -> 0 | EU49: {=SUM(INDIRECT(ADDRESS(savings_min_row, COLUMN()) & ":" & ADDRESS(savings_max_row, COLUMN())))} -> 0 | EV49: {=SUM(INDIRECT(ADDRESS(savings_min_row, COLUMN()) & ":" & ADDRESS(savings_max_row, COLUMN())))} -> 0 | ... FA49: {=SUM(INDIRECT(ADDRESS(savings_min_row, COLUMN()) & ":" & ADDRESS(savings_max_row, COLUMN())))} -> 0

Sheet Budget Tracking
C11: Date | D11: Type | E11: Category | F11: Amount | G11: Details | H11: Balance | I11: Effective Date
C12: 45651 | D12: Income | E12: Employment (Net) | F12: 3500 | H12: {=SUMPRODUCT(Tracking[Amount], --(Tracking[[Date ]]<=Tracking[[#This Row],[Date ]]), (Tracking[Type]<>"Income")*(-1) + (Tracking[Type]="Income"))} -> 3500 | I12: =IF(AND(Tracking[[#This Row],[Type]]="Income", shift_late_income_status="Yes(Active)", DAY(Tracking[[#This Row],[Date ]])>=shift_late_income_starting_day), DATE(YEAR(Tracking[[#This Row],[Date ]]), MONTH(Tracking[[#This Row],[Date ]])+1, 1), Tracking[[#This Row],[Date ]]) -> 45658
C13: 45659 | D13: Expenses | E13: Housing | F13: 1200 | H13: {=SUMPRODUCT(Tracking[Amount], --(Tracking[[Date ]]<=Tracking[[#This Row],[Date ]]), (Tracking[Type]<>"Income")*(-1) + (Tracking[Type]="Income"))} -> 2300 | I13: =IF(AND(Tracking[[#This Row],[Type]]="Income", shift_late_income_status="Yes(Active)", DAY(Tracking[[#This Row],[Date ]])>=shift_late_income_starting_day), DATE(YEAR(Tracking[[#This Row],[Date ]]), MONTH(Tracking[[#This Row],[Date ]])+1, 1), Tracking[[#This Row],[Date ]]) -> 45659
C14: 45660 | D14: Expenses | E14: Clothing | F14: 150 | H14: {=SUMPRODUCT(Tracking[Amount], --(Tracking[[Date ]]<=Tracking[[#This Row],[Date ]]), (Tracking[Type]<>"Income")*(-1) + (Tracking[Type]="Income"))} -> 2150 | I14: =IF(AND(Tracking[[#This Row],[Type]]="Income", shift_late_income_status="Yes(Active)", DAY(Tracking[[#This Row],[Date ]])>=shift_late_income_starting_day), DATE(YEAR(Tracking[[#This Row],[Date ]]), MONTH(Tracking[[#This Row],[Date ]])+1, 1), Tracking[[#This Row],[Date ]]) -> 45660
C15: 45661 | D15: Savings | E15: Emergency Fund | F15: 1000 | H15: {=SUMPRODUCT(Tracking[Amount], --(Tracking[[Date ]]<=Tracking[[#This Row],[Date ]]), (Tracking[Type]<>"Income")*(-1) + (Tracking[Type]="Income"))} -> 1150 | I15: =IF(AND(Tracking[[#This Row],[Type]]="Income", shift_late_income_status="Yes(Active)", DAY(Tracking[[#This Row],[Date ]])>=shift_late_income_starting_day), DATE(YEAR(Tracking[[#This Row],[Date ]]), MONTH(Tracking[[#This Row],[Date ]])+1, 1), Tracking[[#This Row],[Date ]]) -> 45661
C16: 45662 | D16: Expenses | E16: Utilites | F16: 300 | H16: {=SUMPRODUCT(Tracking[Amount], --(Tracking[[Date ]]<=Tracking[[#This Row],[Date ]]), (Tracking[Type]<>"Income")*(-1) + (Tracking[Type]="Income"))} -> 850 | I16: =IF(AND(Tracking[[#This Row],[Type]]="Income", shift_late_income_status="Yes(Active)", DAY(Tracking[[#This Row],[Date ]])>=shift_late_income_starting_day), DATE(YEAR(Tracking[[#This Row],[Date ]]), MONTH(Tracking[[#This Row],[Date ]])+1, 1), Tracking[[#This Row],[Date ]]) -> 45662
C17: 45664 | D17: Expenses | E17: Groceries | F17: 120 | H17: {=SUMPRODUCT(Tracking[Amount], --(Tracking[[Date ]]<=Tracking[[#This Row],[Date ]]), (Tracking[Type]<>"Income")*(-1) + (Tracking[Type]="Income"))} -> 730 | I17: =IF(AND(Tracking[[#This Row],[Type]]="Income", shift_late_income_status="Yes(Active)", DAY(Tracking[[#This Row],[Date ]])>=shift_late_income_starting_day), DATE(YEAR(Tracking[[#This Row],[Date ]]), MONTH(Tracking[[#This Row],[Date ]])+1, 1), Tracking[[#This Row],[Date ]]) -> 45664
C18: 45666 | D18: Expenses | E18: Transportation | F18: 80 | H18: {=SUMPRODUCT(Tracking[Amount], --(Tracking[[Date ]]<=Tracking[[#This Row],[Date ]]), (Tracking[Type]<>"Income")*(-1) + (Tracking[Type]="Income"))} -> 650 | I18: =IF(AND(Tracking[[#This Row],[Type]]="Income", shift_late_income_status="Yes(Active)", DAY(Tracking[[#This Row],[Date ]])>=shift_late_income_starting_day), DATE(YEAR(Tracking[[#This Row],[Date ]]), MONTH(Tracking[[#This Row],[Date ]])+1, 1), Tracking[[#This Row],[Date ]]) -> 45666
C19: 45667 | D19: Expenses | E19: Fun & Vacation | F19: 120 | H19: {=SUMPRODUCT(Tracking[Amount], --(Tracking[[Date ]]<=Tracking[[#This Row],[Date ]]), (Tracking[Type]<>"Income")*(-1) + (Tracking[Type]="Income"))} -> 680 | I19: =IF(AND(Tracking[[#This Row],[Type]]="Income", shift_late_income_status="Yes(Active)", DAY(Tracking[[#This Row],[Date ]])>=shift_late_income_starting_day), DATE(YEAR(Tracking[[#This Row],[Date ]]), MONTH(Tracking[[#This Row],[Date ]])+1, 1), Tracking[[#This Row],[Date ]]) -> 45667
C20: 45667 | D20: Income | E20: Dividends | F20: 150 | H20: {=SUMPRODUCT(Tracking[Amount], --(Tracking[[Date ]]<=Tracking[[#This Row],[Date ]]), (Tracking[Type]<>"Income")*(-1) + (Tracking[Type]="Income"))} -> 680 | I20: =IF(AND(Tracking[[#This Row],[Type]]="Income", shift_late_income_status="Yes(Active)", DAY(Tracking[[#This Row],[Date ]])>=shift_late_income_starting_day), DATE(YEAR(Tracking[[#This Row],[Date ]]), MONTH(Tracking[[#This Row],[Date ]])+1, 1), Tracking[[#This Row],[Date ]]) -> 45667
C21: 45669 | D21: Expenses | E21: Media | F21: 50 | H21: {=SUMPRODUCT(Tracking[Amount], --(Tracking[[Date ]]<=Tracking[[#This Row],[Date ]]), (Tracking[Type]<>"Income")*(-1) + (Tracking[Type]="Income"))} -> 630 | I21: =IF(AND(Tracking[[#This Row],[Type]]="Income", shift_late_income_status="Yes(Active)", DAY(Tracking[[#This Row],[Date ]])>=shift_late_income_starting_day), DATE(YEAR(Tracking[[#This Row],[Date ]]), MONTH(Tracking[[#This Row],[Date ]])+1, 1), Tracking[[#This Row],[Date ]]) -> 45669
C22: 45670 | D22: Expenses | E22: Body Care & Medicine | F22: 70 | H22: {=SUMPRODUCT(Tracking[Amount], --(Tracking[[Date ]]<=Tracking[[#This Row],[Date ]]), (Tracking[Type]<>"Income")*(-1) + (Tracking[Type]="Income"))} -> 560 | I22: =IF(AND(Tracking[[#This Row],[Type]]="Income", shift_late_income_status="Yes(Active)", DAY(Tracking[[#This Row],[Date ]])>=shift_late_income_starting_day), DATE(YEAR(Tracking[[#This Row],[Date ]]), MONTH(Tracking[[#This Row],[Date ]])+1, 1), Tracking[[#This Row],[Date ]]) -> 45670
C23: 45671 | D23: Expenses | E23: Groceries | F23: 80 | H23: {=SUMPRODUCT(Tracking[Amount], --(Tracking[[Date ]]<=Tracking[[#This Row],[Date ]]), (Tracking[Type]<>"Income")*(-1) + (Tracking[Type]="Income"))} -> 480 | I23: =IF(AND(Tracking[[#This Row],[Type]]="Income", shift_late_income_status="Yes(Active)", DAY(Tracking[[#This Row],[Date ]])>=shift_late_income_starting_day), DATE(YEAR(Tracking[[#This Row],[Date ]]), MONTH(Tracking[[#This Row],[Date ]])+1, 1), Tracking[[#This Row],[Date ]]) -> 45671
... C70: 45731 | D70: Income | E70: Side Hustle (Net) | F70: 1100 | H70: {=SUMPRODUCT(Tracking[Amount], --(Tracking[[Date ]]<=Tracking[[#This Row],[Date ]]), (Tracking[Type]<>"Income")*(-1) + (Tracking[Type]="Income"))} -> 2620 | I70: =IF(AND(Tracking[[#This Row],[Type]]="Income", shift_late_income_status="Yes(Active)", DAY(Tracking[[#This Row],[Date ]])>=shift_late_income_starting_day), DATE(YEAR(Tracking[[#This Row],[Date ]]), MONTH(Tracking[[#This Row],[Date ]])+1, 1), Tracking[[#This Row],[Date ]]) -> 45731

Sheet Budget Dashboard
AQ5: Year
AN6: Select the year to view → | AQ6: Current Year
AQ8: Period
AN9: Select the period to view → | AQ9: Total Year
Y11: =AF11 -> Summary - 2025(Total Year) | AF11: ="Summary - " & IF(selected_period="Total Year", selected_year & "(Total Year)", selected_period_display & " " & selected_year) -> Summary - 2025(Total Year)
C12: row_id | D12: header_row_id | E12: is_header | F12: is_category | G12: is_total | H12: is_empty | I12: type | J12: item | K12: tracked | L12: budget | M12: sort_min_row | N12: sort_max_row | O12: tracked_range | P12: tracker_rank | Q12: budget_range | R12: budget_rank | S12: combined_rank | T12: combined_rank_range | U12: combined_rank_norm | V12: combined_rank_norm_run_range | W12: combined_rank_unique | X12: sorted_row_id [Lookup]
C13: 9 | D13: =IF(is_header, row_id, IF(NOT(is_empty), D12, -1)) -> 9 | E13: {=1*OR(row_id=income_header_row, row_id=expenses_header_row, row_id=savings_header_row)} -> 1 | F13: =1*NOT(OR(is_header, is_total, is_empty)) -> 0 | G13: {=1*OR(row_id=income_total_row, row_id=expenses_total_row, row_id=savings_total_row)} -> 0 | H13: =1*OR(row_id="/1", row_id="/2", row_id=-1) -> 0 | I13: {=IFERROR(INDEX('Budget Planning'!$C:$C, header_row_id), "")} -> Income | J13: {=IFERROR(INDEX('Budget Planning'!$C:$C, row_id), "")} -> Income | K13: {=IF(OR(is_header, is_empty), "", IF(is_total, IF(selected_period="Total Year", SUM(Tracking[Amount] * (Tracking[Type]=type) * (YEAR(Tracking[Effective Date])=selected_year)), SUM(Tracking[Amount] * (Tracking[Type]=type) * (YEAR(Tracking[Effective Date])=selected_year) * (MONTH(Tracking[Effective Date])=selected_period))), IF(selected_period="Total Year", SUM(Tracking[Amount] * (Tracking[Type]=type) * (Tracking[Category]=item) * (YEAR(Tracking[Effective Date])=selected_year)), SUM(Tracking[Amount] * (Tracking[Type]=type) * (Tracking[Category]=item) * (YEAR(Tracking[Effective Date])=selected_year) * (MONTH(Tracking[Effective Date])=selected_period)))))} | L13: {=IF(OR(is_header, is_empty), "", INDEX('Budget Planning'!$E:$EM, row_id, MATCH(IF(selected_period="Total Year", selected_year, DATE(selected_year, selected_period, 1)), 'Budget Planning'!$E$9:$EM$9, 0)))} | M13: {=IF(is_category, IF(header_row_id=income_header_row, MATCH(income_min_row, $C:$C, 0), IF(header_row_id=expenses_header_row, MATCH(expenses_min_row, $C:$C, 0), IF(header_row_id=savings_header_row, MATCH(savings_min_row, $C:$C, 0), ""))), "")} | N13: {=IF(is_category, IF(header_row_id=income_header_row, MATCH(income_max_row, $C:$C, 0), IF(header_row_id=expenses_header_row, MATCH(expenses_max_row, $C:$C, 0), IF(header_row_id=savings_header_row, MATCH(savings_max_row, $C:$C, 0), ""))), "")} | O13: =IF(is_category, ADDRESS(sort_min_row, COLUMN(tracked)) & ":" & ADDRESS(sort_max_row, COLUMN(tracked)), "") | P13: =IF(is_category, RANK(tracked, INDIRECT(tracked_range), 0), "") | Q13: =IF(is_category, ADDRESS(sort_min_row, COLUMN(budget)) & ":" & ADDRESS(sort_max_row, COLUMN(budget)), "") | R13: =IF(is_category, RANK(budget, INDIRECT(budget_range), 0), "") | S13: =IF(is_category, _xlfn.NUMBERVALUE(tracker_rank & budget_rank), "") | T13: =IF(is_category, ADDRESS(sort_min_row, COLUMN(combined_rank)) & ":" & ADDRESS(sort_max_row, COLUMN(combined_rank)), "") | U13: =IF(is_category, RANK(combined_rank, INDIRECT(combined_rank_range), 1), "") | V13: =IF(is_category, ADDRESS(sort_min_row, COLUMN(combined_rank_norm)) & ":" & ADDRESS(ROW(), COLUMN(combined_rank_norm)), "") | W13: =IF(is_category, combined_rank_norm + COUNTIF(INDIRECT(combined_rank_norm_run_range), combined_rank_norm)-1, "") | X13: =IF(is_category, header_row_id + combined_rank_unique, row_id) -> 9 | Y13: =IF(is_empty, "", INDEX($J:$J, MATCH(row_id, $X:$X, 0))) -> Income | Z13: =IF(is_empty, "", IF(is_header, "Tracked", INDEX($K:$K, MATCH(row_id, $X:$X, 0)))) -> Tracked | AA13: =IF(is_empty, "", IF(is_header, "Budget", INDEX($L:$L, MATCH(row_id, $X:$X, 0)))) -> Budget | AB13: =IF(is_empty, "", IF(is_header, "% Compl.", IFERROR(out_tracked / out_budget, "-"))) -> % Compl. | AC13: =IF(is_empty, "", IF(is_header, "Remaining", IF(out_budget - out_tracked > 0, out_budget - out_tracked, 0))) -> Remaining | AD13: =IF(is_empty, "", IF(is_header, "Excess", IF(out_budget - out_tracked < 0, out_tracked - out_budget, 0))) -> Excess
C14: {=IF(C13=-1,-1, IF(C13<income_max_row, C13+1, IF(C13=income_max_row, income_total_row, IF(C13=income_total_row, "/1", IF(C13="/1", expenses_header_row, IF(C13<expenses_max_row, C13+1, IF(C13=expenses_max_row, expenses_total_row, IF(C13=expenses_total_row, "/2", IF(C13="/2", savings_header_row, IF(C13<savings_max_row, C13+1, IF(C13=savings_max_row, savings_total_row, -1)))))))))))} -> 10 | D14: =IF(is_header, row_id, IF(NOT(is_empty), D13, -1)) -> 9 | E14: {=1*OR(row_id=income_header_row, row_id=expenses_header_row, row_id=savings_header_row)} -> 0 | F14: =1*NOT(OR(is_header, is_total, is_empty)) -> 1 | G14: {=1*OR(row_id=income_total_row, row_id=expenses_total_row, row_id=savings_total_row)} -> 0 | H14: =1*OR(row_id="/1", row_id="/2", row_id=-1) -> 0 | I14: {=IFERROR(INDEX('Budget Planning'!$C:$C, header_row_id), "")} -> Income | J14: {=IFERROR(INDEX('Budget Planning'!$C:$C, row_id), "")} -> Employment (Net) | K14: {=IF(OR(is_header, is_empty), "", IF(is_total, IF(selected_period="Total Year", SUM(Tracking[Amount] * (Tracking[Type]=type) * (YEAR(Tracking[Effective Date])=selected_year)), SUM(Tracking[Amount] * (Tracking[Type]=type) * (YEAR(Tracking[Effective Date])=selected_year) * (MONTH(Tracking[Effective Date])=selected_period))), IF(selected_period="Total Year", SUM(Tracking[Amount] * (Tracking[Type]=type) * (Tracking[Category]=item) * (YEAR(Tracking[Effective Date])=selected_year)), SUM(Tracking[Amount] * (Tracking[Type]=type) * (Tracking[Category]=item) * (YEAR(Tracking[Effective Date])=selected_year) * (MONTH(Tracking[Effective Date])=selected_period)))))} -> 10500 | L14: {=IF(OR(is_header, is_empty), "", INDEX('Budget Planning'!$E:$EM, row_id, MATCH(IF(selected_period="Total Year", selected_year, DATE(selected_year, selected_period, 1)), 'Budget Planning'!$E$9:$EM$9, 0)))} -> 51000 | M14: {=IF(is_category, IF(header_row_id=income_header_row, MATCH(income_min_row, $C:$C, 0), IF(header_row_id=expenses_header_row, MATCH(expenses_min_row, $C:$C, 0), IF(header_row_id=savings_header_row, MATCH(savings_min_row, $C:$C, 0), ""))), "")} -> 14 | N14: {=IF(is_category, IF(header_row_id=income_header_row, MATCH(income_max_row, $C:$C, 0), IF(header_row_id=expenses_header_row, MATCH(expenses_max_row, $C:$C, 0), IF(header_row_id=savings_header_row, MATCH(savings_max_row, $C:$C, 0), ""))), "")} -> 16 | O14: =IF(is_category, ADDRESS(sort_min_row, COLUMN(tracked)) & ":" & ADDRESS(sort_max_row, COLUMN(tracked)), "") -> $K$14:$K$16 | P14: =IF(is_category, RANK(tracked, INDIRECT(tracked_range), 0), "") -> 1 | Q14: =IF(is_category, ADDRESS(sort_min_row, COLUMN(budget)) & ":" & ADDRESS(sort_max_row, COLUMN(budget)), "") -> $L$14:$L$16 | R14: =IF(is_category, RANK(budget, INDIRECT(budget_range), 0), "") -> 1 | S14: =IF(is_category, _xlfn.NUMBERVALUE(tracker_rank & budget_rank), "") -> 11 | T14: =IF(is_category, ADDRESS(sort_min_row, COLUMN(combined_rank)) & ":" & ADDRESS(sort_max_row, COLUMN(combined_rank)), "") -> $S$14:$S$16 | U14: =IF(is_category, RANK(combined_rank, INDIRECT(combined_rank_range), 1), "") -> 1 | V14: =IF(is_category, ADDRESS(sort_min_row, COLUMN(combined_rank_norm)) & ":" & ADDRESS(ROW(), COLUMN(combined_rank_norm)), "") -> $U$14:$U$14 | W14: =IF(is_category, combined_rank_norm + COUNTIF(INDIRECT(combined_rank_norm_run_range), combined_rank_norm)-1, "") -> 1 | X14: =IF(is_category, header_row_id + combined_rank_unique, row_id) -> 10 | Y14: =IF(is_empty, "", INDEX($J:$J, MATCH(row_id, $X:$X, 0))) -> Employment (Net) | Z14: =IF(is_empty, "", IF(is_header, "Tracked", INDEX($K:$K, MATCH(row_id, $X:$X, 0)))) -> 10500 | AA14: =IF(is_empty, "", IF(is_header, "Budget", INDEX($L:$L, MATCH(row_id, $X:$X, 0)))) -> 51000 | AB14: =IF(is_empty, "", IF(is_header, "% Compl.", IFERROR(out_tracked / out_budget, "-"))) -> 0.20588235 | AC14: =IF(is_empty, "", IF(is_header, "Remaining", IF(out_budget - out_tracked > 0, out_budget - out_tracked, 0))) -> 40500 | AD14: =IF(is_empty, "", IF(is_header, "Excess", IF(out_budget - out_tracked < 0, out_tracked - out_budget, 0))) -> 0
C15: {=IF(C14=-1,-1, IF(C14<income_max_row, C14+1, IF(C14=income_max_row, income_total_row, IF(C14=income_total_row, "/1", IF(C14="/1", expenses_header_row, IF(C14<expenses_max_row, C14+1, IF(C14=expenses_max_row, expenses_total_row, IF(C14=expenses_total_row, "/2", IF(C14="/2", savings_header_row, IF(C14<savings_max_row, C14+1, IF(C14=savings_max_row, savings_total_row, -1)))))))))))} -> 11 | D15: =IF(is_header, row_id, IF(NOT(is_empty), D14, -1)) -> 9 | E15: {=1*OR(row_id=income_header_row, row_id=expenses_header_row, row_id=savings_header_row)} -> 0 | F15: =1*NOT(OR(is_header, is_total, is_empty)) -> 1 | G15: {=1*OR(row_id=income_total_row, row_id=expenses_total_row, row_id=savings_total_row)} -> 0 | H15: =1*OR(row_id="/1", row_id="/2", row_id=-1) -> 0 | I15: {=IFERROR(INDEX('Budget Planning'!$C:$C, header_row_id), "")} -> Income | J15: {=IFERROR(INDEX('Budget Planning'!$C:$C, row_id), "")} -> Side Hustle (Net) | K15: {=IF(OR(is_header, is_empty), "", IF(is_total, IF(selected_period="Total Year", SUM(Tracking[Amount] * (Tracking[Type]=type) * (YEAR(Tracking[Effective Date])=selected_year)), SUM(Tracking[Amount] * (Tracking[Type]=type) * (YEAR(Tracking[Effective Date])=selected_year) * (MONTH(Tracking[Effective Date])=selected_period))), IF(selected_period="Total Year", SUM(Tracking[Amount] * (Tracking[Type]=type) * (Tracking[Category]=item) * (YEAR(Tracking[Effective Date])=selected_year)), SUM(Tracking[Amount] * (Tracking[Type]=type) * (Tracking[Category]=item) * (YEAR(Tracking[Effective Date])=selected_year) * (MONTH(Tracking[Effective Date])=selected_period)))))} -> 2800 | L15: {=IF(OR(is_header, is_empty), "", INDEX('Budget Planning'!$E:$EM, row_id, MATCH(IF(selected_period="Total Year", selected_year, DATE(selected_year, selected_period, 1)), 'Budget Planning'!$E$9:$EM$9, 0)))} -> 12000 | M15: {=IF(is_category, IF(header_row_id=income_header_row, MATCH(income_min_row, $C:$C, 0), IF(header_row_id=expenses_header_row, MATCH(expenses_min_row, $C:$C, 0), IF(header_row_id=savings_header_row, MATCH(savings_min_row, $C:$C, 0), ""))), "")} -> 14 | N15: {=IF(is_category, IF(header_row_id=income_header_row, MATCH(income_max_row, $C:$C, 0), IF(header_row_id=expenses_header_row, MATCH(expenses_max_row, $C:$C, 0), IF(header_row_id=savings_header_row, MATCH(savings_max_row, $C:$C, 0), ""))), "")} -> 16 | O15: =IF(is_category, ADDRESS(sort_min_row, COLUMN(tracked)) & ":" & ADDRESS(sort_max_row, COLUMN(tracked)), "") -> $K$14:$K$16 | P15: =IF(is_category, RANK(tracked, INDIRECT(tracked_range), 0), "") -> 2 | Q15: =IF(is_category, ADDRESS(sort_min_row, COLUMN(budget)) & ":" & ADDRESS(sort_max_row, COLUMN(budget)), "") -> $L$14:$L$16 | R15: =IF(is_category, RANK(budget, INDIRECT(budget_range), 0), "") -> 2 | S15: =IF(is_category, _xlfn.NUMBERVALUE(tracker_rank & budget_rank), "") -> 22 | T15: =IF(is_category, ADDRESS(sort_min_row, COLUMN(combined_rank)) & ":" & ADDRESS(sort_max_row, COLUMN(combined_rank)), "") -> $S$14:$S$16 | U15: =IF(is_category, RANK(combined_rank, INDIRECT(combined_rank_range), 1), "") -> 2 | V15: =IF(is_category, ADDRESS(sort_min_row, COLUMN(combined_rank_norm)) & ":" & ADDRESS(ROW(), COLUMN(combined_rank_norm)), "") -> $U$14:$U$15 | W15: =IF(is_category, combined_rank_norm + COUNTIF(INDIRECT(combined_rank_norm_run_range), combined_rank_norm)-1, "") -> 2 | X15: =IF(is_category, header_row_id + combined_rank_unique, row_id) -> 11 | Y15: =IF(is_empty, "", INDEX($J:$J, MATCH(row_id, $X:$X, 0))) -> Side Hustle (Net) | Z15: =IF(is_empty, "", IF(is_header, "Tracked", INDEX($K:$K, MATCH(row_id, $X:$X, 0)))) -> 2800 | AA15: =IF(is_empty, "", IF(is_header, "Budget", INDEX($L:$L, MATCH(row_id, $X:$X, 0)))) -> 12000 | AB15: =IF(is_empty, "", IF(is_header, "% Compl.", IFERROR(out_tracked / out_budget, "-"))) -> 0.23333333 | AC15: =IF(is_empty, "", IF(is_header, "Remaining", IF(out_budget - out_tracked > 0, out_budget - out_tracked, 0))) -> 9200 | AD15: =IF(is_empty, "", IF(is_header, "Excess", IF(out_budget - out_tracked < 0, out_tracked - out_budget, 0))) -> 0
C16: {=IF(C15=-1,-1, IF(C15<income_max_row, C15+1, IF(C15=income_max_row, income_total_row, IF(C15=income_total_row, "/1", IF(C15="/1", expenses_header_row, IF(C15<expenses_max_row, C15+1, IF(C15=expenses_max_row, expenses_total_row, IF(C15=expenses_total_row, "/2", IF(C15="/2", savings_header_row, IF(C15<savings_max_row, C15+1, IF(C15=savings_max_row, savings_total_row, -1)))))))))))} -> 12 | D16: =IF(is_header, row_id, IF(NOT(is_empty), D15, -1)) -> 9 | E16: {=1*OR(row_id=income_header_row, row_id=expenses_header_row, row_id=savings_header_row)} -> 0 | F16: =1*NOT(OR(is_header, is_total, is_empty)) -> 1 | G16: {=1*OR(row_id=income_total_row, row_id=expenses_total_row, row_id=savings_total_row)} -> 0 | H16: =1*OR(row_id="/1", row_id="/2", row_id=-1) -> 0 | I16: {=IFERROR(INDEX('Budget Planning'!$C:$C, header_row_id), "")} -> Income | J16: {=IFERROR(INDEX('Budget Planning'!$C:$C, row_id), "")} -> Dividends | K16: {=IF(OR(is_header, is_empty), "", IF(is_total, IF(selected_period="Total Year", SUM(Tracking[Amount] * (Tracking[Type]=type) * (YEAR(Tracking[Effective Date])=selected_year)), SUM(Tracking[Amount] * (Tracking[Type]=type) * (YEAR(Tracking[Effective Date])=selected_year) * (MONTH(Tracking[Effective Date])=selected_period))), IF(selected_period="Total Year", SUM(Tracking[Amount] * (Tracking[Type]=type) * (Tracking[Category]=item) * (YEAR(Tracking[Effective Date])=selected_year)), SUM(Tracking[Amount] * (Tracking[Type]=type) * (Tracking[Category]=item) * (YEAR(Tracking[Effective Date])=selected_year) * (MONTH(Tracking[Effective Date])=selected_period)))))} -> 300 | L16: {=IF(OR(is_header, is_empty), "", INDEX('Budget Planning'!$E:$EM, row_id, MATCH(IF(selected_period="Total Year", selected_year, DATE(selected_year, selected_period, 1)), 'Budget Planning'!$E$9:$EM$9, 0)))} -> 1200 | M16: {=IF(is_category, IF(header_row_id=income_header_row, MATCH(income_min_row, $C:$C, 0), IF(header_row_id=expenses_header_row, MATCH(expenses_min_row, $C:$C, 0), IF(header_row_id=savings_header_row, MATCH(savings_min_row, $C:$C, 0), ""))), "")} -> 14 | N16: {=IF(is_category, IF(header_row_id=income_header_row, MATCH(income_max_row, $C:$C, 0), IF(header_row_id=expenses_header_row, MATCH(expenses_max_row, $C:$C, 0), IF(header_row_id=savings_header_row, MATCH(savings_max_row, $C:$C, 0), ""))), "")} -> 16 | O16: =IF(is_category, ADDRESS(sort_min_row, COLUMN(tracked)) & ":" & ADDRESS(sort_max_row, COLUMN(tracked)), "") -> $K$14:$K$16 | P16: =IF(is_category, RANK(tracked, INDIRECT(tracked_range), 0), "") -> 3 | Q16: =IF(is_category, ADDRESS(sort_min_row, COLUMN(budget)) & ":" & ADDRESS(sort_max_row, COLUMN(budget)), "") -> $L$14:$L$16 | R16: =IF(is_category, RANK(budget, INDIRECT(budget_range), 0), "") -> 3 | S16: =IF(is_category, _xlfn.NUMBERVALUE(tracker_rank & budget_rank), "") -> 33 | T16: =IF(is_category, ADDRESS(sort_min_row, COLUMN(combined_rank)) & ":" & ADDRESS(sort_max_row, COLUMN(combined_rank)), "") -> $S$14:$S$16 | U16: =IF(is_category, RANK(combined_rank, INDIRECT(combined_rank_range), 1), "") -> 3 | V16: =IF(is_category, ADDRESS(sort_min_row, COLUMN(combined_rank_norm)) & ":" & ADDRESS(ROW(), COLUMN(combined_rank_norm)), "") -> $U$14:$U$16 | W16: =IF(is_category, combined_rank_norm + COUNTIF(INDIRECT(combined_rank_norm_run_range), combined_rank_norm)-1, "") -> 3 | X16: =IF(is_category, header_row_id + combined_rank_unique, row_id) -> 12 | Y16: =IF(is_empty, "", INDEX($J:$J, MATCH(row_id, $X:$X, 0))) -> Dividends | Z16: =IF(is_empty, "", IF(is_header, "Tracked", INDEX($K:$K, MATCH(row_id, $X:$X, 0)))) -> 300 | AA16: =IF(is_empty, "", IF(is_header, "Budget", INDEX($L:$L, MATCH(row_id, $X:$X, 0)))) -> 1200 | AB16: =IF(is_empty, "", IF(is_header, "% Compl.", IFERROR(out_tracked / out_budget, "-"))) -> 0.25 | AC16: =IF(is_empty, "", IF(is_header, "Remaining", IF(out_budget - out_tracked > 0, out_budget - out_tracked, 0))) -> 900 | AD16: =IF(is_empty, "", IF(is_header, "Excess", IF(out_budget - out_tracked < 0, out_tracked - out_budget, 0))) -> 0 | AI16: =Calculations!E35 -> Employment (Net) | AJ16: =Calculations!F35 -> 10500
C17: {=IF(C16=-1,-1, IF(C16<income_max_row, C16+1, IF(C16=income_max_row, income_total_row, IF(C16=income_total_row, "/1", IF(C16="/1", expenses_header_row, IF(C16<expenses_max_row, C16+1, IF(C16=expenses_max_row, expenses_total_row, IF(C16=expenses_total_row, "/2", IF(C16="/2", savings_header_row, IF(C16<savings_max_row, C16+1, IF(C16=savings_max_row, savings_total_row, -1)))))))))))} -> 20 | D17: =IF(is_header, row_id, IF(NOT(is_empty), D16, -1)) -> 9 | E17: {=1*OR(row_id=income_header_row, row_id=expenses_header_row, row_id=savings_header_row)} -> 0 | F17: =1*NOT(OR(is_header, is_total, is_empty)) -> 0 | G17: {=1*OR(row_id=income_total_row, row_id=expenses_total_row, row_id=savings_total_row)} -> 1 | H17: =1*OR(row_id="/1", row_id="/2", row_id=-1) -> 0 | I17: {=IFERROR(INDEX('Budget Planning'!$C:$C, header_row_id), "")} -> Income | J17: {=IFERROR(INDEX('Budget Planning'!$C:$C, row_id), "")} -> Total | K17: {=IF(OR(is_header, is_empty), "", IF(is_total, IF(selected_period="Total Year", SUM(Tracking[Amount] * (Tracking[Type]=type) * (YEAR(Tracking[Effective Date])=selected_year)), SUM(Tracking[Amount] * (Tracking[Type]=type) * (YEAR(Tracking[Effective Date])=selected_year) * (MONTH(Tracking[Effective Date])=selected_period))), IF(selected_period="Total Year", SUM(Tracking[Amount] * (Tracking[Type]=type) * (Tracking[Category]=item) * (YEAR(Tracking[Effective Date])=selected_year)), SUM(Tracking[Amount] * (Tracking[Type]=type) * (Tracking[Category]=item) * (YEAR(Tracking[Effective Date])=selected_year) * (MONTH(Tracking[Effective Date])=selected_period)))))} -> 13600 | L17: {=IF(OR(is_header, is_empty), "", INDEX('Budget Planning'!$E:$EM, row_id, MATCH(IF(selected_period="Total Year", selected_year, DATE(selected_year, selected_period, 1)), 'Budget Planning'!$E$9:$EM$9, 0)))} -> 64200 | M17: {=IF(is_category, IF(header_row_id=income_header_row, MATCH(income_min_row, $C:$C, 0), IF(header_row_id=expenses_header_row, MATCH(expenses_min_row, $C:$C, 0), IF(header_row_id=savings_header_row, MATCH(savings_min_row, $C:$C, 0), ""))), "")} | N17: {=IF(is_category, IF(header_row_id=income_header_row, MATCH(income_max_row, $C:$C, 0), IF(header_row_id=expenses_header_row, MATCH(expenses_max_row, $C:$C, 0), IF(header_row_id=savings_header_row, MATCH(savings_max_row, $C:$C, 0), ""))), "")} | O17: =IF(is_category, ADDRESS(sort_min_row, COLUMN(tracked)) & ":" & ADDRESS(sort_max_row, COLUMN(tracked)), "") | P17: =IF(is_category, RANK(tracked, INDIRECT(tracked_range), 0), "") | Q17: =IF(is_category, ADDRESS(sort_min_row, COLUMN(budget)) & ":" & ADDRESS(sort_max_row, COLUMN(budget)), "") | R17: =IF(is_category, RANK(budget, INDIRECT(budget_range), 0), "") | S17: =IF(is_category, _xlfn.NUMBERVALUE(tracker_rank & budget_rank), "") | T17: =IF(is_category, ADDRESS(sort_min_row, COLUMN(combined_rank)) & ":" & ADDRESS(sort_max_row, COLUMN(combined_rank)), "") | U17: =IF(is_category, RANK(combined_rank, INDIRECT(combined_rank_range), 1), "") | V17: =IF(is_category, ADDRESS(sort_min_row, COLUMN(combined_rank_norm)) & ":" & ADDRESS(ROW(), COLUMN(combined_rank_norm)), "") | W17: =IF(is_category, combined_rank_norm + COUNTIF(INDIRECT(combined_rank_norm_run_range), combined_rank_norm)-1, "") | X17: =IF(is_category, header_row_id + combined_rank_unique, row_id) -> 20 | Y17: =IF(is_empty, "", INDEX($J:$J, MATCH(row_id, $X:$X, 0))) -> Total | Z17: =IF(is_empty, "", IF(is_header, "Tracked", INDEX($K:$K, MATCH(row_id, $X:$X, 0)))) -> 13600 | AA17: =IF(is_empty, "", IF(is_header, "Budget", INDEX($L:$L, MATCH(row_id, $X:$X, 0)))) -> 64200 | AB17: =IF(is_empty, "", IF(is_header, "% Compl.", IFERROR(out_tracked / out_budget, "-"))) -> 0.21183801 | AC17: =IF(is_empty, "", IF(is_header, "Remaining", IF(out_budget - out_tracked > 0, out_budget - out_tracked, 0))) -> 50600 | AD17: =IF(is_empty, "", IF(is_header, "Excess", IF(out_budget - out_tracked < 0, out_tracked - out_budget, 0))) -> 0 | AI17: =Calculations!E36 -> Side Hustle (Net) | AJ17: =Calculations!F36 -> 2800
C18: {=IF(C17=-1,-1, IF(C17<income_max_row, C17+1, IF(C17=income_max_row, income_total_row, IF(C17=income_total_row, "/1", IF(C17="/1", expenses_header_row, IF(C17<expenses_max_row, C17+1, IF(C17=expenses_max_row, expenses_total_row, IF(C17=expenses_total_row, "/2", IF(C17="/2", savings_header_row, IF(C17<savings_max_row, C17+1, IF(C17=savings_max_row, savings_total_row, -1)))))))))))} -> /1 | D18: =IF(is_header, row_id, IF(NOT(is_empty), D17, -1)) -> -1 | E18: {=1*OR(row_id=income_header_row, row_id=expenses_header_row, row_id=savings_header_row)} -> 0 | F18: =1*NOT(OR(is_header, is_total, is_empty)) -> 0 | G18: {=1*OR(row_id=income_total_row, row_id=expenses_total_row, row_id=savings_total_row)} -> 0 | H18: =1*OR(row_id="/1", row_id="/2", row_id=-1) -> 1 | I18: {=IFERROR(INDEX('Budget Planning'!$C:$C, header_row_id), "")} | J18: {=IFERROR(INDEX('Budget Planning'!$C:$C, row_id), "")} | K18: {=IF(OR(is_header, is_empty), "", IF(is_total, IF(selected_period="Total Year", SUM(Tracking[Amount] * (Tracking[Type]=type) * (YEAR(Tracking[Effective Date])=selected_year)), SUM(Tracking[Amount] * (Tracking[Type]=type) * (YEAR(Tracking[Effective Date])=selected_year) * (MONTH(Tracking[Effective Date])=selected_period))), IF(selected_period="Total Year", SUM(Tracking[Amount] * (Tracking[Type]=type) * (Tracking[Category]=item) * (YEAR(Tracking[Effective Date])=selected_year)), SUM(Tracking[Amount] * (Tracking[Type]=type) * (Tracking[Category]=item) * (YEAR(Tracking[Effective Date])=selected_year) * (MONTH(Tracking[Effective Date])=selected_period)))))} | L18: {=IF(OR(is_header, is_empty), "", INDEX('Budget Planning'!$E:$EM, row_id, MATCH(IF(selected_period="Total Year", selected_year, DATE(selected_year, selected_period, 1)), 'Budget Planning'!$E$9:$EM$9, 0)))} | M18: {=IF(is_category, IF(header_row_id=income_header_row, MATCH(income_min_row, $C:$C, 0), IF(header_row_id=expenses_header_row, MATCH(expenses_min_row, $C:$C, 0), IF(header_row_id=savings_header_row, MATCH(savings_min_row, $C:$C, 0), ""))), "")} | N18: {=IF(is_category, IF(header_row_id=income_header_row, MATCH(income_max_row, $C:$C, 0), IF(header_row_id=expenses_header_row, MATCH(expenses_max_row, $C:$C, 0), IF(header_row_id=savings_header_row, MATCH(savings_max_row, $C:$C, 0), ""))), "")} | O18: =IF(is_category, ADDRESS(sort_min_row, COLUMN(tracked)) & ":" & ADDRESS(sort_max_row, COLUMN(tracked)), "") | P18: =IF(is_category, RANK(tracked, INDIRECT(tracked_range), 0), "") | Q18: =IF(is_category, ADDRESS(sort_min_row, COLUMN(budget)) & ":" & ADDRESS(sort_max_row, COLUMN(budget)), "") | R18: =IF(is_category, RANK(budget, INDIRECT(budget_range), 0), "") | S18: =IF(is_category, _xlfn.NUMBERVALUE(tracker_rank & budget_rank), "") | T18: =IF(is_category, ADDRESS(sort_min_row, COLUMN(combined_rank)) & ":" & ADDRESS(sort_max_row, COLUMN(combined_rank)), "") | U18: =IF(is_category, RANK(combined_rank, INDIRECT(combined_rank_range), 1), "") | V18: =IF(is_category, ADDRESS(sort_min_row, COLUMN(combined_rank_norm)) & ":" & ADDRESS(ROW(), COLUMN(combined_rank_norm)), "") | W18: =IF(is_category, combined_rank_norm + COUNTIF(INDIRECT(combined_rank_norm_run_range), combined_rank_norm)-1, "") | X18: =IF(is_category, header_row_id + combined_rank_unique, row_id) -> /1 | Y18: =IF(is_empty, "", INDEX($J:$J, MATCH(row_id, $X:$X, 0))) | Z18: =IF(is_empty, "", IF(is_header, "Tracked", INDEX($K:$K, MATCH(row_id, $X:$X, 0)))) | AA18: =IF(is_empty, "", IF(is_header, "Budget", INDEX($L:$L, MATCH(row_id, $X:$X, 0)))) | AB18: =IF(is_empty, "", IF(is_header, "% Compl.", IFERROR(out_tracked / out_budget, "-"))) | AC18: =IF(is_empty, "", IF(is_header, "Remaining", IF(out_budget - out_tracked > 0, out_budget - out_tracked, 0))) | AD18: =IF(is_empty, "", IF(is_header, "Excess", IF(out_budget - out_tracked < 0, out_tracked - out_budget, 0))) | AI18: =Calculations!E37 -> Dividends | AJ18: =Calculations!F37 -> 300
C19: {=IF(C18=-1,-1, IF(C18<income_max_row, C18+1, IF(C18=income_max_row, income_total_row, IF(C18=income_total_row, "/1", IF(C18="/1", expenses_header_row, IF(C18<expenses_max_row, C18+1, IF(C18=expenses_max_row, expenses_total_row, IF(C18=expenses_total_row, "/2", IF(C18="/2", savings_header_row, IF(C18<savings_max_row, C18+1, IF(C18=savings_max_row, savings_total_row, -1)))))))))))} -> 22 | D19: =IF(is_header, row_id, IF(NOT(is_empty), D18, -1)) -> 22 | E19: {=1*OR(row_id=income_header_row, row_id=expenses_header_row, row_id=savings_header_row)} -> 1 | F19: =1*NOT(OR(is_header, is_total, is_empty)) -> 0 | G19: {=1*OR(row_id=income_total_row, row_id=expenses_total_row, row_id=savings_total_row)} -> 0 | H19: =1*OR(row_id="/1", row_id="/2", row_id=-1) -> 0 | I19: {=IFERROR(INDEX('Budget Planning'!$C:$C, header_row_id), "")} -> Expenses | J19: {=IFERROR(INDEX('Budget Planning'!$C:$C, row_id), "")} -> Expenses | K19: {=IF(OR(is_header, is_empty), "", IF(is_total, IF(selected_period="Total Year", SUM(Tracking[Amount] * (Tracking[Type]=type) * (YEAR(Tracking[Effective Date])=selected_year)), SUM(Tracking[Amount] * (Tracking[Type]=type) * (YEAR(Tracking[Effective Date])=selected_year) * (MONTH(Tracking[Effective Date])=selected_period))), IF(selected_period="Total Year", SUM(Tracking[Amount] * (Tracking[Type]=type) * (Tracking[Category]=item) * (YEAR(Tracking[Effective Date])=selected_year)), SUM(Tracking[Amount] * (Tracking[Type]=type) * (Tracking[Category]=item) * (YEAR(Tracking[Effective Date])=selected_year) * (MONTH(Tracking[Effective Date])=selected_period)))))} | L19: {=IF(OR(is_header, is_empty), "", INDEX('Budget Planning'!$E:$EM, row_id, MATCH(IF(selected_period="Total Year", selected_year, DATE(selected_year, selected_period, 1)), 'Budget Planning'!$E$9:$EM$9, 0)))} | M19: {=IF(is_category, IF(header_row_id=income_header_row, MATCH(income_min_row, $C:$C, 0), IF(header_row_id=expenses_header_row, MATCH(expenses_min_row, $C:$C, 0), IF(header_row_id=savings_header_row, MATCH(savings_min_row, $C:$C, 0), ""))), "")} | N19: {=IF(is_category, IF(header_row_id=income_header_row, MATCH(income_max_row, $C:$C, 0), IF(header_row_id=expenses_header_row, MATCH(expenses_max_row, $C:$C, 0), IF(header_row_id=savings_header_row, MATCH(savings_max_row, $C:$C, 0), ""))), "")} | O19: =IF(is_category, ADDRESS(sort_min_row, COLUMN(tracked)) & ":" & ADDRESS(sort_max_row, COLUMN(tracked)), "") | P19: =IF(is_category, RANK(tracked, INDIRECT(tracked_range), 0), "") | Q19: =IF(is_category, ADDRESS(sort_min_row, COLUMN(budget)) & ":" & ADDRESS(sort_max_row, COLUMN(budget)), "") | R19: =IF(is_category, RANK(budget, INDIRECT(budget_range), 0), "") | S19: =IF(is_category, _xlfn.NUMBERVALUE(tracker_rank & budget_rank), "") | T19: =IF(is_category, ADDRESS(sort_min_row, COLUMN(combined_rank)) & ":" & ADDRESS(sort_max_row, COLUMN(combined_rank)), "") | U19: =IF(is_category, RANK(combined_rank, INDIRECT(combined_rank_range), 1), "") | V19: =IF(is_category, ADDRESS(sort_min_row, COLUMN(combined_rank_norm)) & ":" & ADDRESS(ROW(), COLUMN(combined_rank_norm)), "") | W19: =IF(is_category, combined_rank_norm + COUNTIF(INDIRECT(combined_rank_norm_run_range), combined_rank_norm)-1, "") | X19: =IF(is_category, header_row_id + combined_rank_unique, row_id) -> 22 | Y19: =IF(is_empty, "", INDEX($J:$J, MATCH(row_id, $X:$X, 0))) -> Expenses | Z19: =IF(is_empty, "", IF(is_header, "Tracked", INDEX($K:$K, MATCH(row_id, $X:$X, 0)))) -> Tracked | AA19: =IF(is_empty, "", IF(is_header, "Budget", INDEX($L:$L, MATCH(row_id, $X:$X, 0)))) -> Budget | AB19: =IF(is_empty, "", IF(is_header, "% Compl.", IFERROR(out_tracked / out_budget, "-"))) -> % Compl. | AC19: =IF(is_empty, "", IF(is_header, "Remaining", IF(out_budget - out_tracked > 0, out_budget - out_tracked, 0))) -> Remaining | AD19: =IF(is_empty, "", IF(is_header, "Excess", IF(out_budget - out_tracked < 0, out_tracked - out_budget, 0))) -> Excess | AI19: =Calculations!E38 | AJ19: =Calculations!F38
C20: {=IF(C19=-1,-1, IF(C19<income_max_row, C19+1, IF(C19=income_max_row, income_total_row, IF(C19=income_total_row, "/1", IF(C19="/1", expenses_header_row, IF(C19<expenses_max_row, C19+1, IF(C19=expenses_max_row, expenses_total_row, IF(C19=expenses_total_row, "/2", IF(C19="/2", savings_header_row, IF(C19<savings_max_row, C19+1, IF(C19=savings_max_row, savings_total_row, -1)))))))))))} -> 23 | D20: =IF(is_header, row_id, IF(NOT(is_empty), D19, -1)) -> 22 | E20: {=1*OR(row_id=income_header_row, row_id=expenses_header_row, row_id=savings_header_row)} -> 0 | F20: =1*NOT(OR(is_header, is_total, is_empty)) -> 1 | G20: {=1*OR(row_id=income_total_row, row_id=expenses_total_row, row_id=savings_total_row)} -> 0 | H20: =1*OR(row_id="/1", row_id="/2", row_id=-1) -> 0 | I20: {=IFERROR(INDEX('Budget Planning'!$C:$C, header_row_id), "")} -> Expenses | J20: {=IFERROR(INDEX('Budget Planning'!$C:$C, row_id), "")} -> Housing | K20: {=IF(OR(is_header, is_empty), "", IF(is_total, IF(selected_period="Total Year", SUM(Tracking[Amount] * (Tracking[Type]=type) * (YEAR(Tracking[Effective Date])=selected_year)), SUM(Tracking[Amount] * (Tracking[Type]=type) * (YEAR(Tracking[Effective Date])=selected_year) * (MONTH(Tracking[Effective Date])=selected_period))), IF(selected_period="Total Year", SUM(Tracking[Amount] * (Tracking[Type]=type) * (Tracking[Category]=item) * (YEAR(Tracking[Effective Date])=selected_year)), SUM(Tracking[Amount] * (Tracking[Type]=type) * (Tracking[Category]=item) * (YEAR(Tracking[Effective Date])=selected_year) * (MONTH(Tracking[Effective Date])=selected_period)))))} -> 3600 | L20: {=IF(OR(is_header, is_empty), "", INDEX('Budget Planning'!$E:$EM, row_id, MATCH(IF(selected_period="Total Year", selected_year, DATE(selected_year, selected_period, 1)), 'Budget Planning'!$E$9:$EM$9, 0)))} -> 14400 | M20: {=IF(is_category, IF(header_row_id=income_header_row, MATCH(income_min_row, $C:$C, 0), IF(header_row_id=expenses_header_row, MATCH(expenses_min_row, $C:$C, 0), IF(header_row_id=savings_header_row, MATCH(savings_min_row, $C:$C, 0), ""))), "")} -> 20 | N20: {=IF(is_category, IF(header_row_id=income_header_row, MATCH(income_max_row, $C:$C, 0), IF(header_row_id=expenses_header_row, MATCH(expenses_max_row, $C:$C, 0), IF(header_row_id=savings_header_row, MATCH(savings_max_row, $C:$C, 0), ""))), "")} -> 28 | O20: =IF(is_category, ADDRESS(sort_min_row, COLUMN(tracked)) & ":" & ADDRESS(sort_max_row, COLUMN(tracked)), "") -> $K$20:$K$28 | P20: =IF(is_category, RANK(tracked, INDIRECT(tracked_range), 0), "") -> 1 | Q20: =IF(is_category, ADDRESS(sort_min_row, COLUMN(budget)) & ":" & ADDRESS(sort_max_row, COLUMN(budget)), "") -> $L$20:$L$28 | R20: =IF(is_category, RANK(budget, INDIRECT(budget_range), 0), "") -> 1 | S20: =IF(is_category, _xlfn.NUMBERVALUE(tracker_rank & budget_rank), "") -> 11 | T20: =IF(is_category, ADDRESS(sort_min_row, COLUMN(combined_rank)) & ":" & ADDRESS(sort_max_row, COLUMN(combined_rank)), "") -> $S$20:$S$28 | U20: =IF(is_category, RANK(combined_rank, INDIRECT(combined_rank_range), 1), "") -> 1 | V20: =IF(is_category, ADDRESS(sort_min_row, COLUMN(combined_rank_norm)) & ":" & ADDRESS(ROW(), COLUMN(combined_rank_norm)), "") -> $U$20:$U$20 | W20: =IF(is_category, combined_rank_norm + COUNTIF(INDIRECT(combined_rank_norm_run_range), combined_rank_norm)-1, "") -> 1 | X20: =IF(is_category, header_row_id + combined_rank_unique, row_id) -> 23 | Y20: =IF(is_empty, "", INDEX($J:$J, MATCH(row_id, $X:$X, 0))) -> Housing | Z20: =IF(is_empty, "", IF(is_header, "Tracked", INDEX($K:$K, MATCH(row_id, $X:$X, 0)))) -> 3600 | AA20: =IF(is_empty, "", IF(is_header, "Budget", INDEX($L:$L, MATCH(row_id, $X:$X, 0)))) -> 14400 | AB20: =IF(is_empty, "", IF(is_header, "% Compl.", IFERROR(out_tracked / out_budget, "-"))) -> 0.25 | AC20: =IF(is_empty, "", IF(is_header, "Remaining", IF(out_budget - out_tracked > 0, out_budget - out_tracked, 0))) -> 10800 | AD20: =IF(is_empty, "", IF(is_header, "Excess", IF(out_budget - out_tracked < 0, out_tracked - out_budget, 0))) -> 0 | AI20: =Calculations!E39 | AJ20: =Calculations!F39
C21: {=IF(C20=-1,-1, IF(C20<income_max_row, C20+1, IF(C20=income_max_row, income_total_row, IF(C20=income_total_row, "/1", IF(C20="/1", expenses_header_row, IF(C20<expenses_max_row, C20+1, IF(C20=expenses_max_row, expenses_total_row, IF(C20=expenses_total_row, "/2", IF(C20="/2", savings_header_row, IF(C20<savings_max_row, C20+1, IF(C20=savings_max_row, savings_total_row, -1)))))))))))} -> 24 | D21: =IF(is_header, row_id, IF(NOT(is_empty), D20, -1)) -> 22 | E21: {=1*OR(row_id=income_header_row, row_id=expenses_header_row, row_id=savings_header_row)} -> 0 | F21: =1*NOT(OR(is_header, is_total, is_empty)) -> 1 | G21: {=1*OR(row_id=income_total_row, row_id=expenses_total_row, row_id=savings_total_row)} -> 0 | H21: =1*OR(row_id="/1", row_id="/2", row_id=-1) -> 0 | I21: {=IFERROR(INDEX('Budget Planning'!$C:$C, header_row_id), "")} -> Expenses | J21: {=IFERROR(INDEX('Budget Planning'!$C:$C, row_id), "")} -> Utilites | K21: {=IF(OR(is_header, is_empty), "", IF(is_total, IF(selected_period="Total Year", SUM(Tracking[Amount] * (Tracking[Type]=type) * (YEAR(Tracking[Effective Date])=selected_year)), SUM(Tracking[Amount] * (Tracking[Type]=type) * (YEAR(Tracking[Effective Date])=selected_year) * (MONTH(Tracking[Effective Date])=selected_period))), IF(selected_period="Total Year", SUM(Tracking[Amount] * (Tracking[Type]=type) * (Tracking[Category]=item) * (YEAR(Tracking[Effective Date])=selected_year)), SUM(Tracking[Amount] * (Tracking[Type]=type) * (Tracking[Category]=item) * (YEAR(Tracking[Effective Date])=selected_year) * (MONTH(Tracking[Effective Date])=selected_period)))))} -> 900 | L21: {=IF(OR(is_header, is_empty), "", INDEX('Budget Planning'!$E:$EM, row_id, MATCH(IF(selected_period="Total Year", selected_year, DATE(selected_year, selected_period, 1)), 'Budget Planning'!$E$9:$EM$9, 0)))} -> 3600 | M21: {=IF(is_category, IF(header_row_id=income_header_row, MATCH(income_min_row, $C:$C, 0), IF(header_row_id=expenses_header_row, MATCH(expenses_min_row, $C:$C, 0), IF(header_row_id=savings_header_row, MATCH(savings_min_row, $C:$C, 0), ""))), "")} -> 20 | N21: {=IF(is_category, IF(header_row_id=income_header_row, MATCH(income_max_row, $C:$C, 0), IF(header_row_id=expenses_header_row, MATCH(expenses_max_row, $C:$C, 0), IF(header_row_id=savings_header_row, MATCH(savings_max_row, $C:$C, 0), ""))), "")} -> 28 | O21: =IF(is_category, ADDRESS(sort_min_row, COLUMN(tracked)) & ":" & ADDRESS(sort_max_row, COLUMN(tracked)), "") -> $K$20:$K$28 | P21: =IF(is_category, RANK(tracked, INDIRECT(tracked_range), 0), "") -> 2 | Q21: =IF(is_category, ADDRESS(sort_min_row, COLUMN(budget)) & ":" & ADDRESS(sort_max_row, COLUMN(budget)), "") -> $L$20:$L$28 | R21: =IF(is_category, RANK(budget, INDIRECT(budget_range), 0), "") -> 4 | S21: =IF(is_category, _xlfn.NUMBERVALUE(tracker_rank & budget_rank), "") -> 24 | T21: =IF(is_category, ADDRESS(sort_min_row, COLUMN(combined_rank)) & ":" & ADDRESS(sort_max_row, COLUMN(combined_rank)), "") -> $S$20:$S$28 | U21: =IF(is_category, RANK(combined_rank, INDIRECT(combined_rank_range), 1), "") -> 3 | V21: =IF(is_category, ADDRESS(sort_min_row, COLUMN(combined_rank_norm)) & ":" & ADDRESS(ROW(), COLUMN(combined_rank_norm)), "") -> $U$20:$U$21 | W21: =IF(is_category, combined_rank_norm + COUNTIF(INDIRECT(combined_rank_norm_run_range), combined_rank_norm)-1, "") -> 3 | X21: =IF(is_category, header_row_id + combined_rank_unique, row_id) -> 25 | Y21: =IF(is_empty, "", INDEX($J:$J, MATCH(row_id, $X:$X, 0))) -> Groceries | Z21: =IF(is_empty, "", IF(is_header, "Tracked", INDEX($K:$K, MATCH(row_id, $X:$X, 0)))) -> 900 | AA21: =IF(is_empty, "", IF(is_header, "Budget", INDEX($L:$L, MATCH(row_id, $X:$X, 0)))) -> 4200 | AB21: =IF(is_empty, "", IF(is_header, "% Compl.", IFERROR(out_tracked / out_budget, "-"))) -> 0.21428571 | AC21: =IF(is_empty, "", IF(is_header, "Remaining", IF(out_budget - out_tracked > 0, out_budget - out_tracked, 0))) -> 3300 | AD21: =IF(is_empty, "", IF(is_header, "Excess", IF(out_budget - out_tracked < 0, out_tracked - out_budget, 0))) -> 0 | AI21: =Calculations!E40 | AJ21: =Calculations!F40
C22: {=IF(C21=-1,-1, IF(C21<income_max_row, C21+1, IF(C21=income_max_row, income_total_row, IF(C21=income_total_row, "/1", IF(C21="/1", expenses_header_row, IF(C21<expenses_max_row, C21+1, IF(C21=expenses_max_row, expenses_total_row, IF(C21=expenses_total_row, "/2", IF(C21="/2", savings_header_row, IF(C21<savings_max_row, C21+1, IF(C21=savings_max_row, savings_total_row, -1)))))))))))} -> 25 | D22: =IF(is_header, row_id, IF(NOT(is_empty), D21, -1)) -> 22 | E22: {=1*OR(row_id=income_header_row, row_id=expenses_header_row, row_id=savings_header_row)} -> 0 | F22: =1*NOT(OR(is_header, is_total, is_empty)) -> 1 | G22: {=1*OR(row_id=income_total_row, row_id=expenses_total_row, row_id=savings_total_row)} -> 0 | H22: =1*OR(row_id="/1", row_id="/2", row_id=-1) -> 0 | I22: {=IFERROR(INDEX('Budget Planning'!$C:$C, header_row_id), "")} -> Expenses | J22: {=IFERROR(INDEX('Budget Planning'!$C:$C, row_id), "")} -> Groceries | K22: {=IF(OR(is_header, is_empty), "", IF(is_total, IF(selected_period="Total Year", SUM(Tracking[Amount] * (Tracking[Type]=type) * (YEAR(Tracking[Effective Date])=selected_year)), SUM(Tracking[Amount] * (Tracking[Type]=type) * (YEAR(Tracking[Effective Date])=selected_year) * (MONTH(Tracking[Effective Date])=selected_period))), IF(selected_period="Total Year", SUM(Tracking[Amount] * (Tracking[Type]=type) * (Tracking[Category]=item) * (YEAR(Tracking[Effective Date])=selected_year)), SUM(Tracking[Amount] * (Tracking[Type]=type) * (Tracking[Category]=item) * (YEAR(Tracking[Effective Date])=selected_year) * (MONTH(Tracking[Effective Date])=selected_period)))))} -> 900 | L22: {=IF(OR(is_header, is_empty), "", INDEX('Budget Planning'!$E:$EM, row_id, MATCH(IF(selected_period="Total Year", selected_year, DATE(selected_year, selected_period, 1)), 'Budget Planning'!$E$9:$EM$9, 0)))} -> 4200 | M22: {=IF(is_category, IF(header_row_id=income_header_row, MATCH(income_min_row, $C:$C, 0), IF(header_row_id=expenses_header_row, MATCH(expenses_min_row, $C:$C, 0), IF(header_row_id=savings_header_row, MATCH(savings_min_row, $C:$C, 0), ""))), "")} -> 20 | N22: {=IF(is_category, IF(header_row_id=income_header_row, MATCH(income_max_row, $C:$C, 0), IF(header_row_id=expenses_header_row, MATCH(expenses_max_row, $C:$C, 0), IF(header_row_id=savings_header_row, MATCH(savings_max_row, $C:$C, 0), ""))), "")} -> 28 | O22: =IF(is_category, ADDRESS(sort_min_row, COLUMN(tracked)) & ":" & ADDRESS(sort_max_row, COLUMN(tracked)), "") -> $K$20:$K$28 | P22: =IF(is_category, RANK(tracked, INDIRECT(tracked_range), 0), "") -> 2 | Q22: =IF(is_category, ADDRESS(sort_min_row, COLUMN(budget)) & ":" & ADDRESS(sort_max_row, COLUMN(budget)), "") -> $L$20:$L$28 | R22: =IF(is_category, RANK(budget, INDIRECT(budget_range), 0), "") -> 3 | S22: =IF(is_category, _xlfn.NUMBERVALUE(tracker_rank & budget_rank), "") -> 23 | T22: =IF(is_category, ADDRESS(sort_min_row, COLUMN(combined_rank)) & ":" & ADDRESS(sort_max_row, COLUMN(combined_rank)), "") -> $S$20:$S$28 | U22: =IF(is_category, RANK(combined_rank, INDIRECT(combined_rank_range), 1), "") -> 2 | V22: =IF(is_category, ADDRESS(sort_min_row, COLUMN(combined_rank_norm)) & ":" & ADDRESS(ROW(), COLUMN(combined_rank_norm)), "") -> $U$20:$U$22 | W22: =IF(is_category, combined_rank_norm + COUNTIF(INDIRECT(combined_rank_norm_run_range), combined_rank_norm)-1, "") -> 2 | X22: =IF(is_category, header_row_id + combined_rank_unique, row_id) -> 24 | Y22: =IF(is_empty, "", INDEX($J:$J, MATCH(row_id, $X:$X, 0))) -> Utilites | Z22: =IF(is_empty, "", IF(is_header, "Tracked", INDEX($K:$K, MATCH(row_id, $X:$X, 0)))) -> 900 | AA22: =IF(is_empty, "", IF(is_header, "Budget", INDEX($L:$L, MATCH(row_id, $X:$X, 0)))) -> 3600 | AB22: =IF(is_empty, "", IF(is_header, "% Compl.", IFERROR(out_tracked / out_budget, "-"))) -> 0.25 | AC22: =IF(is_empty, "", IF(is_header, "Remaining", IF(out_budget - out_tracked > 0, out_budget - out_tracked, 0))) -> 2700 | AD22: =IF(is_empty, "", IF(is_header, "Excess", IF(out_budget - out_tracked < 0, out_tracked - out_budget, 0))) -> 0 | AI22: =Calculations!E41 -> Total | AJ22: =Calculations!F41 -> 13600
C23: {=IF(C22=-1,-1, IF(C22<income_max_row, C22+1, IF(C22=income_max_row, income_total_row, IF(C22=income_total_row, "/1", IF(C22="/1", expenses_header_row, IF(C22<expenses_max_row, C22+1, IF(C22=expenses_max_row, expenses_total_row, IF(C22=expenses_total_row, "/2", IF(C22="/2", savings_header_row, IF(C22<savings_max_row, C22+1, IF(C22=savings_max_row, savings_total_row, -1)))))))))))} -> 26 | D23: =IF(is_header, row_id, IF(NOT(is_empty), D22, -1)) -> 22 | E23: {=1*OR(row_id=income_header_row, row_id=expenses_header_row, row_id=savings_header_row)} -> 0 | F23: =1*NOT(OR(is_header, is_total, is_empty)) -> 1 | G23: {=1*OR(row_id=income_total_row, row_id=expenses_total_row, row_id=savings_total_row)} -> 0 | H23: =1*OR(row_id="/1", row_id="/2", row_id=-1) -> 0 | I23: {=IFERROR(INDEX('Budget Planning'!$C:$C, header_row_id), "")} -> Expenses | J23: {=IFERROR(INDEX('Budget Planning'!$C:$C, row_id), "")} -> Transportation | K23: {=IF(OR(is_header, is_empty), "", IF(is_total, IF(selected_period="Total Year", SUM(Tracking[Amount] * (Tracking[Type]=type) * (YEAR(Tracking[Effective Date])=selected_year)), SUM(Tracking[Amount] * (Tracking[Type]=type) * (YEAR(Tracking[Effective Date])=selected_year) * (MONTH(Tracking[Effective Date])=selected_period))), IF(selected_period="Total Year", SUM(Tracking[Amount] * (Tracking[Type]=type) * (Tracking[Category]=item) * (YEAR(Tracking[Effective Date])=selected_year)), SUM(Tracking[Amount] * (Tracking[Type]=type) * (Tracking[Category]=item) * (YEAR(Tracking[Effective Date])=selected_year) * (MONTH(Tracking[Effective Date])=selected_period)))))} -> 610 | L23: {=IF(OR(is_header, is_empty), "", INDEX('Budget Planning'!$E:$EM, row_id, MATCH(IF(selected_period="Total Year", selected_year, DATE(selected_year, selected_period, 1)), 'Budget Planning'!$E$9:$EM$9, 0)))} -> 3600 | M23: {=IF(is_category, IF(header_row_id=income_header_row, MATCH(income_min_row, $C:$C, 0), IF(header_row_id=expenses_header_row, MATCH(expenses_min_row, $C:$C, 0), IF(header_row_id=savings_header_row, MATCH(savings_min_row, $C:$C, 0), ""))), "")} -> 20 | N23: {=IF(is_category, IF(header_row_id=income_header_row, MATCH(income_max_row, $C:$C, 0), IF(header_row_id=expenses_header_row, MATCH(expenses_max_row, $C:$C, 0), IF(header_row_id=savings_header_row, MATCH(savings_max_row, $C:$C, 0), ""))), "")} -> 28 | O23: =IF(is_category, ADDRESS(sort_min_row, COLUMN(tracked)) & ":" & ADDRESS(sort_max_row, COLUMN(tracked)), "") -> $K$20:$K$28 | P23: =IF(is_category, RANK(tracked, INDIRECT(tracked_range), 0), "") -> 5 | Q23: =IF(is_category, ADDRESS(sort_min_row, COLUMN(budget)) & ":" & ADDRESS(sort_max_row, COLUMN(budget)), "") -> $L$20:$L$28 | R23: =IF(is_category, RANK(budget, INDIRECT(budget_range), 0), "") -> 4 | S23: =IF(is_category, _xlfn.NUMBERVALUE(tracker_rank & budget_rank), "") -> 54 | T23: =IF(is_category, ADDRESS(sort_min_row, COLUMN(combined_rank)) & ":" & ADDRESS(sort_max_row, COLUMN(combined_rank)), "") -> $S$20:$S$28 | U23: =IF(is_category, RANK(combined_rank, INDIRECT(combined_rank_range), 1), "") -> 5 | V23: =IF(is_category, ADDRESS(sort_min_row, COLUMN(combined_rank_norm)) & ":" & ADDRESS(ROW(), COLUMN(combined_rank_norm)), "") -> $U$20:$U$23 | W23: =IF(is_category, combined_rank_norm + COUNTIF(INDIRECT(combined_rank_norm_run_range), combined_rank_norm)-1, "") -> 5 | X23: =IF(is_category, header_row_id + combined_rank_unique, row_id) -> 27 | Y23: =IF(is_empty, "", INDEX($J:$J, MATCH(row_id, $X:$X, 0))) -> Fun & Vacation | Z23: =IF(is_empty, "", IF(is_header, "Tracked", INDEX($K:$K, MATCH(row_id, $X:$X, 0)))) -> 730 | AA23: =IF(is_empty, "", IF(is_header, "Budget", INDEX($L:$L, MATCH(row_id, $X:$X, 0)))) -> 6000 | AB23: =IF(is_empty, "", IF(is_header, "% Compl.", IFERROR(out_tracked / out_budget, "-"))) -> 0.12166667 | AC23: =IF(is_empty, "", IF(is_header, "Remaining", IF(out_budget - out_tracked > 0, out_budget - out_tracked, 0))) -> 5270 | AD23: =IF(is_empty, "", IF(is_header, "Excess", IF(out_budget - out_tracked < 0, out_tracked - out_budget, 0))) -> 0
C24: {=IF(C23=-1,-1, IF(C23<income_max_row, C23+1, IF(C23=income_max_row, income_total_row, IF(C23=income_total_row, "/1", IF(C23="/1", expenses_header_row, IF(C23<expenses_max_row, C23+1, IF(C23=expenses_max_row, expenses_total_row, IF(C23=expenses_total_row, "/2", IF(C23="/2", savings_header_row, IF(C23<savings_max_row, C23+1, IF(C23=savings_max_row, savings_total_row, -1)))))))))))} -> 27 | D24: =IF(is_header, row_id, IF(NOT(is_empty), D23, -1)) -> 22 | E24: {=1*OR(row_id=income_header_row, row_id=expenses_header_row, row_id=savings_header_row)} -> 0 | F24: =1*NOT(OR(is_header, is_total, is_empty)) -> 1 | G24: {=1*OR(row_id=income_total_row, row_id=expenses_total_row, row_id=savings_total_row)} -> 0 | H24: =1*OR(row_id="/1", row_id="/2", row_id=-1) -> 0 | I24: {=IFERROR(INDEX('Budget Planning'!$C:$C, header_row_id), "")} -> Expenses | J24: {=IFERROR(INDEX('Budget Planning'!$C:$C, row_id), "")} -> Insurances | K24: {=IF(OR(is_header, is_empty), "", IF(is_total, IF(selected_period="Total Year", SUM(Tracking[Amount] * (Tracking[Type]=type) * (YEAR(Tracking[Effective Date])=selected_year)), SUM(Tracking[Amount] * (Tracking[Type]=type) * (YEAR(Tracking[Effective Date])=selected_year) * (MONTH(Tracking[Effective Date])=selected_period))), IF(selected_period="Total Year", SUM(Tracking[Amount] * (Tracking[Type]=type) * (Tracking[Category]=item) * (YEAR(Tracking[Effective Date])=selected_year)), SUM(Tracking[Amount] * (Tracking[Type]=type) * (Tracking[Category]=item) * (YEAR(Tracking[Effective Date])=selected_year) * (MONTH(Tracking[Effective Date])=selected_period)))))} -> 150 | L24: {=IF(OR(is_header, is_empty), "", INDEX('Budget Planning'!$E:$EM, row_id, MATCH(IF(selected_period="Total Year", selected_year, DATE(selected_year, selected_period, 1)), 'Budget Planning'!$E$9:$EM$9, 0)))} -> 600 | M24: {=IF(is_category, IF(header_row_id=income_header_row, MATCH(income_min_row, $C:$C, 0), IF(header_row_id=expenses_header_row, MATCH(expenses_min_row, $C:$C, 0), IF(header_row_id=savings_header_row, MATCH(savings_min_row, $C:$C, 0), ""))), "")} -> 20 | N24: {=IF(is_category, IF(header_row_id=income_header_row, MATCH(income_max_row, $C:$C, 0), IF(header_row_id=expenses_header_row, MATCH(expenses_max_row, $C:$C, 0), IF(header_row_id=savings_header_row, MATCH(savings_max_row, $C:$C, 0), ""))), "")} -> 28 | O24: =IF(is_category, ADDRESS(sort_min_row, COLUMN(tracked)) & ":" & ADDRESS(sort_max_row, COLUMN(tracked)), "") -> $K$20:$K$28 | P24: =IF(is_category, RANK(tracked, INDIRECT(tracked_range), 0), "") -> 9 | Q24: =IF(is_category, ADDRESS(sort_min_row, COLUMN(budget)) & ":" & ADDRESS(sort_max_row, COLUMN(budget)), "") -> $L$20:$L$28 | R24: =IF(is_category, RANK(budget, INDIRECT(budget_range), 0), "") -> 8 | S24: =IF(is_category, _xlfn.NUMBERVALUE(tracker_rank & budget_rank), "") -> 98 | T24: =IF(is_category, ADDRESS(sort_min_row, COLUMN(combined_rank)) & ":" & ADDRESS(sort_max_row, COLUMN(combined_rank)), "") -> $S$20:$S$28 | U24: =IF(is_category, RANK(combined_rank, INDIRECT(combined_rank_range), 1), "") -> 9 | V24: =IF(is_category, ADDRESS(sort_min_row, COLUMN(combined_rank_norm)) & ":" & ADDRESS(ROW(), COLUMN(combined_rank_norm)), "") -> $U$20:$U$24 | W24: =IF(is_category, combined_rank_norm + COUNTIF(INDIRECT(combined_rank_norm_run_range), combined_rank_norm)-1, "") -> 9 | X24: =IF(is_category, header_row_id + combined_rank_unique, row_id) -> 31 | Y24: =IF(is_empty, "", INDEX($J:$J, MATCH(row_id, $X:$X, 0))) -> Transportation | Z24: =IF(is_empty, "", IF(is_header, "Tracked", INDEX($K:$K, MATCH(row_id, $X:$X, 0)))) -> 610 | AA24: =IF(is_empty, "", IF(is_header, "Budget", INDEX($L:$L, MATCH(row_id, $X:$X, 0)))) -> 3600 | AB24: =IF(is_empty, "", IF(is_header, "% Compl.", IFERROR(out_tracked / out_budget, "-"))) -> 0.16944444 | AC24: =IF(is_empty, "", IF(is_header, "Remaining", IF(out_budget - out_tracked > 0, out_budget - out_tracked, 0))) -> 2990 | AD24: =IF(is_empty, "", IF(is_header, "Excess", IF(out_budget - out_tracked < 0, out_tracked - out_budget, 0))) -> 0
C25: {=IF(C24=-1,-1, IF(C24<income_max_row, C24+1, IF(C24=income_max_row, income_total_row, IF(C24=income_total_row, "/1", IF(C24="/1", expenses_header_row, IF(C24<expenses_max_row, C24+1, IF(C24=expenses_max_row, expenses_total_row, IF(C24=expenses_total_row, "/2", IF(C24="/2", savings_header_row, IF(C24<savings_max_row, C24+1, IF(C24=savings_max_row, savings_total_row, -1)))))))))))} -> 28 | D25: =IF(is_header, row_id, IF(NOT(is_empty), D24, -1)) -> 22 | E25: {=1*OR(row_id=income_header_row, row_id=expenses_header_row, row_id=savings_header_row)} -> 0 | F25: =1*NOT(OR(is_header, is_total, is_empty)) -> 1 | G25: {=1*OR(row_id=income_total_row, row_id=expenses_total_row, row_id=savings_total_row)} -> 0 | H25: =1*OR(row_id="/1", row_id="/2", row_id=-1) -> 0 | I25: {=IFERROR(INDEX('Budget Planning'!$C:$C, header_row_id), "")} -> Expenses | J25: {=IFERROR(INDEX('Budget Planning'!$C:$C, row_id), "")} -> Clothing | K25: {=IF(OR(is_header, is_empty), "", IF(is_total, IF(selected_period="Total Year", SUM(Tracking[Amount] * (Tracking[Type]=type) * (YEAR(Tracking[Effective Date])=selected_year)), SUM(Tracking[Amount] * (Tracking[Type]=type) * (YEAR(Tracking[Effective Date])=selected_year) * (MONTH(Tracking[Effective Date])=selected_period))), IF(selected_period="Total Year", SUM(Tracking[Amount] * (Tracking[Type]=type) * (Tracking[Category]=item) * (YEAR(Tracking[Effective Date])=selected_year)), SUM(Tracking[Amount] * (Tracking[Type]=type) * (Tracking[Category]=item) * (YEAR(Tracking[Effective Date])=selected_year) * (MONTH(Tracking[Effective Date])=selected_period)))))} -> 360 | L25: {=IF(OR(is_header, is_empty), "", INDEX('Budget Planning'!$E:$EM, row_id, MATCH(IF(selected_period="Total Year", selected_year, DATE(selected_year, selected_period, 1)), 'Budget Planning'!$E$9:$EM$9, 0)))} -> 2400 | M25: {=IF(is_category, IF(header_row_id=income_header_row, MATCH(income_min_row, $C:$C, 0), IF(header_row_id=expenses_header_row, MATCH(expenses_min_row, $C:$C, 0), IF(header_row_id=savings_header_row, MATCH(savings_min_row, $C:$C, 0), ""))), "")} -> 20 | N25: {=IF(is_category, IF(header_row_id=income_header_row, MATCH(income_max_row, $C:$C, 0), IF(header_row_id=expenses_header_row, MATCH(expenses_max_row, $C:$C, 0), IF(header_row_id=savings_header_row, MATCH(savings_max_row, $C:$C, 0), ""))), "")} -> 28 | O25: =IF(is_category, ADDRESS(sort_min_row, COLUMN(tracked)) & ":" & ADDRESS(sort_max_row, COLUMN(tracked)), "") -> $K$20:$K$28 | P25: =IF(is_category, RANK(tracked, INDIRECT(tracked_range), 0), "") -> 7 | Q25: =IF(is_category, ADDRESS(sort_min_row, COLUMN(budget)) & ":" & ADDRESS(sort_max_row, COLUMN(budget)), "") -> $L$20:$L$28 | R25: =IF(is_category, RANK(budget, INDIRECT(budget_range), 0), "") -> 6 | S25: =IF(is_category, _xlfn.NUMBERVALUE(tracker_rank & budget_rank), "") -> 76 | T25: =IF(is_category, ADDRESS(sort_min_row, COLUMN(combined_rank)) & ":" & ADDRESS(sort_max_row, COLUMN(combined_rank)), "") -> $S$20:$S$28 | U25: =IF(is_category, RANK(combined_rank, INDIRECT(combined_rank_range), 1), "") -> 7 | V25: =IF(is_category, ADDRESS(sort_min_row, COLUMN(combined_rank_norm)) & ":" & ADDRESS(ROW(), COLUMN(combined_rank_norm)), "") -> $U$20:$U$25 | W25: =IF(is_category, combined_rank_norm + COUNTIF(INDIRECT(combined_rank_norm_run_range), combined_rank_norm)-1, "") -> 7 | X25: =IF(is_category, header_row_id + combined_rank_unique, row_id) -> 29 | Y25: =IF(is_empty, "", INDEX($J:$J, MATCH(row_id, $X:$X, 0))) -> Body Care & Medicine | Z25: =IF(is_empty, "", IF(is_header, "Tracked", INDEX($K:$K, MATCH(row_id, $X:$X, 0)))) -> 470 | AA25: =IF(is_empty, "", IF(is_header, "Budget", INDEX($L:$L, MATCH(row_id, $X:$X, 0)))) -> 2400 | AB25: =IF(is_empty, "", IF(is_header, "% Compl.", IFERROR(out_tracked / out_budget, "-"))) -> 0.19583333 | AC25: =IF(is_empty, "", IF(is_header, "Remaining", IF(out_budget - out_tracked > 0, out_budget - out_tracked, 0))) -> 1930 | AD25: =IF(is_empty, "", IF(is_header, "Excess", IF(out_budget - out_tracked < 0, out_tracked - out_budget, 0))) -> 0
C26: {=IF(C25=-1,-1, IF(C25<income_max_row, C25+1, IF(C25=income_max_row, income_total_row, IF(C25=income_total_row, "/1", IF(C25="/1", expenses_header_row, IF(C25<expenses_max_row, C25+1, IF(C25=expenses_max_row, expenses_total_row, IF(C25=expenses_total_row, "/2", IF(C25="/2", savings_header_row, IF(C25<savings_max_row, C25+1, IF(C25=savings_max_row, savings_total_row, -1)))))))))))} -> 29 | D26: =IF(is_header, row_id, IF(NOT(is_empty), D25, -1)) -> 22 | E26: {=1*OR(row_id=income_header_row, row_id=expenses_header_row, row_id=savings_header_row)} -> 0 | F26: =1*NOT(OR(is_header, is_total, is_empty)) -> 1 | G26: {=1*OR(row_id=income_total_row, row_id=expenses_total_row, row_id=savings_total_row)} -> 0 | H26: =1*OR(row_id="/1", row_id="/2", row_id=-1) -> 0 | I26: {=IFERROR(INDEX('Budget Planning'!$C:$C, header_row_id), "")} -> Expenses | J26: {=IFERROR(INDEX('Budget Planning'!$C:$C, row_id), "")} -> Body Care & Medicine | K26: {=IF(OR(is_header, is_empty), "", IF(is_total, IF(selected_period="Total Year", SUM(Tracking[Amount] * (Tracking[Type]=type) * (YEAR(Tracking[Effective Date])=selected_year)), SUM(Tracking[Amount] * (Tracking[Type]=type) * (YEAR(Tracking[Effective Date])=selected_year) * (MONTH(Tracking[Effective Date])=selected_period))), IF(selected_period="Total Year", SUM(Tracking[Amount] * (Tracking[Type]=type) * (Tracking[Category]=item) * (YEAR(Tracking[Effective Date])=selected_year)), SUM(Tracking[Amount] * (Tracking[Type]=type) * (Tracking[Category]=item) * (YEAR(Tracking[Effective Date])=selected_year) * (MONTH(Tracking[Effective Date])=selected_period)))))} -> 470 | L26: {=IF(OR(is_header, is_empty), "", INDEX('Budget Planning'!$E:$EM, row_id, MATCH(IF(selected_period="Total Year", selected_year, DATE(selected_year, selected_period, 1)), 'Budget Planning'!$E$9:$EM$9, 0)))} -> 2400 | M26: {=IF(is_category, IF(header_row_id=income_header_row, MATCH(income_min_row, $C:$C, 0), IF(header_row_id=expenses_header_row, MATCH(expenses_min_row, $C:$C, 0), IF(header_row_id=savings_header_row, MATCH(savings_min_row, $C:$C, 0), ""))), "")} -> 20 | N26: {=IF(is_category, IF(header_row_id=income_header_row, MATCH(income_max_row, $C:$C, 0), IF(header_row_id=expenses_header_row, MATCH(expenses_max_row, $C:$C, 0), IF(header_row_id=savings_header_row, MATCH(savings_max_row, $C:$C, 0), ""))), "")} -> 28 | O26: =IF(is_category, ADDRESS(sort_min_row, COLUMN(tracked)) & ":" & ADDRESS(sort_max_row, COLUMN(tracked)), "") -> $K$20:$K$28 | P26: =IF(is_category, RANK(tracked, INDIRECT(tracked_range), 0), "") -> 6 | Q26: =IF(is_category, ADDRESS(sort_min_row, COLUMN(budget)) & ":" & ADDRESS(sort_max_row, COLUMN(budget)), "") -> $L$20:$L$28 | R26: =IF(is_category, RANK(budget, INDIRECT(budget_range), 0), "") -> 6 | S26: =IF(is_category, _xlfn.NUMBERVALUE(tracker_rank & budget_rank), "") -> 66 | T26: =IF(is_category, ADDRESS(sort_min_row, COLUMN(combined_rank)) & ":" & ADDRESS(sort_max_row, COLUMN(combined_rank)), "") -> $S$20:$S$28 | U26: =IF(is_category, RANK(combined_rank, INDIRECT(combined_rank_range), 1), "") -> 6 | V26: =IF(is_category, ADDRESS(sort_min_row, COLUMN(combined_rank_norm)) & ":" & ADDRESS(ROW(), COLUMN(combined_rank_norm)), "") -> $U$20:$U$26 | W26: =IF(is_category, combined_rank_norm + COUNTIF(INDIRECT(combined_rank_norm_run_range), combined_rank_norm)-1, "") -> 6 | X26: =IF(is_category, header_row_id + combined_rank_unique, row_id) -> 28 | Y26: =IF(is_empty, "", INDEX($J:$J, MATCH(row_id, $X:$X, 0))) -> Clothing | Z26: =IF(is_empty, "", IF(is_header, "Tracked", INDEX($K:$K, MATCH(row_id, $X:$X, 0)))) -> 360 | AA26: =IF(is_empty, "", IF(is_header, "Budget", INDEX($L:$L, MATCH(row_id, $X:$X, 0)))) -> 2400 | AB26: =IF(is_empty, "", IF(is_header, "% Compl.", IFERROR(out_tracked / out_budget, "-"))) -> 0.15 | AC26: =IF(is_empty, "", IF(is_header, "Remaining", IF(out_budget - out_tracked > 0, out_budget - out_tracked, 0))) -> 2040 | AD26: =IF(is_empty, "", IF(is_header, "Excess", IF(out_budget - out_tracked < 0, out_tracked - out_budget, 0))) -> 0
C27: {=IF(C26=-1,-1, IF(C26<income_max_row, C26+1, IF(C26=income_max_row, income_total_row, IF(C26=income_total_row, "/1", IF(C26="/1", expenses_header_row, IF(C26<expenses_max_row, C26+1, IF(C26=expenses_max_row, expenses_total_row, IF(C26=expenses_total_row, "/2", IF(C26="/2", savings_header_row, IF(C26<savings_max_row, C26+1, IF(C26=savings_max_row, savings_total_row, -1)))))))))))} -> 30 | D27: =IF(is_header, row_id, IF(NOT(is_empty), D26, -1)) -> 22 | E27: {=1*OR(row_id=income_header_row, row_id=expenses_header_row, row_id=savings_header_row)} -> 0 | F27: =1*NOT(OR(is_header, is_total, is_empty)) -> 1 | G27: {=1*OR(row_id=income_total_row, row_id=expenses_total_row, row_id=savings_total_row)} -> 0 | H27: =1*OR(row_id="/1", row_id="/2", row_id=-1) -> 0 | I27: {=IFERROR(INDEX('Budget Planning'!$C:$C, header_row_id), "")} -> Expenses | J27: {=IFERROR(INDEX('Budget Planning'!$C:$C, row_id), "")} -> Media | K27: {=IF(OR(is_header, is_empty), "", IF(is_total, IF(selected_period="Total Year", SUM(Tracking[Amount] * (Tracking[Type]=type) * (YEAR(Tracking[Effective Date])=selected_year)), SUM(Tracking[Amount] * (Tracking[Type]=type) * (YEAR(Tracking[Effective Date])=selected_year) * (MONTH(Tracking[Effective Date])=selected_period))), IF(selected_period="Total Year", SUM(Tracking[Amount] * (Tracking[Type]=type) * (Tracking[Category]=item) * (YEAR(Tracking[Effective Date])=selected_year)), SUM(Tracking[Amount] * (Tracking[Type]=type) * (Tracking[Category]=item) * (YEAR(Tracking[Effective Date])=selected_year) * (MONTH(Tracking[Effective Date])=selected_period)))))} -> 170 | L27: {=IF(OR(is_header, is_empty), "", INDEX('Budget Planning'!$E:$EM, row_id, MATCH(IF(selected_period="Total Year", selected_year, DATE(selected_year, selected_period, 1)), 'Budget Planning'!$E$9:$EM$9, 0)))} -> 600 | M27: {=IF(is_category, IF(header_row_id=income_header_row, MATCH(income_min_row, $C:$C, 0), IF(header_row_id=expenses_header_row, MATCH(expenses_min_row, $C:$C, 0), IF(header_row_id=savings_header_row, MATCH(savings_min_row, $C:$C, 0), ""))), "")} -> 20 | N27: {=IF(is_category, IF(header_row_id=income_header_row, MATCH(income_max_row, $C:$C, 0), IF(header_row_id=expenses_header_row, MATCH(expenses_max_row, $C:$C, 0), IF(header_row_id=savings_header_row, MATCH(savings_max_row, $C:$C, 0), ""))), "")} -> 28 | O27: =IF(is_category, ADDRESS(sort_min_row, COLUMN(tracked)) & ":" & ADDRESS(sort_max_row, COLUMN(tracked)), "") -> $K$20:$K$28 | P27: =IF(is_category, RANK(tracked, INDIRECT(tracked_range), 0), "") -> 8 | Q27: =IF(is_category, ADDRESS(sort_min_row, COLUMN(budget)) & ":" & ADDRESS(sort_max_row, COLUMN(budget)), "") -> $L$20:$L$28 | R27: =IF(is_category, RANK(budget, INDIRECT(budget_range), 0), "") -> 8 | S27: =IF(is_category, _xlfn.NUMBERVALUE(tracker_rank & budget_rank), "") -> 88 | T27: =IF(is_category, ADDRESS(sort_min_row, COLUMN(combined_rank)) & ":" & ADDRESS(sort_max_row, COLUMN(combined_rank)), "") -> $S$20:$S$28 | U27: =IF(is_category, RANK(combined_rank, INDIRECT(combined_rank_range), 1), "") -> 8 | V27: =IF(is_category, ADDRESS(sort_min_row, COLUMN(combined_rank_norm)) & ":" & ADDRESS(ROW(), COLUMN(combined_rank_norm)), "") -> $U$20:$U$27 | W27: =IF(is_category, combined_rank_norm + COUNTIF(INDIRECT(combined_rank_norm_run_range), combined_rank_norm)-1, "") -> 8 | X27: =IF(is_category, header_row_id + combined_rank_unique, row_id) -> 30 | Y27: =IF(is_empty, "", INDEX($J:$J, MATCH(row_id, $X:$X, 0))) -> Media | Z27: =IF(is_empty, "", IF(is_header, "Tracked", INDEX($K:$K, MATCH(row_id, $X:$X, 0)))) -> 170 | AA27: =IF(is_empty, "", IF(is_header, "Budget", INDEX($L:$L, MATCH(row_id, $X:$X, 0)))) -> 600 | AB27: =IF(is_empty, "", IF(is_header, "% Compl.", IFERROR(out_tracked / out_budget, "-"))) -> 0.28333333 | AC27: =IF(is_empty, "", IF(is_header, "Remaining", IF(out_budget - out_tracked > 0, out_budget - out_tracked, 0))) -> 430 | AD27: =IF(is_empty, "", IF(is_header, "Excess", IF(out_budget - out_tracked < 0, out_tracked - out_budget, 0))) -> 0
C28: {=IF(C27=-1,-1, IF(C27<income_max_row, C27+1, IF(C27=income_max_row, income_total_row, IF(C27=income_total_row, "/1", IF(C27="/1", expenses_header_row, IF(C27<expenses_max_row, C27+1, IF(C27=expenses_max_row, expenses_total_row, IF(C27=expenses_total_row, "/2", IF(C27="/2", savings_header_row, IF(C27<savings_max_row, C27+1, IF(C27=savings_max_row, savings_total_row, -1)))))))))))} -> 31 | D28: =IF(is_header, row_id, IF(NOT(is_empty), D27, -1)) -> 22 | E28: {=1*OR(row_id=income_header_row, row_id=expenses_header_row, row_id=savings_header_row)} -> 0 | F28: =1*NOT(OR(is_header, is_total, is_empty)) -> 1 | G28: {=1*OR(row_id=income_total_row, row_id=expenses_total_row, row_id=savings_total_row)} -> 0 | H28: =1*OR(row_id="/1", row_id="/2", row_id=-1) -> 0 | I28: {=IFERROR(INDEX('Budget Planning'!$C:$C, header_row_id), "")} -> Expenses | J28: {=IFERROR(INDEX('Budget Planning'!$C:$C, row_id), "")} -> Fun & Vacation | K28: {=IF(OR(is_header, is_empty), "", IF(is_total, IF(selected_period="Total Year", SUM(Tracking[Amount] * (Tracking[Type]=type) * (YEAR(Tracking[Effective Date])=selected_year)), SUM(Tracking[Amount] * (Tracking[Type]=type) * (YEAR(Tracking[Effective Date])=selected_year) * (MONTH(Tracking[Effective Date])=selected_period))), IF(selected_period="Total Year", SUM(Tracking[Amount] * (Tracking[Type]=type) * (Tracking[Category]=item) * (YEAR(Tracking[Effective Date])=selected_year)), SUM(Tracking[Amount] * (Tracking[Type]=type) * (Tracking[Category]=item) * (YEAR(Tracking[Effective Date])=selected_year) * (MONTH(Tracking[Effective Date])=selected_period)))))} -> 730 | L28: {=IF(OR(is_header, is_empty), "", INDEX('Budget Planning'!$E:$EM, row_id, MATCH(IF(selected_period="Total Year", selected_year, DATE(selected_year, selected_period, 1)), 'Budget Planning'!$E$9:$EM$9, 0)))} -> 6000 | M28: {=IF(is_category, IF(header_row_id=income_header_row, MATCH(income_min_row, $C:$C, 0), IF(header_row_id=expenses_header_row, MATCH(expenses_min_row, $C:$C, 0), IF(header_row_id=savings_header_row, MATCH(savings_min_row, $C:$C, 0), ""))), "")} -> 20 | N28: {=IF(is_category, IF(header_row_id=income_header_row, MATCH(income_max_row, $C:$C, 0), IF(header_row_id=expenses_header_row, MATCH(expenses_max_row, $C:$C, 0), IF(header_row_id=savings_header_row, MATCH(savings_max_row, $C:$C, 0), ""))), "")} -> 28 | O28: =IF(is_category, ADDRESS(sort_min_row, COLUMN(tracked)) & ":" & ADDRESS(sort_max_row, COLUMN(tracked)), "") -> $K$20:$K$28 | P28: =IF(is_category, RANK(tracked, INDIRECT(tracked_range), 0), "") -> 4 | Q28: =IF(is_category, ADDRESS(sort_min_row, COLUMN(budget)) & ":" & ADDRESS(sort_max_row, COLUMN(budget)), "") -> $L$20:$L$28 | R28: =IF(is_category, RANK(budget, INDIRECT(budget_range), 0), "") -> 2 | S28: =IF(is_category, _xlfn.NUMBERVALUE(tracker_rank & budget_rank), "") -> 42 | T28: =IF(is_category, ADDRESS(sort_min_row, COLUMN(combined_rank)) & ":" & ADDRESS(sort_max_row, COLUMN(combined_rank)), "") -> $S$20:$S$28 | U28: =IF(is_category, RANK(combined_rank, INDIRECT(combined_rank_range), 1), "") -> 4 | V28: =IF(is_category, ADDRESS(sort_min_row, COLUMN(combined_rank_norm)) & ":" & ADDRESS(ROW(), COLUMN(combined_rank_norm)), "") -> $U$20:$U$28 | W28: =IF(is_category, combined_rank_norm + COUNTIF(INDIRECT(combined_rank_norm_run_range), combined_rank_norm)-1, "") -> 4 | X28: =IF(is_category, header_row_id + combined_rank_unique, row_id) -> 26 | Y28: =IF(is_empty, "", INDEX($J:$J, MATCH(row_id, $X:$X, 0))) -> Insurances | Z28: =IF(is_empty, "", IF(is_header, "Tracked", INDEX($K:$K, MATCH(row_id, $X:$X, 0)))) -> 150 | AA28: =IF(is_empty, "", IF(is_header, "Budget", INDEX($L:$L, MATCH(row_id, $X:$X, 0)))) -> 600 | AB28: =IF(is_empty, "", IF(is_header, "% Compl.", IFERROR(out_tracked / out_budget, "-"))) -> 0.25 | AC28: =IF(is_empty, "", IF(is_header, "Remaining", IF(out_budget - out_tracked > 0, out_budget - out_tracked, 0))) -> 450 | AD28: =IF(is_empty, "", IF(is_header, "Excess", IF(out_budget - out_tracked < 0, out_tracked - out_budget, 0))) -> 0
C29: {=IF(C28=-1,-1, IF(C28<income_max_row, C28+1, IF(C28=income_max_row, income_total_row, IF(C28=income_total_row, "/1", IF(C28="/1", expenses_header_row, IF(C28<expenses_max_row, C28+1, IF(C28=expenses_max_row, expenses_total_row, IF(C28=expenses_total_row, "/2", IF(C28="/2", savings_header_row, IF(C28<savings_max_row, C28+1, IF(C28=savings_max_row, savings_total_row, -1)))))))))))} -> 36 | D29: =IF(is_header, row_id, IF(NOT(is_empty), D28, -1)) -> 22 | E29: {=1*OR(row_id=income_header_row, row_id=expenses_header_row, row_id=savings_header_row)} -> 0 | F29: =1*NOT(OR(is_header, is_total, is_empty)) -> 0 | G29: {=1*OR(row_id=income_total_row, row_id=expenses_total_row, row_id=savings_total_row)} -> 1 | H29: =1*OR(row_id="/1", row_id="/2", row_id=-1) -> 0 | I29: {=IFERROR(INDEX('Budget Planning'!$C:$C, header_row_id), "")} -> Expenses | J29: {=IFERROR(INDEX('Budget Planning'!$C:$C, row_id), "")} -> Total | K29: {=IF(OR(is_header, is_empty), "", IF(is_total, IF(selected_period="Total Year", SUM(Tracking[Amount] * (Tracking[Type]=type) * (YEAR(Tracking[Effective Date])=selected_year)), SUM(Tracking[Amount] * (Tracking[Type]=type) * (YEAR(Tracking[Effective Date])=selected_year) * (MONTH(Tracking[Effective Date])=selected_period))), IF(selected_period="Total Year", SUM(Tracking[Amount] * (Tracking[Type]=type) * (Tracking[Category]=item) * (YEAR(Tracking[Effective Date])=selected_year)), SUM(Tracking[Amount] * (Tracking[Type]=type) * (Tracking[Category]=item) * (YEAR(Tracking[Effective Date])=selected_year) * (MONTH(Tracking[Effective Date])=selected_period)))))} -> 7890 | L29: {=IF(OR(is_header, is_empty), "", INDEX('Budget Planning'!$E:$EM, row_id, MATCH(IF(selected_period="Total Year", selected_year, DATE(selected_year, selected_period, 1)), 'Budget Planning'!$E$9:$EM$9, 0)))} -> 37800 | M29: {=IF(is_category, IF(header_row_id=income_header_row, MATCH(income_min_row, $C:$C, 0), IF(header_row_id=expenses_header_row, MATCH(expenses_min_row, $C:$C, 0), IF(header_row_id=savings_header_row, MATCH(savings_min_row, $C:$C, 0), ""))), "")} | N29: {=IF(is_category, IF(header_row_id=income_header_row, MATCH(income_max_row, $C:$C, 0), IF(header_row_id=expenses_header_row, MATCH(expenses_max_row, $C:$C, 0), IF(header_row_id=savings_header_row, MATCH(savings_max_row, $C:$C, 0), ""))), "")} | O29: =IF(is_category, ADDRESS(sort_min_row, COLUMN(tracked)) & ":" & ADDRESS(sort_max_row, COLUMN(tracked)), "") | P29: =IF(is_category, RANK(tracked, INDIRECT(tracked_range), 0), "") | Q29: =IF(is_category, ADDRESS(sort_min_row, COLUMN(budget)) & ":" & ADDRESS(sort_max_row, COLUMN(budget)), "") | R29: =IF(is_category, RANK(budget, INDIRECT(budget_range), 0), "") | S29: =IF(is_category, _xlfn.NUMBERVALUE(tracker_rank & budget_rank), "") | T29: =IF(is_category, ADDRESS(sort_min_row, COLUMN(combined_rank)) & ":" & ADDRESS(sort_max_row, COLUMN(combined_rank)), "") | U29: =IF(is_category, RANK(combined_rank, INDIRECT(combined_rank_range), 1), "") | V29: =IF(is_category, ADDRESS(sort_min_row, COLUMN(combined_rank_norm)) & ":" & ADDRESS(ROW(), COLUMN(combined_rank_norm)), "") | W29: =IF(is_category, combined_rank_norm + COUNTIF(INDIRECT(combined_rank_norm_run_range), combined_rank_norm)-1, "") | X29: =IF(is_category, header_row_id + combined_rank_unique, row_id) -> 36 | Y29: =IF(is_empty, "", INDEX($J:$J, MATCH(row_id, $X:$X, 0))) -> Total | Z29: =IF(is_empty, "", IF(is_header, "Tracked", INDEX($K:$K, MATCH(row_id, $X:$X, 0)))) -> 7890 | AA29: =IF(is_empty, "", IF(is_header, "Budget", INDEX($L:$L, MATCH(row_id, $X:$X, 0)))) -> 37800 | AB29: =IF(is_empty, "", IF(is_header, "% Compl.", IFERROR(out_tracked / out_budget, "-"))) -> 0.20873016 | AC29: =IF(is_empty, "", IF(is_header, "Remaining", IF(out_budget - out_tracked > 0, out_budget - out_tracked, 0))) -> 29910 | AD29: =IF(is_empty, "", IF(is_header, "Excess", IF(out_budget - out_tracked < 0, out_tracked - out_budget, 0))) -> 0 | AI29: =Calculations!I35 -> Housing | AJ29: =Calculations!J35 -> 3600 | AP29: =Calculations!M35 -> Emergency Fund | AQ29: =Calculations!N35 -> 1140
C30: {=IF(C29=-1,-1, IF(C29<income_max_row, C29+1, IF(C29=income_max_row, income_total_row, IF(C29=income_total_row, "/1", IF(C29="/1", expenses_header_row, IF(C29<expenses_max_row, C29+1, IF(C29=expenses_max_row, expenses_total_row, IF(C29=expenses_total_row, "/2", IF(C29="/2", savings_header_row, IF(C29<savings_max_row, C29+1, IF(C29=savings_max_row, savings_total_row, -1)))))))))))} -> /2 | D30: =IF(is_header, row_id, IF(NOT(is_empty), D29, -1)) -> -1 | E30: {=1*OR(row_id=income_header_row, row_id=expenses_header_row, row_id=savings_header_row)} -> 0 | F30: =1*NOT(OR(is_header, is_total, is_empty)) -> 0 | G30: {=1*OR(row_id=income_total_row, row_id=expenses_total_row, row_id=savings_total_row)} -> 0 | H30: =1*OR(row_id="/1", row_id="/2", row_id=-1) -> 1 | I30: {=IFERROR(INDEX('Budget Planning'!$C:$C, header_row_id), "")} | J30: {=IFERROR(INDEX('Budget Planning'!$C:$C, row_id), "")} | K30: {=IF(OR(is_header, is_empty), "", IF(is_total, IF(selected_period="Total Year", SUM(Tracking[Amount] * (Tracking[Type]=type) * (YEAR(Tracking[Effective Date])=selected_year)), SUM(Tracking[Amount] * (Tracking[Type]=type) * (YEAR(Tracking[Effective Date])=selected_year) * (MONTH(Tracking[Effective Date])=selected_period))), IF(selected_period="Total Year", SUM(Tracking[Amount] * (Tracking[Type]=type) * (Tracking[Category]=item) * (YEAR(Tracking[Effective Date])=selected_year)), SUM(Tracking[Amount] * (Tracking[Type]=type) * (Tracking[Category]=item) * (YEAR(Tracking[Effective Date])=selected_year) * (MONTH(Tracking[Effective Date])=selected_period)))))} | L30: {=IF(OR(is_header, is_empty), "", INDEX('Budget Planning'!$E:$EM, row_id, MATCH(IF(selected_period="Total Year", selected_year, DATE(selected_year, selected_period, 1)), 'Budget Planning'!$E$9:$EM$9, 0)))} | M30: {=IF(is_category, IF(header_row_id=income_header_row, MATCH(income_min_row, $C:$C, 0), IF(header_row_id=expenses_header_row, MATCH(expenses_min_row, $C:$C, 0), IF(header_row_id=savings_header_row, MATCH(savings_min_row, $C:$C, 0), ""))), "")} | N30: {=IF(is_category, IF(header_row_id=income_header_row, MATCH(income_max_row, $C:$C, 0), IF(header_row_id=expenses_header_row, MATCH(expenses_max_row, $C:$C, 0), IF(header_row_id=savings_header_row, MATCH(savings_max_row, $C:$C, 0), ""))), "")} | O30: =IF(is_category, ADDRESS(sort_min_row, COLUMN(tracked)) & ":" & ADDRESS(sort_max_row, COLUMN(tracked)), "") | P30: =IF(is_category, RANK(tracked, INDIRECT(tracked_range), 0), "") | Q30: =IF(is_category, ADDRESS(sort_min_row, COLUMN(budget)) & ":" & ADDRESS(sort_max_row, COLUMN(budget)), "") | R30: =IF(is_category, RANK(budget, INDIRECT(budget_range), 0), "") | S30: =IF(is_category, _xlfn.NUMBERVALUE(tracker_rank & budget_rank), "") | T30: =IF(is_category, ADDRESS(sort_min_row, COLUMN(combined_rank)) & ":" & ADDRESS(sort_max_row, COLUMN(combined_rank)), "") | U30: =IF(is_category, RANK(combined_rank, INDIRECT(combined_rank_range), 1), "") | V30: =IF(is_category, ADDRESS(sort_min_row, COLUMN(combined_rank_norm)) & ":" & ADDRESS(ROW(), COLUMN(combined_rank_norm)), "") | W30: =IF(is_category, combined_rank_norm + COUNTIF(INDIRECT(combined_rank_norm_run_range), combined_rank_norm)-1, "") | X30: =IF(is_category, header_row_id + combined_rank_unique, row_id) -> /2 | Y30: =IF(is_empty, "", INDEX($J:$J, MATCH(row_id, $X:$X, 0))) | Z30: =IF(is_empty, "", IF(is_header, "Tracked", INDEX($K:$K, MATCH(row_id, $X:$X, 0)))) | AA30: =IF(is_empty, "", IF(is_header, "Budget", INDEX($L:$L, MATCH(row_id, $X:$X, 0)))) | AB30: =IF(is_empty, "", IF(is_header, "% Compl.", IFERROR(out_tracked / out_budget, "-"))) | AC30: =IF(is_empty, "", IF(is_header, "Remaining", IF(out_budget - out_tracked > 0, out_budget - out_tracked, 0))) | AD30: =IF(is_empty, "", IF(is_header, "Excess", IF(out_budget - out_tracked < 0, out_tracked - out_budget, 0))) | AI30: =Calculations!I36 -> Groceries | AJ30: =Calculations!J36 -> 900 | AP30: =Calculations!M36 -> Retirement Account | AQ30: =Calculations!N36 -> 800
C31: {=IF(C30=-1,-1, IF(C30<income_max_row, C30+1, IF(C30=income_max_row, income_total_row, IF(C30=income_total_row, "/1", IF(C30="/1", expenses_header_row, IF(C30<expenses_max_row, C30+1, IF(C30=expenses_max_row, expenses_total_row, IF(C30=expenses_total_row, "/2", IF(C30="/2", savings_header_row, IF(C30<savings_max_row, C30+1, IF(C30=savings_max_row, savings_total_row, -1)))))))))))} -> 38 | D31: =IF(is_header, row_id, IF(NOT(is_empty), D30, -1)) -> 38 | E31: {=1*OR(row_id=income_header_row, row_id=expenses_header_row, row_id=savings_header_row)} -> 1 | F31: =1*NOT(OR(is_header, is_total, is_empty)) -> 0 | G31: {=1*OR(row_id=income_total_row, row_id=expenses_total_row, row_id=savings_total_row)} -> 0 | H31: =1*OR(row_id="/1", row_id="/2", row_id=-1) -> 0 | I31: {=IFERROR(INDEX('Budget Planning'!$C:$C, header_row_id), "")} -> Savings | J31: {=IFERROR(INDEX('Budget Planning'!$C:$C, row_id), "")} -> Savings | K31: {=IF(OR(is_header, is_empty), "", IF(is_total, IF(selected_period="Total Year", SUM(Tracking[Amount] * (Tracking[Type]=type) * (YEAR(Tracking[Effective Date])=selected_year)), SUM(Tracking[Amount] * (Tracking[Type]=type) * (YEAR(Tracking[Effective Date])=selected_year) * (MONTH(Tracking[Effective Date])=selected_period))), IF(selected_period="Total Year", SUM(Tracking[Amount] * (Tracking[Type]=type) * (Tracking[Category]=item) * (YEAR(Tracking[Effective Date])=selected_year)), SUM(Tracking[Amount] * (Tracking[Type]=type) * (Tracking[Category]=item) * (YEAR(Tracking[Effective Date])=selected_year) * (MONTH(Tracking[Effective Date])=selected_period)))))} | L31: {=IF(OR(is_header, is_empty), "", INDEX('Budget Planning'!$E:$EM, row_id, MATCH(IF(selected_period="Total Year", selected_year, DATE(selected_year, selected_period, 1)), 'Budget Planning'!$E$9:$EM$9, 0)))} | M31: {=IF(is_category, IF(header_row_id=income_header_row, MATCH(income_min_row, $C:$C, 0), IF(header_row_id=expenses_header_row, MATCH(expenses_min_row, $C:$C, 0), IF(header_row_id=savings_header_row, MATCH(savings_min_row, $C:$C, 0), ""))), "")} | N31: {=IF(is_category, IF(header_row_id=income_header_row, MATCH(income_max_row, $C:$C, 0), IF(header_row_id=expenses_header_row, MATCH(expenses_max_row, $C:$C, 0), IF(header_row_id=savings_header_row, MATCH(savings_max_row, $C:$C, 0), ""))), "")} | O31: =IF(is_category, ADDRESS(sort_min_row, COLUMN(tracked)) & ":" & ADDRESS(sort_max_row, COLUMN(tracked)), "") | P31: =IF(is_category, RANK(tracked, INDIRECT(tracked_range), 0), "") | Q31: =IF(is_category, ADDRESS(sort_min_row, COLUMN(budget)) & ":" & ADDRESS(sort_max_row, COLUMN(budget)), "") | R31: =IF(is_category, RANK(budget, INDIRECT(budget_range), 0), "") | S31: =IF(is_category, _xlfn.NUMBERVALUE(tracker_rank & budget_rank), "") | T31: =IF(is_category, ADDRESS(sort_min_row, COLUMN(combined_rank)) & ":" & ADDRESS(sort_max_row, COLUMN(combined_rank)), "") | U31: =IF(is_category, RANK(combined_rank, INDIRECT(combined_rank_range), 1), "") | V31: =IF(is_category, ADDRESS(sort_min_row, COLUMN(combined_rank_norm)) & ":" & ADDRESS(ROW(), COLUMN(combined_rank_norm)), "") | W31: =IF(is_category, combined_rank_norm + COUNTIF(INDIRECT(combined_rank_norm_run_range), combined_rank_norm)-1, "") | X31: =IF(is_category, header_row_id + combined_rank_unique, row_id) -> 38 | Y31: =IF(is_empty, "", INDEX($J:$J, MATCH(row_id, $X:$X, 0))) -> Savings | Z31: =IF(is_empty, "", IF(is_header, "Tracked", INDEX($K:$K, MATCH(row_id, $X:$X, 0)))) -> Tracked | AA31: =IF(is_empty, "", IF(is_header, "Budget", INDEX($L:$L, MATCH(row_id, $X:$X, 0)))) -> Budget | AB31: =IF(is_empty, "", IF(is_header, "% Compl.", IFERROR(out_tracked / out_budget, "-"))) -> % Compl. | AC31: =IF(is_empty, "", IF(is_header, "Remaining", IF(out_budget - out_tracked > 0, out_budget - out_tracked, 0))) -> Remaining | AD31: =IF(is_empty, "", IF(is_header, "Excess", IF(out_budget - out_tracked < 0, out_tracked - out_budget, 0))) -> Excess | AI31: =Calculations!I37 -> Utilites | AJ31: =Calculations!J37 -> 900 | AP31: =Calculations!M37 -> Stock Portfolio | AQ31: =Calculations!N37 -> 750
C32: {=IF(C31=-1,-1, IF(C31<income_max_row, C31+1, IF(C31=income_max_row, income_total_row, IF(C31=income_total_row, "/1", IF(C31="/1", expenses_header_row, IF(C31<expenses_max_row, C31+1, IF(C31=expenses_max_row, expenses_total_row, IF(C31=expenses_total_row, "/2", IF(C31="/2", savings_header_row, IF(C31<savings_max_row, C31+1, IF(C31=savings_max_row, savings_total_row, -1)))))))))))} -> 39 | D32: =IF(is_header, row_id, IF(NOT(is_empty), D31, -1)) -> 38 | E32: {=1*OR(row_id=income_header_row, row_id=expenses_header_row, row_id=savings_header_row)} -> 0 | F32: =1*NOT(OR(is_header, is_total, is_empty)) -> 1 | G32: {=1*OR(row_id=income_total_row, row_id=expenses_total_row, row_id=savings_total_row)} -> 0 | H32: =1*OR(row_id="/1", row_id="/2", row_id=-1) -> 0 | I32: {=IFERROR(INDEX('Budget Planning'!$C:$C, header_row_id), "")} -> Savings | J32: {=IFERROR(INDEX('Budget Planning'!$C:$C, row_id), "")} -> Emergency Fund | K32: {=IF(OR(is_header, is_empty), "", IF(is_total, IF(selected_period="Total Year", SUM(Tracking[Amount] * (Tracking[Type]=type) * (YEAR(Tracking[Effective Date])=selected_year)), SUM(Tracking[Amount] * (Tracking[Type]=type) * (YEAR(Tracking[Effective Date])=selected_year) * (MONTH(Tracking[Effective Date])=selected_period))), IF(selected_period="Total Year", SUM(Tracking[Amount] * (Tracking[Type]=type) * (Tracking[Category]=item) * (YEAR(Tracking[Effective Date])=selected_year)), SUM(Tracking[Amount] * (Tracking[Type]=type) * (Tracking[Category]=item) * (YEAR(Tracking[Effective Date])=selected_year) * (MONTH(Tracking[Effective Date])=selected_period)))))} -> 1140 | L32: {=IF(OR(is_header, is_empty), "", INDEX('Budget Planning'!$E:$EM, row_id, MATCH(IF(selected_period="Total Year", selected_year, DATE(selected_year, selected_period, 1)), 'Budget Planning'!$E$9:$EM$9, 0)))} -> 3000 | M32: {=IF(is_category, IF(header_row_id=income_header_row, MATCH(income_min_row, $C:$C, 0), IF(header_row_id=expenses_header_row, MATCH(expenses_min_row, $C:$C, 0), IF(header_row_id=savings_header_row, MATCH(savings_min_row, $C:$C, 0), ""))), "")} -> 32 | N32: {=IF(is_category, IF(header_row_id=income_header_row, MATCH(income_max_row, $C:$C, 0), IF(header_row_id=expenses_header_row, MATCH(expenses_max_row, $C:$C, 0), IF(header_row_id=savings_header_row, MATCH(savings_max_row, $C:$C, 0), ""))), "")} -> 36 | O32: =IF(is_category, ADDRESS(sort_min_row, COLUMN(tracked)) & ":" & ADDRESS(sort_max_row, COLUMN(tracked)), "") -> $K$32:$K$36 | P32: =IF(is_category, RANK(tracked, INDIRECT(tracked_range), 0), "") -> 1 | Q32: =IF(is_category, ADDRESS(sort_min_row, COLUMN(budget)) & ":" & ADDRESS(sort_max_row, COLUMN(budget)), "") -> $L$32:$L$36 | R32: =IF(is_category, RANK(budget, INDIRECT(budget_range), 0), "") -> 4 | S32: =IF(is_category, _xlfn.NUMBERVALUE(tracker_rank & budget_rank), "") -> 14 | T32: =IF(is_category, ADDRESS(sort_min_row, COLUMN(combined_rank)) & ":" & ADDRESS(sort_max_row, COLUMN(combined_rank)), "") -> $S$32:$S$36 | U32: =IF(is_category, RANK(combined_rank, INDIRECT(combined_rank_range), 1), "") -> 1 | V32: =IF(is_category, ADDRESS(sort_min_row, COLUMN(combined_rank_norm)) & ":" & ADDRESS(ROW(), COLUMN(combined_rank_norm)), "") -> $U$32:$U$32 | W32: =IF(is_category, combined_rank_norm + COUNTIF(INDIRECT(combined_rank_norm_run_range), combined_rank_norm)-1, "") -> 1 | X32: =IF(is_category, header_row_id + combined_rank_unique, row_id) -> 39 | Y32: =IF(is_empty, "", INDEX($J:$J, MATCH(row_id, $X:$X, 0))) -> Emergency Fund | Z32: =IF(is_empty, "", IF(is_header, "Tracked", INDEX($K:$K, MATCH(row_id, $X:$X, 0)))) -> 1140 | AA32: =IF(is_empty, "", IF(is_header, "Budget", INDEX($L:$L, MATCH(row_id, $X:$X, 0)))) -> 3000 | AB32: =IF(is_empty, "", IF(is_header, "% Compl.", IFERROR(out_tracked / out_budget, "-"))) -> 0.38 | AC32: =IF(is_empty, "", IF(is_header, "Remaining", IF(out_budget - out_tracked > 0, out_budget - out_tracked, 0))) -> 1860 | AD32: =IF(is_empty, "", IF(is_header, "Excess", IF(out_budget - out_tracked < 0, out_tracked - out_budget, 0))) -> 0 | AI32: =Calculations!I38 -> Fun & Vacation | AJ32: =Calculations!J38 -> 730 | AP32: =Calculations!M38 -> Sinking Fund Rest | AQ32: =Calculations!N38 -> 400
C33: {=IF(C32=-1,-1, IF(C32<income_max_row, C32+1, IF(C32=income_max_row, income_total_row, IF(C32=income_total_row, "/1", IF(C32="/1", expenses_header_row, IF(C32<expenses_max_row, C32+1, IF(C32=expenses_max_row, expenses_total_row, IF(C32=expenses_total_row, "/2", IF(C32="/2", savings_header_row, IF(C32<savings_max_row, C32+1, IF(C32=savings_max_row, savings_total_row, -1)))))))))))} -> 40 | D33: =IF(is_header, row_id, IF(NOT(is_empty), D32, -1)) -> 38 | E33: {=1*OR(row_id=income_header_row, row_id=expenses_header_row, row_id=savings_header_row)} -> 0 | F33: =1*NOT(OR(is_header, is_total, is_empty)) -> 1 | G33: {=1*OR(row_id=income_total_row, row_id=expenses_total_row, row_id=savings_total_row)} -> 0 | H33: =1*OR(row_id="/1", row_id="/2", row_id=-1) -> 0 | I33: {=IFERROR(INDEX('Budget Planning'!$C:$C, header_row_id), "")} -> Savings | J33: {=IFERROR(INDEX('Budget Planning'!$C:$C, row_id), "")} -> Retirement Account | K33: {=IF(OR(is_header, is_empty), "", IF(is_total, IF(selected_period="Total Year", SUM(Tracking[Amount] * (Tracking[Type]=type) * (YEAR(Tracking[Effective Date])=selected_year)), SUM(Tracking[Amount] * (Tracking[Type]=type) * (YEAR(Tracking[Effective Date])=selected_year) * (MONTH(Tracking[Effective Date])=selected_period))), IF(selected_period="Total Year", SUM(Tracking[Amount] * (Tracking[Type]=type) * (Tracking[Category]=item) * (YEAR(Tracking[Effective Date])=selected_year)), SUM(Tracking[Amount] * (Tracking[Type]=type) * (Tracking[Category]=item) * (YEAR(Tracking[Effective Date])=selected_year) * (MONTH(Tracking[Effective Date])=selected_period)))))} -> 800 | L33: {=IF(OR(is_header, is_empty), "", INDEX('Budget Planning'!$E:$EM, row_id, MATCH(IF(selected_period="Total Year", selected_year, DATE(selected_year, selected_period, 1)), 'Budget Planning'!$E$9:$EM$9, 0)))} -> 4800 | M33: {=IF(is_category, IF(header_row_id=income_header_row, MATCH(income_min_row, $C:$C, 0), IF(header_row_id=expenses_header_row, MATCH(expenses_min_row, $C:$C, 0), IF(header_row_id=savings_header_row, MATCH(savings_min_row, $C:$C, 0), ""))), "")} -> 32 | N33: {=IF(is_category, IF(header_row_id=income_header_row, MATCH(income_max_row, $C:$C, 0), IF(header_row_id=expenses_header_row, MATCH(expenses_max_row, $C:$C, 0), IF(header_row_id=savings_header_row, MATCH(savings_max_row, $C:$C, 0), ""))), "")} -> 36 | O33: =IF(is_category, ADDRESS(sort_min_row, COLUMN(tracked)) & ":" & ADDRESS(sort_max_row, COLUMN(tracked)), "") -> $K$32:$K$36 | P33: =IF(is_category, RANK(tracked, INDIRECT(tracked_range), 0), "") -> 2 | Q33: =IF(is_category, ADDRESS(sort_min_row, COLUMN(budget)) & ":" & ADDRESS(sort_max_row, COLUMN(budget)), "") -> $L$32:$L$36 | R33: =IF(is_category, RANK(budget, INDIRECT(budget_range), 0), "") -> 3 | S33: =IF(is_category, _xlfn.NUMBERVALUE(tracker_rank & budget_rank), "") -> 23 | T33: =IF(is_category, ADDRESS(sort_min_row, COLUMN(combined_rank)) & ":" & ADDRESS(sort_max_row, COLUMN(combined_rank)), "") -> $S$32:$S$36 | U33: =IF(is_category, RANK(combined_rank, INDIRECT(combined_rank_range), 1), "") -> 2 | V33: =IF(is_category, ADDRESS(sort_min_row, COLUMN(combined_rank_norm)) & ":" & ADDRESS(ROW(), COLUMN(combined_rank_norm)), "") -> $U$32:$U$33 | W33: =IF(is_category, combined_rank_norm + COUNTIF(INDIRECT(combined_rank_norm_run_range), combined_rank_norm)-1, "") -> 2 | X33: =IF(is_category, header_row_id + combined_rank_unique, row_id) -> 40 | Y33: =IF(is_empty, "", INDEX($J:$J, MATCH(row_id, $X:$X, 0))) -> Retirement Account | Z33: =IF(is_empty, "", IF(is_header, "Tracked", INDEX($K:$K, MATCH(row_id, $X:$X, 0)))) -> 800 | AA33: =IF(is_empty, "", IF(is_header, "Budget", INDEX($L:$L, MATCH(row_id, $X:$X, 0)))) -> 4800 | AB33: =IF(is_empty, "", IF(is_header, "% Compl.", IFERROR(out_tracked / out_budget, "-"))) -> 0.16666667 | AC33: =IF(is_empty, "", IF(is_header, "Remaining", IF(out_budget - out_tracked > 0, out_budget - out_tracked, 0))) -> 4000 | AD33: =IF(is_empty, "", IF(is_header, "Excess", IF(out_budget - out_tracked < 0, out_tracked - out_budget, 0))) -> 0 | AI33: =Calculations!I39 -> Transportation | AJ33: =Calculations!J39 -> 610 | AP33: =Calculations!M39 | AQ33: =Calculations!N39
C34: {=IF(C33=-1,-1, IF(C33<income_max_row, C33+1, IF(C33=income_max_row, income_total_row, IF(C33=income_total_row, "/1", IF(C33="/1", expenses_header_row, IF(C33<expenses_max_row, C33+1, IF(C33=expenses_max_row, expenses_total_row, IF(C33=expenses_total_row, "/2", IF(C33="/2", savings_header_row, IF(C33<savings_max_row, C33+1, IF(C33=savings_max_row, savings_total_row, -1)))))))))))} -> 41 | D34: =IF(is_header, row_id, IF(NOT(is_empty), D33, -1)) -> 38 | E34: {=1*OR(row_id=income_header_row, row_id=expenses_header_row, row_id=savings_header_row)} -> 0 | F34: =1*NOT(OR(is_header, is_total, is_empty)) -> 1 | G34: {=1*OR(row_id=income_total_row, row_id=expenses_total_row, row_id=savings_total_row)} -> 0 | H34: =1*OR(row_id="/1", row_id="/2", row_id=-1) -> 0 | I34: {=IFERROR(INDEX('Budget Planning'!$C:$C, header_row_id), "")} -> Savings | J34: {=IFERROR(INDEX('Budget Planning'!$C:$C, row_id), "")} -> Stock Portfolio | K34: {=IF(OR(is_header, is_empty), "", IF(is_total, IF(selected_period="Total Year", SUM(Tracking[Amount] * (Tracking[Type]=type) * (YEAR(Tracking[Effective Date])=selected_year)), SUM(Tracking[Amount] * (Tracking[Type]=type) * (YEAR(Tracking[Effective Date])=selected_year) * (MONTH(Tracking[Effective Date])=selected_period))), IF(selected_period="Total Year", SUM(Tracking[Amount] * (Tracking[Type]=type) * (Tracking[Category]=item) * (YEAR(Tracking[Effective Date])=selected_year)), SUM(Tracking[Amount] * (Tracking[Type]=type) * (Tracking[Category]=item) * (YEAR(Tracking[Effective Date])=selected_year) * (MONTH(Tracking[Effective Date])=selected_period)))))} -> 750 | L34: {=IF(OR(is_header, is_empty), "", INDEX('Budget Planning'!$E:$EM, row_id, MATCH(IF(selected_period="Total Year", selected_year, DATE(selected_year, selected_period, 1)), 'Budget Planning'!$E$9:$EM$9, 0)))} -> 7200 | M34: {=IF(is_category, IF(header_row_id=income_header_row, MATCH(income_min_row, $C:$C, 0), IF(header_row_id=expenses_header_row, MATCH(expenses_min_row, $C:$C, 0), IF(header_row_id=savings_header_row, MATCH(savings_min_row, $C:$C, 0), ""))), "")} -> 32 | N34: {=IF(is_category, IF(header_row_id=income_header_row, MATCH(income_max_row, $C:$C, 0), IF(header_row_id=expenses_header_row, MATCH(expenses_max_row, $C:$C, 0), IF(header_row_id=savings_header_row, MATCH(savings_max_row, $C:$C, 0), ""))), "")} -> 36 | O34: =IF(is_category, ADDRESS(sort_min_row, COLUMN(tracked)) & ":" & ADDRESS(sort_max_row, COLUMN(tracked)), "") -> $K$32:$K$36 | P34: =IF(is_category, RANK(tracked, INDIRECT(tracked_range), 0), "") -> 3 | Q34: =IF(is_category, ADDRESS(sort_min_row, COLUMN(budget)) & ":" & ADDRESS(sort_max_row, COLUMN(budget)), "") -> $L$32:$L$36 | R34: =IF(is_category, RANK(budget, INDIRECT(budget_range), 0), "") -> 2 | S34: =IF(is_category, _xlfn.NUMBERVALUE(tracker_rank & budget_rank), "") -> 32 | T34: =IF(is_category, ADDRESS(sort_min_row, COLUMN(combined_rank)) & ":" & ADDRESS(sort_max_row, COLUMN(combined_rank)), "") -> $S$32:$S$36 | U34: =IF(is_category, RANK(combined_rank, INDIRECT(combined_rank_range), 1), "") -> 3 | V34: =IF(is_category, ADDRESS(sort_min_row, COLUMN(combined_rank_norm)) & ":" & ADDRESS(ROW(), COLUMN(combined_rank_norm)), "") -> $U$32:$U$34 | W34: =IF(is_category, combined_rank_norm + COUNTIF(INDIRECT(combined_rank_norm_run_range), combined_rank_norm)-1, "") -> 3 | X34: =IF(is_category, header_row_id + combined_rank_unique, row_id) -> 41 | Y34: =IF(is_empty, "", INDEX($J:$J, MATCH(row_id, $X:$X, 0))) -> Stock Portfolio | Z34: =IF(is_empty, "", IF(is_header, "Tracked", INDEX($K:$K, MATCH(row_id, $X:$X, 0)))) -> 750 | AA34: =IF(is_empty, "", IF(is_header, "Budget", INDEX($L:$L, MATCH(row_id, $X:$X, 0)))) -> 7200 | AB34: =IF(is_empty, "", IF(is_header, "% Compl.", IFERROR(out_tracked / out_budget, "-"))) -> 0.10416667 | AC34: =IF(is_empty, "", IF(is_header, "Remaining", IF(out_budget - out_tracked > 0, out_budget - out_tracked, 0))) -> 6450 | AD34: =IF(is_empty, "", IF(is_header, "Excess", IF(out_budget - out_tracked < 0, out_tracked - out_budget, 0))) -> 0 | AI34: =Calculations!I40 -> Other | AJ34: =Calculations!J40 -> 1150 | AP34: =Calculations!M40 | AQ34: =Calculations!N40
C35: {=IF(C34=-1,-1, IF(C34<income_max_row, C34+1, IF(C34=income_max_row, income_total_row, IF(C34=income_total_row, "/1", IF(C34="/1", expenses_header_row, IF(C34<expenses_max_row, C34+1, IF(C34=expenses_max_row, expenses_total_row, IF(C34=expenses_total_row, "/2", IF(C34="/2", savings_header_row, IF(C34<savings_max_row, C34+1, IF(C34=savings_max_row, savings_total_row, -1)))))))))))} -> 42 | D35: =IF(is_header, row_id, IF(NOT(is_empty), D34, -1)) -> 38 | E35: {=1*OR(row_id=income_header_row, row_id=expenses_header_row, row_id=savings_header_row)} -> 0 | F35: =1*NOT(OR(is_header, is_total, is_empty)) -> 1 | G35: {=1*OR(row_id=income_total_row, row_id=expenses_total_row, row_id=savings_total_row)} -> 0 | H35: =1*OR(row_id="/1", row_id="/2", row_id=-1) -> 0 | I35: {=IFERROR(INDEX('Budget Planning'!$C:$C, header_row_id), "")} -> Savings | J35: {=IFERROR(INDEX('Budget Planning'!$C:$C, row_id), "")} -> Sinking Fund Down Payment | K35: {=IF(OR(is_header, is_empty), "", IF(is_total, IF(selected_period="Total Year", SUM(Tracking[Amount] * (Tracking[Type]=type) * (YEAR(Tracking[Effective Date])=selected_year)), SUM(Tracking[Amount] * (Tracking[Type]=type) * (YEAR(Tracking[Effective Date])=selected_year) * (MONTH(Tracking[Effective Date])=selected_period))), IF(selected_period="Total Year", SUM(Tracking[Amount] * (Tracking[Type]=type) * (Tracking[Category]=item) * (YEAR(Tracking[Effective Date])=selected_year)), SUM(Tracking[Amount] * (Tracking[Type]=type) * (Tracking[Category]=item) * (YEAR(Tracking[Effective Date])=selected_year) * (MONTH(Tracking[Effective Date])=selected_period)))))} -> 0 | L35: {=IF(OR(is_header, is_empty), "", INDEX('Budget Planning'!$E:$EM, row_id, MATCH(IF(selected_period="Total Year", selected_year, DATE(selected_year, selected_period, 1)), 'Budget Planning'!$E$9:$EM$9, 0)))} -> 10200 | M35: {=IF(is_category, IF(header_row_id=income_header_row, MATCH(income_min_row, $C:$C, 0), IF(header_row_id=expenses_header_row, MATCH(expenses_min_row, $C:$C, 0), IF(header_row_id=savings_header_row, MATCH(savings_min_row, $C:$C, 0), ""))), "")} -> 32 | N35: {=IF(is_category, IF(header_row_id=income_header_row, MATCH(income_max_row, $C:$C, 0), IF(header_row_id=expenses_header_row, MATCH(expenses_max_row, $C:$C, 0), IF(header_row_id=savings_header_row, MATCH(savings_max_row, $C:$C, 0), ""))), "")} -> 36 | O35: =IF(is_category, ADDRESS(sort_min_row, COLUMN(tracked)) & ":" & ADDRESS(sort_max_row, COLUMN(tracked)), "") -> $K$32:$K$36 | P35: =IF(is_category, RANK(tracked, INDIRECT(tracked_range), 0), "") -> 5 | Q35: =IF(is_category, ADDRESS(sort_min_row, COLUMN(budget)) & ":" & ADDRESS(sort_max_row, COLUMN(budget)), "") -> $L$32:$L$36 | R35: =IF(is_category, RANK(budget, INDIRECT(budget_range), 0), "") -> 1 | S35: =IF(is_category, _xlfn.NUMBERVALUE(tracker_rank & budget_rank), "") -> 51 | T35: =IF(is_category, ADDRESS(sort_min_row, COLUMN(combined_rank)) & ":" & ADDRESS(sort_max_row, COLUMN(combined_rank)), "") -> $S$32:$S$36 | U35: =IF(is_category, RANK(combined_rank, INDIRECT(combined_rank_range), 1), "") -> 5 | V35: =IF(is_category, ADDRESS(sort_min_row, COLUMN(combined_rank_norm)) & ":" & ADDRESS(ROW(), COLUMN(combined_rank_norm)), "") -> $U$32:$U$35 | W35: =IF(is_category, combined_rank_norm + COUNTIF(INDIRECT(combined_rank_norm_run_range), combined_rank_norm)-1, "") -> 5 | X35: =IF(is_category, header_row_id + combined_rank_unique, row_id) -> 43 | Y35: =IF(is_empty, "", INDEX($J:$J, MATCH(row_id, $X:$X, 0))) -> Sinking Fund Rest | Z35: =IF(is_empty, "", IF(is_header, "Tracked", INDEX($K:$K, MATCH(row_id, $X:$X, 0)))) -> 400 | AA35: =IF(is_empty, "", IF(is_header, "Budget", INDEX($L:$L, MATCH(row_id, $X:$X, 0)))) -> 1200 | AB35: =IF(is_empty, "", IF(is_header, "% Compl.", IFERROR(out_tracked / out_budget, "-"))) -> 0.33333333 | AC35: =IF(is_empty, "", IF(is_header, "Remaining", IF(out_budget - out_tracked > 0, out_budget - out_tracked, 0))) -> 800 | AD35: =IF(is_empty, "", IF(is_header, "Excess", IF(out_budget - out_tracked < 0, out_tracked - out_budget, 0))) -> 0 | AI35: =Calculations!I41 -> Total | AJ35: =Calculations!J41 -> 7890 | AP35: =Calculations!M41 -> Total | AQ35: =Calculations!N41 -> 3090
C36: {=IF(C35=-1,-1, IF(C35<income_max_row, C35+1, IF(C35=income_max_row, income_total_row, IF(C35=income_total_row, "/1", IF(C35="/1", expenses_header_row, IF(C35<expenses_max_row, C35+1, IF(C35=expenses_max_row, expenses_total_row, IF(C35=expenses_total_row, "/2", IF(C35="/2", savings_header_row, IF(C35<savings_max_row, C35+1, IF(C35=savings_max_row, savings_total_row, -1)))))))))))} -> 43 | D36: =IF(is_header, row_id, IF(NOT(is_empty), D35, -1)) -> 38 | E36: {=1*OR(row_id=income_header_row, row_id=expenses_header_row, row_id=savings_header_row)} -> 0 | F36: =1*NOT(OR(is_header, is_total, is_empty)) -> 1 | G36: {=1*OR(row_id=income_total_row, row_id=expenses_total_row, row_id=savings_total_row)} -> 0 | H36: =1*OR(row_id="/1", row_id="/2", row_id=-1) -> 0 | I36: {=IFERROR(INDEX('Budget Planning'!$C:$C, header_row_id), "")} -> Savings | J36: {=IFERROR(INDEX('Budget Planning'!$C:$C, row_id), "")} -> Sinking Fund Rest | K36: {=IF(OR(is_header, is_empty), "", IF(is_total, IF(selected_period="Total Year", SUM(Tracking[Amount] * (Tracking[Type]=type) * (YEAR(Tracking[Effective Date])=selected_year)), SUM(Tracking[Amount] * (Tracking[Type]=type) * (YEAR(Tracking[Effective Date])=selected_year) * (MONTH(Tracking[Effective Date])=selected_period))), IF(selected_period="Total Year", SUM(Tracking[Amount] * (Tracking[Type]=type) * (Tracking[Category]=item) * (YEAR(Tracking[Effective Date])=selected_year)), SUM(Tracking[Amount] * (Tracking[Type]=type) * (Tracking[Category]=item) * (YEAR(Tracking[Effective Date])=selected_year) * (MONTH(Tracking[Effective Date])=selected_period)))))} -> 400 | L36: {=IF(OR(is_header, is_empty), "", INDEX('Budget Planning'!$E:$EM, row_id, MATCH(IF(selected_period="Total Year", selected_year, DATE(selected_year, selected_period, 1)), 'Budget Planning'!$E$9:$EM$9, 0)))} -> 1200 | M36: {=IF(is_category, IF(header_row_id=income_header_row, MATCH(income_min_row, $C:$C, 0), IF(header_row_id=expenses_header_row, MATCH(expenses_min_row, $C:$C, 0), IF(header_row_id=savings_header_row, MATCH(savings_min_row, $C:$C, 0), ""))), "")} -> 32 | N36: {=IF(is_category, IF(header_row_id=income_header_row, MATCH(income_max_row, $C:$C, 0), IF(header_row_id=expenses_header_row, MATCH(expenses_max_row, $C:$C, 0), IF(header_row_id=savings_header_row, MATCH(savings_max_row, $C:$C, 0), ""))), "")} -> 36 | O36: =IF(is_category, ADDRESS(sort_min_row, COLUMN(tracked)) & ":" & ADDRESS(sort_max_row, COLUMN(tracked)), "") -> $K$32:$K$36 | P36: =IF(is_category, RANK(tracked, INDIRECT(tracked_range), 0), "") -> 4 | Q36: =IF(is_category, ADDRESS(sort_min_row, COLUMN(budget)) & ":" & ADDRESS(sort_max_row, COLUMN(budget)), "") -> $L$32:$L$36 | R36: =IF(is_category, RANK(budget, INDIRECT(budget_range), 0), "") -> 5 | S36: =IF(is_category, _xlfn.NUMBERVALUE(tracker_rank & budget_rank), "") -> 45 | T36: =IF(is_category, ADDRESS(sort_min_row, COLUMN(combined_rank)) & ":" & ADDRESS(sort_max_row, COLUMN(combined_rank)), "") -> $S$32:$S$36 | U36: =IF(is_category, RANK(combined_rank, INDIRECT(combined_rank_range), 1), "") -> 4 | V36: =IF(is_category, ADDRESS(sort_min_row, COLUMN(combined_rank_norm)) & ":" & ADDRESS(ROW(), COLUMN(combined_rank_norm)), "") -> $U$32:$U$36 | W36: =IF(is_category, combined_rank_norm + COUNTIF(INDIRECT(combined_rank_norm_run_range), combined_rank_norm)-1, "") -> 4 | X36: =IF(is_category, header_row_id + combined_rank_unique, row_id) -> 42 | Y36: =IF(is_empty, "", INDEX($J:$J, MATCH(row_id, $X:$X, 0))) -> Sinking Fund Down Payment | Z36: =IF(is_empty, "", IF(is_header, "Tracked", INDEX($K:$K, MATCH(row_id, $X:$X, 0)))) -> 0 | AA36: =IF(is_empty, "", IF(is_header, "Budget", INDEX($L:$L, MATCH(row_id, $X:$X, 0)))) -> 10200 | AB36: =IF(is_empty, "", IF(is_header, "% Compl.", IFERROR(out_tracked / out_budget, "-"))) -> 0 | AC36: =IF(is_empty, "", IF(is_header, "Remaining", IF(out_budget - out_tracked > 0, out_budget - out_tracked, 0))) -> 10200 | AD36: =IF(is_empty, "", IF(is_header, "Excess", IF(out_budget - out_tracked < 0, out_tracked - out_budget, 0))) -> 0
C37: {=IF(C36=-1,-1, IF(C36<income_max_row, C36+1, IF(C36=income_max_row, income_total_row, IF(C36=income_total_row, "/1", IF(C36="/1", expenses_header_row, IF(C36<expenses_max_row, C36+1, IF(C36=expenses_max_row, expenses_total_row, IF(C36=expenses_total_row, "/2", IF(C36="/2", savings_header_row, IF(C36<savings_max_row, C36+1, IF(C36=savings_max_row, savings_total_row, -1)))))))))))} -> 49 | D37: =IF(is_header, row_id, IF(NOT(is_empty), D36, -1)) -> 38 | E37: {=1*OR(row_id=income_header_row, row_id=expenses_header_row, row_id=savings_header_row)} -> 0 | F37: =1*NOT(OR(is_header, is_total, is_empty)) -> 0 | G37: {=1*OR(row_id=income_total_row, row_id=expenses_total_row, row_id=savings_total_row)} -> 1 | H37: =1*OR(row_id="/1", row_id="/2", row_id=-1) -> 0 | I37: {=IFERROR(INDEX('Budget Planning'!$C:$C, header_row_id), "")} -> Savings | J37: {=IFERROR(INDEX('Budget Planning'!$C:$C, row_id), "")} -> Total | K37: {=IF(OR(is_header, is_empty), "", IF(is_total, IF(selected_period="Total Year", SUM(Tracking[Amount] * (Tracking[Type]=type) * (YEAR(Tracking[Effective Date])=selected_year)), SUM(Tracking[Amount] * (Tracking[Type]=type) * (YEAR(Tracking[Effective Date])=selected_year) * (MONTH(Tracking[Effective Date])=selected_period))), IF(selected_period="Total Year", SUM(Tracking[Amount] * (Tracking[Type]=type) * (Tracking[Category]=item) * (YEAR(Tracking[Effective Date])=selected_year)), SUM(Tracking[Amount] * (Tracking[Type]=type) * (Tracking[Category]=item) * (YEAR(Tracking[Effective Date])=selected_year) * (MONTH(Tracking[Effective Date])=selected_period)))))} -> 3090 | L37: {=IF(OR(is_header, is_empty), "", INDEX('Budget Planning'!$E:$EM, row_id, MATCH(IF(selected_period="Total Year", selected_year, DATE(selected_year, selected_period, 1)), 'Budget Planning'!$E$9:$EM$9, 0)))} -> 26400 | M37: {=IF(is_category, IF(header_row_id=income_header_row, MATCH(income_min_row, $C:$C, 0), IF(header_row_id=expenses_header_row, MATCH(expenses_min_row, $C:$C, 0), IF(header_row_id=savings_header_row, MATCH(savings_min_row, $C:$C, 0), ""))), "")} | N37: {=IF(is_category, IF(header_row_id=income_header_row, MATCH(income_max_row, $C:$C, 0), IF(header_row_id=expenses_header_row, MATCH(expenses_max_row, $C:$C, 0), IF(header_row_id=savings_header_row, MATCH(savings_max_row, $C:$C, 0), ""))), "")} | O37: =IF(is_category, ADDRESS(sort_min_row, COLUMN(tracked)) & ":" & ADDRESS(sort_max_row, COLUMN(tracked)), "") | P37: =IF(is_category, RANK(tracked, INDIRECT(tracked_range), 0), "") | Q37: =IF(is_category, ADDRESS(sort_min_row, COLUMN(budget)) & ":" & ADDRESS(sort_max_row, COLUMN(budget)), "") | R37: =IF(is_category, RANK(budget, INDIRECT(budget_range), 0), "") | S37: =IF(is_category, _xlfn.NUMBERVALUE(tracker_rank & budget_rank), "") | T37: =IF(is_category, ADDRESS(sort_min_row, COLUMN(combined_rank)) & ":" & ADDRESS(sort_max_row, COLUMN(combined_rank)), "") | U37: =IF(is_category, RANK(combined_rank, INDIRECT(combined_rank_range), 1), "") | V37: =IF(is_category, ADDRESS(sort_min_row, COLUMN(combined_rank_norm)) & ":" & ADDRESS(ROW(), COLUMN(combined_rank_norm)), "") | W37: =IF(is_category, combined_rank_norm + COUNTIF(INDIRECT(combined_rank_norm_run_range), combined_rank_norm)-1, "") | X37: =IF(is_category, header_row_id + combined_rank_unique, row_id) -> 49 | Y37: =IF(is_empty, "", INDEX($J:$J, MATCH(row_id, $X:$X, 0))) -> Total | Z37: =IF(is_empty, "", IF(is_header, "Tracked", INDEX($K:$K, MATCH(row_id, $X:$X, 0)))) -> 3090 | AA37: =IF(is_empty, "", IF(is_header, "Budget", INDEX($L:$L, MATCH(row_id, $X:$X, 0)))) -> 26400 | AB37: =IF(is_empty, "", IF(is_header, "% Compl.", IFERROR(out_tracked / out_budget, "-"))) -> 0.11704545 | AC37: =IF(is_empty, "", IF(is_header, "Remaining", IF(out_budget - out_tracked > 0, out_budget - out_tracked, 0))) -> 23310 | AD37: =IF(is_empty, "", IF(is_header, "Excess", IF(out_budget - out_tracked < 0, out_tracked - out_budget, 0))) -> 0
C38: {=IF(C37=-1,-1, IF(C37<income_max_row, C37+1, IF(C37=income_max_row, income_total_row, IF(C37=income_total_row, "/1", IF(C37="/1", expenses_header_row, IF(C37<expenses_max_row, C37+1, IF(C37=expenses_max_row, expenses_total_row, IF(C37=expenses_total_row, "/2", IF(C37="/2", savings_header_row, IF(C37<savings_max_row, C37+1, IF(C37=savings_max_row, savings_total_row, -1)))))))))))} -> -1 | D38: =IF(is_header, row_id, IF(NOT(is_empty), D37, -1)) -> -1 | E38: {=1*OR(row_id=income_header_row, row_id=expenses_header_row, row_id=savings_header_row)} -> 0 | F38: =1*NOT(OR(is_header, is_total, is_empty)) -> 0 | G38: {=1*OR(row_id=income_total_row, row_id=expenses_total_row, row_id=savings_total_row)} -> 0 | H38: =1*OR(row_id="/1", row_id="/2", row_id=-1) -> 1 | I38: {=IFERROR(INDEX('Budget Planning'!$C:$C, header_row_id), "")} | J38: {=IFERROR(INDEX('Budget Planning'!$C:$C, row_id), "")} | K38: {=IF(OR(is_header, is_empty), "", IF(is_total, IF(selected_period="Total Year", SUM(Tracking[Amount] * (Tracking[Type]=type) * (YEAR(Tracking[Effective Date])=selected_year)), SUM(Tracking[Amount] * (Tracking[Type]=type) * (YEAR(Tracking[Effective Date])=selected_year) * (MONTH(Tracking[Effective Date])=selected_period))), IF(selected_period="Total Year", SUM(Tracking[Amount] * (Tracking[Type]=type) * (Tracking[Category]=item) * (YEAR(Tracking[Effective Date])=selected_year)), SUM(Tracking[Amount] * (Tracking[Type]=type) * (Tracking[Category]=item) * (YEAR(Tracking[Effective Date])=selected_year) * (MONTH(Tracking[Effective Date])=selected_period)))))} | L38: {=IF(OR(is_header, is_empty), "", INDEX('Budget Planning'!$E:$EM, row_id, MATCH(IF(selected_period="Total Year", selected_year, DATE(selected_year, selected_period, 1)), 'Budget Planning'!$E$9:$EM$9, 0)))} | M38: {=IF(is_category, IF(header_row_id=income_header_row, MATCH(income_min_row, $C:$C, 0), IF(header_row_id=expenses_header_row, MATCH(expenses_min_row, $C:$C, 0), IF(header_row_id=savings_header_row, MATCH(savings_min_row, $C:$C, 0), ""))), "")} | N38: {=IF(is_category, IF(header_row_id=income_header_row, MATCH(income_max_row, $C:$C, 0), IF(header_row_id=expenses_header_row, MATCH(expenses_max_row, $C:$C, 0), IF(header_row_id=savings_header_row, MATCH(savings_max_row, $C:$C, 0), ""))), "")} | O38: =IF(is_category, ADDRESS(sort_min_row, COLUMN(tracked)) & ":" & ADDRESS(sort_max_row, COLUMN(tracked)), "") | P38: =IF(is_category, RANK(tracked, INDIRECT(tracked_range), 0), "") | Q38: =IF(is_category, ADDRESS(sort_min_row, COLUMN(budget)) & ":" & ADDRESS(sort_max_row, COLUMN(budget)), "") | R38: =IF(is_category, RANK(budget, INDIRECT(budget_range), 0), "") | S38: =IF(is_category, _xlfn.NUMBERVALUE(tracker_rank & budget_rank), "") | T38: =IF(is_category, ADDRESS(sort_min_row, COLUMN(combined_rank)) & ":" & ADDRESS(sort_max_row, COLUMN(combined_rank)), "") | U38: =IF(is_category, RANK(combined_rank, INDIRECT(combined_rank_range), 1), "") | V38: =IF(is_category, ADDRESS(sort_min_row, COLUMN(combined_rank_norm)) & ":" & ADDRESS(ROW(), COLUMN(combined_rank_norm)), "") | W38: =IF(is_category, combined_rank_norm + COUNTIF(INDIRECT(combined_rank_norm_run_range), combined_rank_norm)-1, "") | X38: =IF(is_category, header_row_id + combined_rank_unique, row_id) -> -1 | Y38: =IF(is_empty, "", INDEX($J:$J, MATCH(row_id, $X:$X, 0))) | Z38: =IF(is_empty, "", IF(is_header, "Tracked", INDEX($K:$K, MATCH(row_id, $X:$X, 0)))) | AA38: =IF(is_empty, "", IF(is_header, "Budget", INDEX($L:$L, MATCH(row_id, $X:$X, 0)))) | AB38: =IF(is_empty, "", IF(is_header, "% Compl.", IFERROR(out_tracked / out_budget, "-"))) | AC38: =IF(is_empty, "", IF(is_header, "Remaining", IF(out_budget - out_tracked > 0, out_budget - out_tracked, 0))) | AD38: =IF(is_empty, "", IF(is_header, "Excess", IF(out_budget - out_tracked < 0, out_tracked - out_budget, 0)))
C39: {=IF(C38=-1,-1, IF(C38<income_max_row, C38+1, IF(C38=income_max_row, income_total_row, IF(C38=income_total_row, "/1", IF(C38="/1", expenses_header_row, IF(C38<expenses_max_row, C38+1, IF(C38=expenses_max_row, expenses_total_row, IF(C38=expenses_total_row, "/2", IF(C38="/2", savings_header_row, IF(C38<savings_max_row, C38+1, IF(C38=savings_max_row, savings_total_row, -1)))))))))))} -> -1 | D39: =IF(is_header, row_id, IF(NOT(is_empty), D38, -1)) -> -1 | E39: {=1*OR(row_id=income_header_row, row_id=expenses_header_row, row_id=savings_header_row)} -> 0 | F39: =1*NOT(OR(is_header, is_total, is_empty)) -> 0 | G39: {=1*OR(row_id=income_total_row, row_id=expenses_total_row, row_id=savings_total_row)} -> 0 | H39: =1*OR(row_id="/1", row_id="/2", row_id=-1) -> 1 | I39: {=IFERROR(INDEX('Budget Planning'!$C:$C, header_row_id), "")} | J39: {=IFERROR(INDEX('Budget Planning'!$C:$C, row_id), "")} | K39: {=IF(OR(is_header, is_empty), "", IF(is_total, IF(selected_period="Total Year", SUM(Tracking[Amount] * (Tracking[Type]=type) * (YEAR(Tracking[Effective Date])=selected_year)), SUM(Tracking[Amount] * (Tracking[Type]=type) * (YEAR(Tracking[Effective Date])=selected_year) * (MONTH(Tracking[Effective Date])=selected_period))), IF(selected_period="Total Year", SUM(Tracking[Amount] * (Tracking[Type]=type) * (Tracking[Category]=item) * (YEAR(Tracking[Effective Date])=selected_year)), SUM(Tracking[Amount] * (Tracking[Type]=type) * (Tracking[Category]=item) * (YEAR(Tracking[Effective Date])=selected_year) * (MONTH(Tracking[Effective Date])=selected_period)))))} | L39: {=IF(OR(is_header, is_empty), "", INDEX('Budget Planning'!$E:$EM, row_id, MATCH(IF(selected_period="Total Year", selected_year, DATE(selected_year, selected_period, 1)), 'Budget Planning'!$E$9:$EM$9, 0)))} | M39: {=IF(is_category, IF(header_row_id=income_header_row, MATCH(income_min_row, $C:$C, 0), IF(header_row_id=expenses_header_row, MATCH(expenses_min_row, $C:$C, 0), IF(header_row_id=savings_header_row, MATCH(savings_min_row, $C:$C, 0), ""))), "")} | N39: {=IF(is_category, IF(header_row_id=income_header_row, MATCH(income_max_row, $C:$C, 0), IF(header_row_id=expenses_header_row, MATCH(expenses_max_row, $C:$C, 0), IF(header_row_id=savings_header_row, MATCH(savings_max_row, $C:$C, 0), ""))), "")} | O39: =IF(is_category, ADDRESS(sort_min_row, COLUMN(tracked)) & ":" & ADDRESS(sort_max_row, COLUMN(tracked)), "") | P39: =IF(is_category, RANK(tracked, INDIRECT(tracked_range), 0), "") | Q39: =IF(is_category, ADDRESS(sort_min_row, COLUMN(budget)) & ":" & ADDRESS(sort_max_row, COLUMN(budget)), "") | R39: =IF(is_category, RANK(budget, INDIRECT(budget_range), 0), "") | S39: =IF(is_category, _xlfn.NUMBERVALUE(tracker_rank & budget_rank), "") | T39: =IF(is_category, ADDRESS(sort_min_row, COLUMN(combined_rank)) & ":" & ADDRESS(sort_max_row, COLUMN(combined_rank)), "") | U39: =IF(is_category, RANK(combined_rank, INDIRECT(combined_rank_range), 1), "") | V39: =IF(is_category, ADDRESS(sort_min_row, COLUMN(combined_rank_norm)) & ":" & ADDRESS(ROW(), COLUMN(combined_rank_norm)), "") | W39: =IF(is_category, combined_rank_norm + COUNTIF(INDIRECT(combined_rank_norm_run_range), combined_rank_norm)-1, "") | X39: =IF(is_category, header_row_id + combined_rank_unique, row_id) -> -1 | Y39: =IF(is_empty, "", INDEX($J:$J, MATCH(row_id, $X:$X, 0))) | Z39: =IF(is_empty, "", IF(is_header, "Tracked", INDEX($K:$K, MATCH(row_id, $X:$X, 0)))) | AA39: =IF(is_empty, "", IF(is_header, "Budget", INDEX($L:$L, MATCH(row_id, $X:$X, 0)))) | AB39: =IF(is_empty, "", IF(is_header, "% Compl.", IFERROR(out_tracked / out_budget, "-"))) | AC39: =IF(is_empty, "", IF(is_header, "Remaining", IF(out_budget - out_tracked > 0, out_budget - out_tracked, 0))) | AD39: =IF(is_empty, "", IF(is_header, "Excess", IF(out_budget - out_tracked < 0, out_tracked - out_budget, 0)))
C40: {=IF(C39=-1,-1, IF(C39<income_max_row, C39+1, IF(C39=income_max_row, income_total_row, IF(C39=income_total_row, "/1", IF(C39="/1", expenses_header_row, IF(C39<expenses_max_row, C39+1, IF(C39=expenses_max_row, expenses_total_row, IF(C39=expenses_total_row, "/2", IF(C39="/2", savings_header_row, IF(C39<savings_max_row, C39+1, IF(C39=savings_max_row, savings_total_row, -1)))))))))))} -> -1 | D40: =IF(is_header, row_id, IF(NOT(is_empty), D39, -1)) -> -1 | E40: {=1*OR(row_id=income_header_row, row_id=expenses_header_row, row_id=savings_header_row)} -> 0 | F40: =1*NOT(OR(is_header, is_total, is_empty)) -> 0 | G40: {=1*OR(row_id=income_total_row, row_id=expenses_total_row, row_id=savings_total_row)} -> 0 | H40: =1*OR(row_id="/1", row_id="/2", row_id=-1) -> 1 | I40: {=IFERROR(INDEX('Budget Planning'!$C:$C, header_row_id), "")} | J40: {=IFERROR(INDEX('Budget Planning'!$C:$C, row_id), "")} | K40: {=IF(OR(is_header, is_empty), "", IF(is_total, IF(selected_period="Total Year", SUM(Tracking[Amount] * (Tracking[Type]=type) * (YEAR(Tracking[Effective Date])=selected_year)), SUM(Tracking[Amount] * (Tracking[Type]=type) * (YEAR(Tracking[Effective Date])=selected_year) * (MONTH(Tracking[Effective Date])=selected_period))), IF(selected_period="Total Year", SUM(Tracking[Amount] * (Tracking[Type]=type) * (Tracking[Category]=item) * (YEAR(Tracking[Effective Date])=selected_year)), SUM(Tracking[Amount] * (Tracking[Type]=type) * (Tracking[Category]=item) * (YEAR(Tracking[Effective Date])=selected_year) * (MONTH(Tracking[Effective Date])=selected_period)))))} | L40: {=IF(OR(is_header, is_empty), "", INDEX('Budget Planning'!$E:$EM, row_id, MATCH(IF(selected_period="Total Year", selected_year, DATE(selected_year, selected_period, 1)), 'Budget Planning'!$E$9:$EM$9, 0)))} | M40: {=IF(is_category, IF(header_row_id=income_header_row, MATCH(income_min_row, $C:$C, 0), IF(header_row_id=expenses_header_row, MATCH(expenses_min_row, $C:$C, 0), IF(header_row_id=savings_header_row, MATCH(savings_min_row, $C:$C, 0), ""))), "")} | N40: {=IF(is_category, IF(header_row_id=income_header_row, MATCH(income_max_row, $C:$C, 0), IF(header_row_id=expenses_header_row, MATCH(expenses_max_row, $C:$C, 0), IF(header_row_id=savings_header_row, MATCH(savings_max_row, $C:$C, 0), ""))), "")} | O40: =IF(is_category, ADDRESS(sort_min_row, COLUMN(tracked)) & ":" & ADDRESS(sort_max_row, COLUMN(tracked)), "") | P40: =IF(is_category, RANK(tracked, INDIRECT(tracked_range), 0), "") | Q40: =IF(is_category, ADDRESS(sort_min_row, COLUMN(budget)) & ":" & ADDRESS(sort_max_row, COLUMN(budget)), "") | R40: =IF(is_category, RANK(budget, INDIRECT(budget_range), 0), "") | S40: =IF(is_category, _xlfn.NUMBERVALUE(tracker_rank & budget_rank), "") | T40: =IF(is_category, ADDRESS(sort_min_row, COLUMN(combined_rank)) & ":" & ADDRESS(sort_max_row, COLUMN(combined_rank)), "") | U40: =IF(is_category, RANK(combined_rank, INDIRECT(combined_rank_range), 1), "") | V40: =IF(is_category, ADDRESS(sort_min_row, COLUMN(combined_rank_norm)) & ":" & ADDRESS(ROW(), COLUMN(combined_rank_norm)), "") | W40: =IF(is_category, combined_rank_norm + COUNTIF(INDIRECT(combined_rank_norm_run_range), combined_rank_norm)-1, "") | X40: =IF(is_category, header_row_id + combined_rank_unique, row_id) -> -1 | Y40: =IF(is_empty, "", INDEX($J:$J, MATCH(row_id, $X:$X, 0))) | Z40: =IF(is_empty, "", IF(is_header, "Tracked", INDEX($K:$K, MATCH(row_id, $X:$X, 0)))) | AA40: =IF(is_empty, "", IF(is_header, "Budget", INDEX($L:$L, MATCH(row_id, $X:$X, 0)))) | AB40: =IF(is_empty, "", IF(is_header, "% Compl.", IFERROR(out_tracked / out_budget, "-"))) | AC40: =IF(is_empty, "", IF(is_header, "Remaining", IF(out_budget - out_tracked > 0, out_budget - out_tracked, 0))) | AD40: =IF(is_empty, "", IF(is_header, "Excess", IF(out_budget - out_tracked < 0, out_tracked - out_budget, 0)))
C41: {=IF(C40=-1,-1, IF(C40<income_max_row, C40+1, IF(C40=income_max_row, income_total_row, IF(C40=income_total_row, "/1", IF(C40="/1", expenses_header_row, IF(C40<expenses_max_row, C40+1, IF(C40=expenses_max_row, expenses_total_row, IF(C40=expenses_total_row, "/2", IF(C40="/2", savings_header_row, IF(C40<savings_max_row, C40+1, IF(C40=savings_max_row, savings_total_row, -1)))))))))))} -> -1 | D41: =IF(is_header, row_id, IF(NOT(is_empty), D40, -1)) -> -1 | E41: {=1*OR(row_id=income_header_row, row_id=expenses_header_row, row_id=savings_header_row)} -> 0 | F41: =1*NOT(OR(is_header, is_total, is_empty)) -> 0 | G41: {=1*OR(row_id=income_total_row, row_id=expenses_total_row, row_id=savings_total_row)} -> 0 | H41: =1*OR(row_id="/1", row_id="/2", row_id=-1) -> 1 | I41: {=IFERROR(INDEX('Budget Planning'!$C:$C, header_row_id), "")} | J41: {=IFERROR(INDEX('Budget Planning'!$C:$C, row_id), "")} | K41: {=IF(OR(is_header, is_empty), "", IF(is_total, IF(selected_period="Total Year", SUM(Tracking[Amount] * (Tracking[Type]=type) * (YEAR(Tracking[Effective Date])=selected_year)), SUM(Tracking[Amount] * (Tracking[Type]=type) * (YEAR(Tracking[Effective Date])=selected_year) * (MONTH(Tracking[Effective Date])=selected_period))), IF(selected_period="Total Year", SUM(Tracking[Amount] * (Tracking[Type]=type) * (Tracking[Category]=item) * (YEAR(Tracking[Effective Date])=selected_year)), SUM(Tracking[Amount] * (Tracking[Type]=type) * (Tracking[Category]=item) * (YEAR(Tracking[Effective Date])=selected_year) * (MONTH(Tracking[Effective Date])=selected_period)))))} | L41: {=IF(OR(is_header, is_empty), "", INDEX('Budget Planning'!$E:$EM, row_id, MATCH(IF(selected_period="Total Year", selected_year, DATE(selected_year, selected_period, 1)), 'Budget Planning'!$E$9:$EM$9, 0)))} | M41: {=IF(is_category, IF(header_row_id=income_header_row, MATCH(income_min_row, $C:$C, 0), IF(header_row_id=expenses_header_row, MATCH(expenses_min_row, $C:$C, 0), IF(header_row_id=savings_header_row, MATCH(savings_min_row, $C:$C, 0), ""))), "")} | N41: {=IF(is_category, IF(header_row_id=income_header_row, MATCH(income_max_row, $C:$C, 0), IF(header_row_id=expenses_header_row, MATCH(expenses_max_row, $C:$C, 0), IF(header_row_id=savings_header_row, MATCH(savings_max_row, $C:$C, 0), ""))), "")} | O41: =IF(is_category, ADDRESS(sort_min_row, COLUMN(tracked)) & ":" & ADDRESS(sort_max_row, COLUMN(tracked)), "") | P41: =IF(is_category, RANK(tracked, INDIRECT(tracked_range), 0), "") | Q41: =IF(is_category, ADDRESS(sort_min_row, COLUMN(budget)) & ":" & ADDRESS(sort_max_row, COLUMN(budget)), "") | R41: =IF(is_category, RANK(budget, INDIRECT(budget_range), 0), "") | S41: =IF(is_category, _xlfn.NUMBERVALUE(tracker_rank & budget_rank), "") | T41: =IF(is_category, ADDRESS(sort_min_row, COLUMN(combined_rank)) & ":" & ADDRESS(sort_max_row, COLUMN(combined_rank)), "") | U41: =IF(is_category, RANK(combined_rank, INDIRECT(combined_rank_range), 1), "") | V41: =IF(is_category, ADDRESS(sort_min_row, COLUMN(combined_rank_norm)) & ":" & ADDRESS(ROW(), COLUMN(combined_rank_norm)), "") | W41: =IF(is_category, combined_rank_norm + COUNTIF(INDIRECT(combined_rank_norm_run_range), combined_rank_norm)-1, "") | X41: =IF(is_category, header_row_id + combined_rank_unique, row_id) -> -1 | Y41: =IF(is_empty, "", INDEX($J:$J, MATCH(row_id, $X:$X, 0))) | Z41: =IF(is_empty, "", IF(is_header, "Tracked", INDEX($K:$K, MATCH(row_id, $X:$X, 0)))) | AA41: =IF(is_empty, "", IF(is_header, "Budget", INDEX($L:$L, MATCH(row_id, $X:$X, 0)))) | AB41: =IF(is_empty, "", IF(is_header, "% Compl.", IFERROR(out_tracked / out_budget, "-"))) | AC41: =IF(is_empty, "", IF(is_header, "Remaining", IF(out_budget - out_tracked > 0, out_budget - out_tracked, 0))) | AD41: =IF(is_empty, "", IF(is_header, "Excess", IF(out_budget - out_tracked < 0, out_tracked - out_budget, 0)))
C42: {=IF(C41=-1,-1, IF(C41<income_max_row, C41+1, IF(C41=income_max_row, income_total_row, IF(C41=income_total_row, "/1", IF(C41="/1", expenses_header_row, IF(C41<expenses_max_row, C41+1, IF(C41=expenses_max_row, expenses_total_row, IF(C41=expenses_total_row, "/2", IF(C41="/2", savings_header_row, IF(C41<savings_max_row, C41+1, IF(C41=savings_max_row, savings_total_row, -1)))))))))))} -> -1 | D42: =IF(is_header, row_id, IF(NOT(is_empty), D41, -1)) -> -1 | E42: {=1*OR(row_id=income_header_row, row_id=expenses_header_row, row_id=savings_header_row)} -> 0 | F42: =1*NOT(OR(is_header, is_total, is_empty)) -> 0 | G42: {=1*OR(row_id=income_total_row, row_id=expenses_total_row, row_id=savings_total_row)} -> 0 | H42: =1*OR(row_id="/1", row_id="/2", row_id=-1) -> 1 | I42: {=IFERROR(INDEX('Budget Planning'!$C:$C, header_row_id), "")} | J42: {=IFERROR(INDEX('Budget Planning'!$C:$C, row_id), "")} | K42: {=IF(OR(is_header, is_empty), "", IF(is_total, IF(selected_period="Total Year", SUM(Tracking[Amount] * (Tracking[Type]=type) * (YEAR(Tracking[Effective Date])=selected_year)), SUM(Tracking[Amount] * (Tracking[Type]=type) * (YEAR(Tracking[Effective Date])=selected_year) * (MONTH(Tracking[Effective Date])=selected_period))), IF(selected_period="Total Year", SUM(Tracking[Amount] * (Tracking[Type]=type) * (Tracking[Category]=item) * (YEAR(Tracking[Effective Date])=selected_year)), SUM(Tracking[Amount] * (Tracking[Type]=type) * (Tracking[Category]=item) * (YEAR(Tracking[Effective Date])=selected_year) * (MONTH(Tracking[Effective Date])=selected_period)))))} | L42: {=IF(OR(is_header, is_empty), "", INDEX('Budget Planning'!$E:$EM, row_id, MATCH(IF(selected_period="Total Year", selected_year, DATE(selected_year, selected_period, 1)), 'Budget Planning'!$E$9:$EM$9, 0)))} | M42: {=IF(is_category, IF(header_row_id=income_header_row, MATCH(income_min_row, $C:$C, 0), IF(header_row_id=expenses_header_row, MATCH(expenses_min_row, $C:$C, 0), IF(header_row_id=savings_header_row, MATCH(savings_min_row, $C:$C, 0), ""))), "")} | N42: {=IF(is_category, IF(header_row_id=income_header_row, MATCH(income_max_row, $C:$C, 0), IF(header_row_id=expenses_header_row, MATCH(expenses_max_row, $C:$C, 0), IF(header_row_id=savings_header_row, MATCH(savings_max_row, $C:$C, 0), ""))), "")} | O42: =IF(is_category, ADDRESS(sort_min_row, COLUMN(tracked)) & ":" & ADDRESS(sort_max_row, COLUMN(tracked)), "") | P42: =IF(is_category, RANK(tracked, INDIRECT(tracked_range), 0), "") | Q42: =IF(is_category, ADDRESS(sort_min_row, COLUMN(budget)) & ":" & ADDRESS(sort_max_row, COLUMN(budget)), "") | R42: =IF(is_category, RANK(budget, INDIRECT(budget_range), 0), "") | S42: =IF(is_category, _xlfn.NUMBERVALUE(tracker_rank & budget_rank), "") | T42: =IF(is_category, ADDRESS(sort_min_row, COLUMN(combined_rank)) & ":" & ADDRESS(sort_max_row, COLUMN(combined_rank)), "") | U42: =IF(is_category, RANK(combined_rank, INDIRECT(combined_rank_range), 1), "") | V42: =IF(is_category, ADDRESS(sort_min_row, COLUMN(combined_rank_norm)) & ":" & ADDRESS(ROW(), COLUMN(combined_rank_norm)), "") | W42: =IF(is_category, combined_rank_norm + COUNTIF(INDIRECT(combined_rank_norm_run_range), combined_rank_norm)-1, "") | X42: =IF(is_category, header_row_id + combined_rank_unique, row_id) -> -1 | Y42: =IF(is_empty, "", INDEX($J:$J, MATCH(row_id, $X:$X, 0))) | Z42: =IF(is_empty, "", IF(is_header, "Tracked", INDEX($K:$K, MATCH(row_id, $X:$X, 0)))) | AA42: =IF(is_empty, "", IF(is_header, "Budget", INDEX($L:$L, MATCH(row_id, $X:$X, 0)))) | AB42: =IF(is_empty, "", IF(is_header, "% Compl.", IFERROR(out_tracked / out_budget, "-"))) | AC42: =IF(is_empty, "", IF(is_header, "Remaining", IF(out_budget - out_tracked > 0, out_budget - out_tracked, 0))) | AD42: =IF(is_empty, "", IF(is_header, "Excess", IF(out_budget - out_tracked < 0, out_tracked - out_budget, 0)))
